Workbook

Sheet How to use this template.
A1: How to use this template.
A3: Before you start making any changes to this spreadsheet for your company's specific data, you should look at the template as it is and UNDERSTAND how it works and why things are done the way they are.
A8: There are several notes in the spreadsheet, you should read these ALL. They are designed to help you understand how/why things are linked the way they are. Some contain instructions for you to follow.
A13: Any yellow box you should input something. The orange boxes are calculated. The orange cells are not locked. This is because this template is designed for the most common businesses we have seen in the competition. Specific companies may have to do something other than what has been designed in the template. But make sure that you are certain you want to make a change before you do.
A20: The template was designed to handle up to three different revenue streams. If you have more than this, you will have to adapt the spreadsheet for additional income streams. If you have less than three revenue streams you can hide/delete these rows in the financial statements. If you decide to hide lines, just make sure you have entered a $0 on the assumptions tab.
A26: The expenses given on the Income Statement Assumptions tab are very common expenses. You can change the names of them if you want on the Assumptions tab. The expenses on the Assumptions tab are linked directly to the Income Statement. So if you change them on the assumptions page it will automatically correct it on the financial statements. Again if you do not have all of the expenses, you can hide/delete them from the Income Statement. DO NOT DELETE THEM ON THE ASSUMPTIONS TAB. If you decide to hide lines, just make sure you have entered a $0 on the assumptions tab.
A35: The input numbers in this template are completely absurd numbers. Do not assume that they are correct. You should change pretty much every number in yellow.

Sheet Income Statement Assumptions
A1: Sales:
A2: Product 1 sale via web
B3: Year 1
B4: January | C4: February | D4: March | E4: April | F4: May | G4: June | H4: July | I4: August | J4: September | K4: October | L4: November | M4: December | N4: Total
A5: Price per Unit | B5: 20 | C5: 20 | D5: 20 | E5: 20 | F5: 20 | G5: 20 | H5: 20 | I5: 20 | J5: 20 | K5: 20 | L5: 20 | M5: 20
A6: Units Sold | B6: 0 | C6: 0 | D6: 0 | E6: 0 | F6: 0 | G6: 0 | H6: 100 | I6: 150 | J6: 250 | K6: 300 | L6: 400 | M6: 500 | N6: =SUM(B6:M6) -> 1700
B8: Year 2
B9: January | C9: February | D9: March | E9: April | F9: May | G9: June | H9: July | I9: August | J9: September | K9: October | L9: November | M9: December | N9: Total
A10: Price per Unit | B10: 20 | C10: 20 | D10: 20 | E10: 20 | F10: 20 | G10: 20 | H10: 20 | I10: 20 | J10: 20 | K10: 20 | L10: 20 | M10: 20
A11: Units Sold | B11: =ROUND(M6*(1+D29),0) -> 563 | C11: =ROUND(B11*(1+$D$29),0) -> 633 | D11: =ROUND(C11*(1+$D$29),0) -> 712 | E11: =ROUND(D11*(1+$D$29),0) -> 801 | F11: =ROUND(E11*(1+$D$29),0) -> 901 | G11: =ROUND(F11*(1+$D$29),0) -> 1014 | H11: =ROUND(G11*(1+$D$29),0) -> 1141 | I11: =ROUND(H11*(1+$D$29),0) -> 1284 | J11: =ROUND(I11*(1+$D$29),0) -> 1445 | ... M11: =ROUND(L11*(1+$D$29),0) -> 2058 | N11: =SUM(B11:M11) -> 14007
B13: Year 3
D14: Quarter 1 | G14: Quarter 2 | J14: Quarter 3 | M14: Quarter 4 | N14: Total
A15: Price per Unit | D15: 22 | G15: 22 | J15: 22 | M15: 22
A16: Units Sold | D16: =ROUND((K11+L11+M11)*(1+D30),0) -> 6891 | G16: =ROUND(D16*(1+D30),0) -> 8614 | J16: =ROUND(G16*(1+D30),0) -> 10768 | M16: =ROUND(J16*(1+D30),0) -> 13460 | N16: =SUM(B16:M16) -> 39733
B18: Year 4
D19: Quarter 1 | G19: Quarter 2 | J19: Quarter 3 | M19: Quarter 4 | N19: Total
A20: Price per Unit | D20: 24 | G20: 24 | J20: 24 | M20: 24
A21: Units Sold | D21: =ROUND((M16)*(1+D31),0) -> 15479 | G21: =ROUND(D21*(1+D31),0) -> 17801 | J21: =ROUND(G21*(1+D31),0) -> 20471 | M21: =ROUND(J21*(1+D31),0) -> 23542 | N21: =SUM(B21:M21) -> 77293
B23: Year 5
N24: Total
A25: Price per Unit | M25: 25
A26: Units Sold | N26: =ROUND(N21*(1+D32),0) -> 100481
B28: Annual Rate | D28: Periodic Rate
A29: Year 2 Percentage Sales Growth | B29: 1.5 | D29: =B29/12 -> 0.125
A30: Year 3 Percentage Sales Growth | B30: 1 | D30: =B30/4 -> 0.25
A31: Year 4 Percentage Sales Growth | B31: 0.6 | D31: =B31/4 -> 0.15
A32: Year 5 Percentage Sales Growth | B32: 0.3 | D32: =B32 -> 0.3
A34: Product 2 Sale via Retailer
B35: Year 1
B36: January | C36: February | D36: March | E36: April | F36: May | G36: June | H36: July | I36: August | J36: September | K36: October | L36: November | M36: December | N36: Total
A37: Price per Unit | B37: 10 | C37: 10 | D37: 10 | E37: 10 | F37: 10 | G37: 10 | H37: 10 | I37: 10 | J37: 10 | K37: 10 | L37: 10 | M37: 10
A38: Units Sold | B38: 0 | C38: 0 | D38: 0 | E38: 0 | F38: 0 | G38: 0 | H38: 2000 | I38: 2000 | J38: 2500 | K38: 3000 | L38: 3000 | M38: 3500 | N38: =SUM(B38:M38) -> 16000
B40: Year 2
B41: January | C41: February | D41: March | E41: April | F41: May | G41: June | H41: July | I41: August | J41: September | K41: October | L41: November | M41: December | N41: Total
A42: Price per Unit | B42: 10 | C42: 10 | D42: 10 | E42: 10 | F42: 10 | G42: 10 | H42: 10 | I42: 10 | J42: 10 | K42: 10 | L42: 10 | M42: 10
A43: Units Sold | B43: =ROUND(M38*(1+D61),0) -> 3938 | C43: =ROUND(B43*(1+$D$29),0) -> 4430 | D43: =ROUND(C43*(1+$D$29),0) -> 4984 | E43: =ROUND(D43*(1+$D$29),0) -> 5607 | F43: =ROUND(E43*(1+$D$29),0) -> 6308 | G43: =ROUND(F43*(1+$D$29),0) -> 7097 | H43: =ROUND(G43*(1+$D$29),0) -> 7984 | I43: =ROUND(H43*(1+$D$29),0) -> 8982 | J43: =ROUND(I43*(1+$D$29),0) -> 10105 | ... M43: =ROUND(L43*(1+$D$29),0) -> 14388 | N43: =SUM(B43:M43) -> 97980
B45: Year 3
D46: Quarter 1 | G46: Quarter 2 | J46: Quarter 3 | M46: Quarter 4 | N46: Total
A47: Price per Unit | D47: 11 | G47: 11 | J47: 11 | M47: 11
A48: Units Sold | D48: =ROUND((K43+L43+M43)*(1+D62),0) -> 48181 | G48: =ROUND(D48*(1+D62),0) -> 60226 | J48: =ROUND(G48*(1+D62),0) -> 75283 | M48: =ROUND(J48*(1+D62),0) -> 94104 | N48: =SUM(B48:M48) -> 277794
B50: Year 4
D51: Quarter 1 | G51: Quarter 2 | J51: Quarter 3 | M51: Quarter 4 | N51: Total
A52: Price per Unit | D52: 12 | G52: 12 | J52: 12 | M52: 12
A53: Units Sold | D53: =ROUND((M48)*(1+D63),0) -> 108220 | G53: =ROUND(D53*(1+D63),0) -> 124453 | J53: =ROUND(G53*(1+D63),0) -> 143121 | M53: =ROUND(J53*(1+D63),0) -> 164589 | N53: =SUM(B53:M53) -> 540383
B55: Year 5
N56: Total
A57: Price per Unit | M57: 12.5
A58: Units Sold | N58: =ROUND(N53*(1+D64),0) -> 702498
B60: Annual Rate | D60: Periodic Rate
A61: Year 2 Percentage Sales Growth | B61: 1.5 | D61: =B61/12 -> 0.125
A62: Year 3 Percentage Sales Growth | B62: 1 | D62: =B62/4 -> 0.25
A63: Year 4 Percentage Sales Growth | B63: 0.6 | D63: =B63/4 -> 0.15
A64: Year 5 Percentage Sales Growth | B64: 0.3 | D64: =B64 -> 0.3
A66: Product 3 Service plan
B67: Year 1
B68: January | C68: February | D68: March | E68: April | F68: May | G68: June | H68: July | I68: August | J68: September | K68: October | L68: November | M68: December | N68: Total
A69: Price per Unit | B69: 2 | C69: 2 | D69: 2 | E69: 2 | F69: 2 | G69: 2 | H69: 2 | I69: 2 | J69: 2 | K69: 2 | L69: 2 | M69: 2
A70: Units Sold | B70: 0 | C70: 0 | D70: 0 | E70: 0 | F70: 0 | G70: 0 | H70: 1050 | I70: 1075 | J70: 1500 | K70: 1650 | L70: 1700 | M70: 2000 | N70: =SUM(B70:M70) -> 8975
B72: Year 2
B73: January | C73: February | D73: March | E73: April | F73: May | G73: June | H73: July | I73: August | J73: September | K73: October | L73: November | M73: December | N73: Total
A74: Price per Unit | B74: 2 | C74: 2 | D74: 2 | E74: 2 | F74: 2 | G74: 2 | H74: 2 | I74: 2 | J74: 2 | K74: 2 | L74: 2 | M74: 2
A75: Units Sold | B75: =ROUND(M70*(1+D93),0) -> 2250 | C75: =ROUND(B75*(1+$D$29),0) -> 2531 | D75: =ROUND(C75*(1+$D$29),0) -> 2847 | E75: =ROUND(D75*(1+$D$29),0) -> 3203 | F75: =ROUND(E75*(1+$D$29),0) -> 3603 | G75: =ROUND(F75*(1+$D$29),0) -> 4053 | H75: =ROUND(G75*(1+$D$29),0) -> 4560 | I75: =ROUND(H75*(1+$D$29),0) -> 5130 | J75: =ROUND(I75*(1+$D$29),0) -> 5771 | ... M75: =ROUND(L75*(1+$D$29),0) -> 8217 | N75: =SUM(B75:M75) -> 55961
B77: Year 3
D78: Quarter 1 | G78: Quarter 2 | J78: Quarter 3 | M78: Quarter 4 | N78: Total
A79: Price per Unit | D79: 2 | G79: 2 | J79: 2 | M79: 2
A80: Units Sold | D80: =ROUND((K75+L75+M75)*(1+D94),0) -> 27516 | G80: =ROUND(D80*(1+D94),0) -> 34395 | J80: =ROUND(G80*(1+D94),0) -> 42994 | M80: =ROUND(J80*(1+D94),0) -> 53743 | N80: =SUM(B80:M80) -> 158648
B82: Year 4
D83: Quarter 1 | G83: Quarter 2 | J83: Quarter 3 | M83: Quarter 4 | N83: Total
A84: Price per Unit | D84: 2 | G84: 2 | J84: 2 | M84: 2
A85: Units Sold | D85: =ROUND((M80)*(1+D95),0) -> 61804 | G85: =ROUND(D85*(1+D95),0) -> 71075 | J85: =ROUND(G85*(1+D95),0) -> 81736 | M85: =ROUND(J85*(1+D95),0) -> 93996 | N85: =SUM(B85:M85) -> 308611
B87: Year 5
N88: Total
A89: Price per Unit | M89: 2
A90: Units Sold | N90: =ROUND(N85*(1+D96),0) -> 401194
B92: Annual Rate | D92: Periodic Rate
A93: Year 2 Percentage Sales Growth | B93: 1.5 | D93: =B93/12 -> 0.125
A94: Year 3 Percentage Sales Growth | B94: 1 | D94: =B94/4 -> 0.25
A95: Year 4 Percentage Sales Growth | B95: 0.6 | D95: =B95/4 -> 0.15
A96: Year 5 Percentage Sales Growth | B96: 0.3 | D96: =B96 -> 0.3
A99: Costs of Goods Sold | F99: Year 2 | G99: Year 3 | H99: Year 4 | I99: Year 5
A100: Product 1 Internet sale | B100: Cost per Unit | D100: Annual Increase | F100: Periodic Rate | G100: Periodic Rate | H100: Periodic Rate | I100: Periodic Rate
A101: outsourced product | B101: 5.25 | D101: 0.02 | F101: =D101/12 -> 0.0016666667 | G101: =D101/4 -> 0.005 | H101: =D101/4 -> 0.005 | I101: =D101 -> 0.02
A102: 3PL | B102: 0.75 | D102: 0.02 | F102: =D102/12 -> 0.0016666667 | G102: =D102/4 -> 0.005 | H102: =D102/4 -> 0.005 | I102: =D102 -> 0.02
A103: CC fee | B103: =B5*0.03 -> 0.6 | D103: 0.02 | F103: =D103/12 -> 0.0016666667 | G103: =D103/4 -> 0.005 | H103: =D103/4 -> 0.005 | I103: =D103 -> 0.02
A104: warranty | B104: 0.15 | D104: 0.05 | F104: =D104/12 -> 0.0041666667 | G104: =D104/4 -> 0.0125 | H104: =D104/4 -> 0.0125 | I104: =D104 -> 0.05
A106: Product 2 via retailer | B106: Cost per Unit | D106: Annual Increase | F106: Periodic Rate | G106: Periodic Rate | H106: Periodic Rate | I106: Periodic Rate
A107: Outsourced product | B107: 5.25 | D107: 0.02 | F107: =D107/12 -> 0.0016666667 | G107: =D107/4 -> 0.005 | H107: =D107/4 -> 0.005 | I107: =D107 -> 0.02
A108: 3PL | B108: 0.75 | D108: 0.02 | F108: =D108/12 -> 0.0016666667 | G108: =D108/4 -> 0.005 | H108: =D108/4 -> 0.005 | I108: =D108 -> 0.02
A109: CC fee | D109: 0.02 | F109: =D109/12 -> 0.0016666667 | G109: =D109/4 -> 0.005 | H109: =D109/4 -> 0.005 | I109: =D109 -> 0.02
A110: warranty | B110: 0.15 | D110: 0.05 | F110: =D110/12 -> 0.0041666667 | G110: =D110/4 -> 0.0125 | H110: =D110/4 -> 0.0125 | I110: =D110 -> 0.05
A112: Product 3 service plan | B112: Cost per Unit | D112: Annual Increase | F112: Periodic Rate | G112: Periodic Rate | H112: Periodic Rate | I112: Periodic Rate
A113: repair labor | B113: 0.2 | D113: 0.1 | F113: =D113/12 -> 0.0083333333 | G113: =D113/4 -> 0.025 | H113: =D113/4 -> 0.025 | I113: =D113 -> 0.1
A114: shipping | B114: 0.1 | D114: 0.05 | F114: =D114/12 -> 0.0041666667 | G114: =D114/4 -> 0.0125 | H114: =D114/4 -> 0.0125 | I114: =D114 -> 0.05
B115: 0 | D115: 0 | F115: =D115/12 -> 0 | G115: =D115/4 -> 0 | H115: =D115/4 -> 0 | I115: =D115 -> 0
B116: 0 | D116: 0 | F116: =D116/12 -> 0 | G116: =D116/4 -> 0 | H116: =D116/4 -> 0 | I116: =D116 -> 0
A119: Common Operating Expenses | F119: Year 2 | G119: Year 3 | H119: Year 4 | I119: Year 5
A120: Administrative: | B120: Annual Costs | D120: Annual Increase | F120: Periodic Rate | G120: Periodic Rate | H120: Periodic Rate | I120: Periodic Rate
A121: Start up Expenses | B121: 125000
A122: Rent of Office Plus Utilities | B122: 24000 | D122: 0.05 | F122: =D122/12 -> 0.0041666667 | G122: =D122/4 -> 0.0125 | H122: =D122/4 -> 0.0125 | I122: =D122 -> 0.05
A123: Office Supplies | B123: 8000 | D123: 0.05 | F123: =D123/12 -> 0.0041666667 | G123: =D123/4 -> 0.0125 | H123: =D123/4 -> 0.0125 | I123: =D123 -> 0.05
...

Sheet Balance Sheet Assumptions
A1: Assets:
A3: Minimum Cash On Hand | B3: 100000 | C3: 3X your monthly burn rate
A5: Accounts Receivable as a percentage of sales | B5: 0.5
A7: Inventory as a percentage of COGS | B7: 0.4
A9: Fixed Assets - See Fixed Asset Tab
A12: Liabilities:
A14: Accounts Payable as a percentage of COGS | B14: 0.6
A17: Owners' Equity:
A19: Founders' Contribution | B19: 100000 | C19: $20,000 per founder
A20: Angel Investor's Contribution | B20: 675000 | C20: We solve for this later.
A22: Dividends Paid | B22: 0

Sheet Fixed Asset Assumptions
A1: Note: Do not think that just because you intend to work out of your parents garage/basement that you will not have fixed assets. If you have a sales force, don't assume that they are going to be using their own office equipment either. Also as your company grows you need to add more office furniture and equipment. If you are making a million dollars in sales you need more than what you started with.
A7: Tangible Asstes: Original Purchases Only
B8: Year 1 | C8: Year 2 | D8: Year 3 | E8: Year 4 | F8: Year 5
A9: Office:
A10: Computers | B10: 10000 | C10: 0 | D10: 0 | E10: 10000 | F10: 0
A11: Phones | B11: 4000 | C11: 0 | D11: 4000 | E11: 0 | F11: 4000
A12: Other Office Equipment | B12: 10000 | C12: 500 | D12: 500 | E12: 4000 | F12: 500
A14: Production:
A15: Machinery | B15: 0 | C15: 0 | D15: 0 | E15: 0 | F15: 0
A16: Transportation - Vehicle | B16: 10000 | C16: 0 | D16: 0 | E16: 0 | F16: 0
A17: Other Production Equipment | B17: 0 | C17: 0 | D17: 0 | E17: 0 | F17: 0
A19: Sales:
A20: Trade Booth for shows | B20: 15000 | C20: 2000 | D20: 0 | E20: 2000 | F20: 0
A21: Other Sales Equipment | B21: 0 | C21: 0 | D21: 0 | E21: 0 | F21: 0
A23: Total Additions to Fixed Assets | B23: =SUM(B10:B22) -> 49000 | C23: =SUM(C10:C22) -> 2500 | D23: =SUM(D10:D22) -> 4500 | E23: =SUM(E10:E22) -> 16000 | F23: =SUM(F10:F22) -> 4500
A25: Total Fixed Assets | B25: =B23 -> 49000 | C25: =C23+B25 -> 51500 | D25: =D23+C25 -> 56000 | E25: =E23+D25 -> 72000 | F25: =F23+E25 -> 76500
A27: Useful Life | B27: 5 | C27: 5 | D27: 5 | E27: =D27 -> 5 | F27: =E27 -> 5
A29: Annual Depreciation Expense | B29: =B25/B27 -> 9800 | C29: =C25/C27 -> 10300 | D29: =D25/D27 -> 11200 | E29: =E25/E27 -> 14400 | F29: =F25/F27 -> 15300
A31: Periodic Depreciation Expense | B31: =ROUND(B29/12,0) -> 817 | C31: =ROUND(C29/12,0) -> 858 | D31: =ROUND(D29/4,0) -> 2800 | E31: =ROUND(E29/4,0) -> 3600 | F31: =ROUND(F29,0) -> 15300
A35: Intangible Asstes: Original Purchases Only
B36: Year 1 | C36: Year 2 | D36: Year 3 | E36: Year 4 | F36: Year 5
A37: Patents | B37: 20000 | C37: 0 | D37: 0 | E37: 0 | F37: 0
A38: Trademarks | C38: 0 | D38: 0 | E38: 0 | F38: 0
A39: Other Intangible Assest | B39: 0 | C39: 0 | D39: 0 | E39: 0 | F39: 0
A41: Total Additions to Intangible Assets | B41: =SUM(B37:B40) -> 20000 | C41: =SUM(C37:C40) -> 0 | D41: =SUM(D37:D40) -> 0 | E41: =SUM(E37:E40) -> 0 | F41: =SUM(F37:F40) -> 0
A43: Total Fixed Assets | B43: =B41 -> 20000 | C43: =C41+B43 -> 20000 | D43: =D41+C43 -> 20000 | E43: =E41+D43 -> 20000 | F43: =F41+E43 -> 20000
A45: Useful Life | B45: 20 | C45: 20 | D45: 20 | E45: 20 | F45: =E45 -> 20
A47: Annual Depreciation Expense | B47: =B43/B45 -> 1000 | C47: =C43/C45 -> 1000 | D47: =D43/D45 -> 1000 | E47: =E43/E45 -> 1000 | F47: =F43/F45 -> 1000
A49: Periodic Depreciation Expense | B49: =ROUND(B47/12,0) -> 83 | C49: =ROUND(C47/12,0) -> 83 | D49: =ROUND(D47/4,0) -> 250 | E49: =ROUND(E47/4,0) -> 250 | F49: =ROUND(F47,0) -> 1000

Sheet Income Statement
B1: Company Name | O1: =B1 -> Company Name | AB1: =O1 -> Company Name
B2: Income Statement | O2: Income Statement | AB2: Income Statement
B4: Year 1 | O4: Year 2 | AB4: Year 3 | AG4: Year 4 | AL4: Year 5
A5: Revenue | B5: January | C5: February | D5: March | E5: April | F5: May | G5: June | H5: July | I5: August | J5: September | K5: October | L5: November | M5: December | N5: Total | O5: January | P5: February | Q5: March | R5: April | S5: May | T5: June | U5: July | V5: August | W5: September | X5: October | Y5: November | Z5: December | AA5: Total | AB5: Quarter 1 | AC5: Quarter 2 | AD5: Quarter 3 | AE5: Quarter 4 | AF5: Total | AG5: Quarter 1 | AH5: Quarter 2 | AI5: Quarter 3 | AJ5: Quarter 4 | AK5: Total | AL5: Total
A6: Product 1 | B6: ='Income Statement Assumptions'!B5*'Income Statement Assumptions'!B6 -> 0 | C6: ='Income Statement Assumptions'!C5*'Income Statement Assumptions'!C6 -> 0 | D6: ='Income Statement Assumptions'!D5*'Income Statement Assumptions'!D6 -> 0 | E6: ='Income Statement Assumptions'!E5*'Income Statement Assumptions'!E6 -> 0 | F6: ='Income Statement Assumptions'!F5*'Income Statement Assumptions'!F6 -> 0 | G6: ='Income Statement Assumptions'!G5*'Income Statement Assumptions'!G6 -> 0 | H6: ='Income Statement Assumptions'!H5*'Income Statement Assumptions'!H6 -> 2000 | I6: ='Income Statement Assumptions'!I5*'Income Statement Assumptions'!I6 -> 3000 | ... M6: ='Income Statement Assumptions'!M5*'Income Statement Assumptions'!M6 -> 10000 | N6: =SUM(B6:M6) -> 34000 | O6: ='Income Statement Assumptions'!B11*'Income Statement Assumptions'!B10 -> 11260 | P6: ='Income Statement Assumptions'!C11*'Income Statement Assumptions'!C10 -> 12660 | Q6: ='Income Statement Assumptions'!D11*'Income Statement Assumptions'!D10 -> 14240 | R6: ='Income Statement Assumptions'!E11*'Income Statement Assumptions'!E10 -> 16020 | S6: ='Income Statement Assumptions'!F11*'Income Statement Assumptions'!F10 -> 18020 | T6: ='Income Statement Assumptions'!G11*'Income Statement Assumptions'!G10 -> 20280 | U6: ='Income Statement Assumptions'!H11*'Income Statement Assumptions'!H10 -> 22820 | V6: ='Income Statement Assumptions'!I11*'Income Statement Assumptions'!I10 -> 25680 | ... Z6: ='Income Statement Assumptions'!M11*'Income Statement Assumptions'!M10 -> 41160 | AA6: =SUM(O6:Z6) -> 280140 | AB6: ='Income Statement Assumptions'!D15*'Income Statement Assumptions'!D16 -> 151602 | AC6: ='Income Statement Assumptions'!G15*'Income Statement Assumptions'!G16 -> 189508 | AD6: ='Income Statement Assumptions'!J15*'Income Statement Assumptions'!J16 -> 236896 | AE6: ='Income Statement Assumptions'!M15*'Income Statement Assumptions'!M16 -> 296120 | AF6: =SUM(AB6:AE6) -> 874126 | AG6: ='Income Statement Assumptions'!D20*'Income Statement Assumptions'!D21 -> 371496 | AH6: ='Income Statement Assumptions'!G20*'Income Statement Assumptions'!G21 -> 427224 | AI6: ='Income Statement Assumptions'!J20*'Income Statement Assumptions'!J21 -> 491304 | AJ6: ='Income Statement Assumptions'!M20*'Income Statement Assumptions'!M21 -> 565008 | AK6: =SUM(AG6:AJ6) -> 1855032 | AL6: ='Income Statement Assumptions'!M25*'Income Statement Assumptions'!N26 -> 2512025
A7: Product 2 | B7: ='Income Statement Assumptions'!B37*'Income Statement Assumptions'!B38 -> 0 | C7: ='Income Statement Assumptions'!C37*'Income Statement Assumptions'!C38 -> 0 | D7: ='Income Statement Assumptions'!D37*'Income Statement Assumptions'!D38 -> 0 | E7: ='Income Statement Assumptions'!E37*'Income Statement Assumptions'!E38 -> 0 | F7: ='Income Statement Assumptions'!F37*'Income Statement Assumptions'!F38 -> 0 | G7: ='Income Statement Assumptions'!G37*'Income Statement Assumptions'!G38 -> 0 | H7: ='Income Statement Assumptions'!H37*'Income Statement Assumptions'!H38 -> 20000 | I7: ='Income Statement Assumptions'!I37*'Income Statement Assumptions'!I38 -> 20000 | ... M7: ='Income Statement Assumptions'!M37*'Income Statement Assumptions'!M38 -> 35000 | N7: =SUM(B7:M7) -> 160000 | O7: ='Income Statement Assumptions'!B43*'Income Statement Assumptions'!B42 -> 39380 | P7: ='Income Statement Assumptions'!C43*'Income Statement Assumptions'!C42 -> 44300 | Q7: ='Income Statement Assumptions'!D43*'Income Statement Assumptions'!D42 -> 49840 | R7: ='Income Statement Assumptions'!E43*'Income Statement Assumptions'!E42 -> 56070 | S7: ='Income Statement Assumptions'!F43*'Income Statement Assumptions'!F42 -> 63080 | T7: ='Income Statement Assumptions'!G43*'Income Statement Assumptions'!G42 -> 70970 | U7: ='Income Statement Assumptions'!H43*'Income Statement Assumptions'!H42 -> 79840 | V7: ='Income Statement Assumptions'!I43*'Income Statement Assumptions'!I42 -> 89820 | ... Z7: ='Income Statement Assumptions'!M43*'Income Statement Assumptions'!M42 -> 143880 | AA7: =SUM(O7:Z7) -> 979800 | AB7: ='Income Statement Assumptions'!D47*'Income Statement Assumptions'!D48 -> 529991 | AC7: ='Income Statement Assumptions'!G47*'Income Statement Assumptions'!G48 -> 662486 | AD7: ='Income Statement Assumptions'!J47*'Income Statement Assumptions'!J48 -> 828113 | AE7: ='Income Statement Assumptions'!M47*'Income Statement Assumptions'!M48 -> 1035144 | AF7: =SUM(AB7:AE7) -> 3055734 | AG7: ='Income Statement Assumptions'!D52*'Income Statement Assumptions'!D53 -> 1298640 | AH7: ='Income Statement Assumptions'!G52*'Income Statement Assumptions'!G53 -> 1493436 | AI7: ='Income Statement Assumptions'!J52*'Income Statement Assumptions'!J53 -> 1717452 | AJ7: ='Income Statement Assumptions'!M52*'Income Statement Assumptions'!M53 -> 1975068 | AK7: =SUM(AG7:AJ7) -> 6484596 | AL7: ='Income Statement Assumptions'!M57*'Income Statement Assumptions'!N58 -> 8781225
A8: Product 3 | B8: ='Income Statement Assumptions'!B69*'Income Statement Assumptions'!B70 -> 0 | C8: ='Income Statement Assumptions'!C69*'Income Statement Assumptions'!C70 -> 0 | D8: ='Income Statement Assumptions'!D69*'Income Statement Assumptions'!D70 -> 0 | E8: ='Income Statement Assumptions'!E69*'Income Statement Assumptions'!E70 -> 0 | F8: ='Income Statement Assumptions'!F69*'Income Statement Assumptions'!F70 -> 0 | G8: ='Income Statement Assumptions'!G69*'Income Statement Assumptions'!G70 -> 0 | H8: ='Income Statement Assumptions'!H69*'Income Statement Assumptions'!H70 -> 2100 | I8: ='Income Statement Assumptions'!I69*'Income Statement Assumptions'!I70 -> 2150 | ... M8: ='Income Statement Assumptions'!M69*'Income Statement Assumptions'!M70 -> 4000 | N8: =SUM(B8:M8) -> 17950 | O8: ='Income Statement Assumptions'!B75*'Income Statement Assumptions'!B74 -> 4500 | P8: ='Income Statement Assumptions'!C75*'Income Statement Assumptions'!C74 -> 5062 | Q8: ='Income Statement Assumptions'!D75*'Income Statement Assumptions'!D74 -> 5694 | R8: ='Income Statement Assumptions'!E75*'Income Statement Assumptions'!E74 -> 6406 | S8: ='Income Statement Assumptions'!F75*'Income Statement Assumptions'!F74 -> 7206 | T8: ='Income Statement Assumptions'!G75*'Income Statement Assumptions'!G74 -> 8106 | U8: ='Income Statement Assumptions'!H75*'Income Statement Assumptions'!H74 -> 9120 | V8: ='Income Statement Assumptions'!I75*'Income Statement Assumptions'!I74 -> 10260 | ... Z8: ='Income Statement Assumptions'!M75*'Income Statement Assumptions'!M74 -> 16434 | AA8: =SUM(O8:Z8) -> 111922 | AB8: ='Income Statement Assumptions'!D79*'Income Statement Assumptions'!D80 -> 55032 | AC8: ='Income Statement Assumptions'!G79*'Income Statement Assumptions'!G80 -> 68790 | AD8: ='Income Statement Assumptions'!J79*'Income Statement Assumptions'!J80 -> 85988 | AE8: ='Income Statement Assumptions'!M79*'Income Statement Assumptions'!M80 -> 107486 | AF8: =SUM(AB8:AE8) -> 317296 | AG8: ='Income Statement Assumptions'!D84*'Income Statement Assumptions'!D85 -> 123608 | AH8: ='Income Statement Assumptions'!G84*'Income Statement Assumptions'!G85 -> 142150 | AI8: ='Income Statement Assumptions'!J84*'Income Statement Assumptions'!J85 -> 163472 | AJ8: ='Income Statement Assumptions'!M84*'Income Statement Assumptions'!M85 -> 187992 | AK8: =SUM(AG8:AJ8) -> 617222 | AL8: ='Income Statement Assumptions'!M89*'Income Statement Assumptions'!N90 -> 802388
A10: Total Revenue | B10: =SUM(B6:B9) -> 0 | C10: =SUM(C6:C9) -> 0 | D10: =SUM(D6:D9) -> 0 | E10: =SUM(E6:E9) -> 0 | F10: =SUM(F6:F9) -> 0 | G10: =SUM(G6:G9) -> 0 | H10: =SUM(H6:H9) -> 24100 | I10: =SUM(I6:I9) -> 25150 | ... M10: =SUM(M6:M9) -> 49000 | N10: =SUM(N6:N8) -> 211950 | O10: =SUM(O6:O9) -> 55140 | P10: =SUM(P6:P9) -> 62022 | Q10: =SUM(Q6:Q9) -> 69774 | R10: =SUM(R6:R9) -> 78496 | S10: =SUM(S6:S9) -> 88306 | T10: =SUM(T6:T9) -> 99356 | U10: =SUM(U6:U9) -> 111780 | V10: =SUM(V6:V9) -> 125760 | ... AL10: =SUM(AL6:AL9) -> 12095638
A12: Cost of Goods Sold
A13: =A6 -> Product 1
A14: ='Income Statement Assumptions'!A101 -> outsourced product | B14: ='Income Statement Assumptions'!$B$101*'Income Statement Assumptions'!B6 -> 0 | C14: ='Income Statement Assumptions'!$B$101*'Income Statement Assumptions'!C6 -> 0 | D14: ='Income Statement Assumptions'!$B$101*'Income Statement Assumptions'!D6 -> 0 | E14: ='Income Statement Assumptions'!$B$101*'Income Statement Assumptions'!E6 -> 0 | F14: ='Income Statement Assumptions'!$B$101*'Income Statement Assumptions'!F6 -> 0 | G14: ='Income Statement Assumptions'!$B$101*'Income Statement Assumptions'!G6 -> 0 | H14: ='Income Statement Assumptions'!$B$101*'Income Statement Assumptions'!H6 -> 525 | I14: ='Income Statement Assumptions'!$B$101*'Income Statement Assumptions'!I6 -> 787.5 | ... M14: ='Income Statement Assumptions'!$B$101*'Income Statement Assumptions'!M6 -> 2625 | N14: =SUM(B14:M14) -> 8925 | O14: =ROUND(('Income Statement Assumptions'!B$11*('Income Statement Assumptions'!$B101*(1+'Income Statement Assumptions'!$F$101))),0) -> 2961 | P14: =ROUND(('Income Statement Assumptions'!C$11*('Income Statement Assumptions'!$B101*(1+'Income Statement Assumptions'!$F$101))),0) -> 3329 | Q14: =ROUND(('Income Statement Assumptions'!D$11*('Income Statement Assumptions'!$B101*(1+'Income Statement Assumptions'!$F$101))),0) -> 3744 | R14: =ROUND(('Income Statement Assumptions'!E$11*('Income Statement Assumptions'!$B101*(1+'Income Statement Assumptions'!$F$101))),0) -> 4212 | S14: =ROUND(('Income Statement Assumptions'!F$11*('Income Statement Assumptions'!$B101*(1+'Income Statement Assumptions'!$F$101))),0) -> 4738 | T14: =ROUND(('Income Statement Assumptions'!G$11*('Income Statement Assumptions'!$B101*(1+'Income Statement Assumptions'!$F$101))),0) -> 5332 | U14: =ROUND(('Income Statement Assumptions'!H$11*('Income Statement Assumptions'!$B101*(1+'Income Statement Assumptions'!$F$101))),0) -> 6000 | V14: =ROUND(('Income Statement Assumptions'!I$11*('Income Statement Assumptions'!$B101*(1+'Income Statement Assumptions'!$F$101))),0) -> 6752 | ... Z14: =ROUND(('Income Statement Assumptions'!M$11*('Income Statement Assumptions'!$B101*(1+'Income Statement Assumptions'!$F$101))),0) -> 10823 | AA14: =SUM(O14:Z14) -> 73659 | AB14: =ROUND(('Income Statement Assumptions'!$B101*(1+'Income Statement Assumptions'!$D101)*(1+'Income Statement Assumptions'!$G101))*'Income Statement Assumptions'!D$16,0) -> 37086 | AC14: =ROUND(('Income Statement Assumptions'!$B101*(1+'Income Statement Assumptions'!$D101)*(1+'Income Statement Assumptions'!$G101))*'Income Statement Assumptions'!G$16,0) -> 46359 | AD14: =ROUND(('Income Statement Assumptions'!$B101*(1+'Income Statement Assumptions'!$D101)*(1+'Income Statement Assumptions'!$G101))*'Income Statement Assumptions'!J$16,0) -> 57951 | AE14: =ROUND(('Income Statement Assumptions'!$B101*(1+'Income Statement Assumptions'!$D101)*(1+'Income Statement Assumptions'!$G101))*'Income Statement Assumptions'!M$16,0) -> 72439 | AF14: =SUM(AB14:AE14) -> 213835 | AG14: =ROUND(('Income Statement Assumptions'!$B101*(1+'Income Statement Assumptions'!$D101)*(1+'Income Statement Assumptions'!$D101)*(1+'Income Statement Assumptions'!$H101)*'Income Statement Assumptions'!D$21),0) -> 84971 | AH14: =ROUND(('Income Statement Assumptions'!$B101*(1+'Income Statement Assumptions'!$D101)*(1+'Income Statement Assumptions'!$D101)*(1+'Income Statement Assumptions'!$H101)*'Income Statement Assumptions'!G$21),0) -> 97717 | AI14: =ROUND(('Income Statement Assumptions'!$B101*(1+'Income Statement Assumptions'!$D101)*(1+'Income Statement Assumptions'!$D101)*(1+'Income Statement Assumptions'!$H101)*'Income Statement Assumptions'!J$21),0) -> 112374 | AJ14: =ROUND(('Income Statement Assumptions'!$B101*(1+'Income Statement Assumptions'!$D101)*(1+'Income Statement Assumptions'!$D101)*(1+'Income Statement Assumptions'!$H101)*'Income Statement Assumptions'!M$21),0) -> 129232 | AK14: =SUM(AG14:AJ14) -> 424294 | AL14: =ROUND(('Income Statement Assumptions'!$B101*(1+'Income Statement Assumptions'!$D101)*(1+'Income Statement Assumptions'!$D101)*(1+'Income Statement Assumptions'!D101))*(1+'Income Statement Assumptions'!I101)*'Income Statement Assumptions'!N$26,0) -> 571010
A15: ='Income Statement Assumptions'!A102 -> 3PL | B15: ='Income Statement Assumptions'!$B102*'Income Statement Assumptions'!B6 -> 0 | C15: ='Income Statement Assumptions'!$B$102*'Income Statement Assumptions'!C6 -> 0 | D15: ='Income Statement Assumptions'!$B$102*'Income Statement Assumptions'!D6 -> 0 | E15: ='Income Statement Assumptions'!$B$102*'Income Statement Assumptions'!E6 -> 0 | F15: ='Income Statement Assumptions'!$B$102*'Income Statement Assumptions'!F6 -> 0 | G15: ='Income Statement Assumptions'!$B$102*'Income Statement Assumptions'!G6 -> 0 | H15: ='Income Statement Assumptions'!$B$102*'Income Statement Assumptions'!H6 -> 75 | I15: ='Income Statement Assumptions'!$B$102*'Income Statement Assumptions'!I6 -> 112.5 | J15: ='Income Statement Assumptions'!$B$102*'Income Statement Assumptions'!J6 -> 187.5 | ... M15: ='Income Statement Assumptions'!$B$102*'Income Statement Assumptions'!M6 -> 375 | N15: =SUM(B15:M15) -> 1275 | O15: =ROUND(('Income Statement Assumptions'!B$11*('Income Statement Assumptions'!$B102*(1+'Income Statement Assumptions'!$F$101))),0) -> 423 | P15: =ROUND(('Income Statement Assumptions'!C$11*('Income Statement Assumptions'!$B102*(1+'Income Statement Assumptions'!$F$101))),0) -> 476 | Q15: =ROUND(('Income Statement Assumptions'!D$11*('Income Statement Assumptions'!$B102*(1+'Income Statement Assumptions'!$F$101))),0) -> 535 | R15: =ROUND(('Income Statement Assumptions'!E$11*('Income Statement Assumptions'!$B102*(1+'Income Statement Assumptions'!$F$101))),0) -> 602 | S15: =ROUND(('Income Statement Assumptions'!F$11*('Income Statement Assumptions'!$B102*(1+'Income Statement Assumptions'!$F$101))),0) -> 677 | T15: =ROUND(('Income Statement Assumptions'!G$11*('Income Statement Assumptions'!$B102*(1+'Income Statement Assumptions'!$F$101))),0) -> 762 | U15: =ROUND(('Income Statement Assumptions'!H$11*('Income Statement Assumptions'!$B102*(1+'Income Statement Assumptions'!$F$101))),0) -> 857 | V15: =ROUND(('Income Statement Assumptions'!I$11*('Income Statement Assumptions'!$B102*(1+'Income Statement Assumptions'!$F$101))),0) -> 965 | ... Z15: =ROUND(('Income Statement Assumptions'!M$11*('Income Statement Assumptions'!$B102*(1+'Income Statement Assumptions'!$F$101))),0) -> 1546 | AA15: =SUM(O15:Z15) -> 10525 | AB15: =ROUND(('Income Statement Assumptions'!$B102*(1+'Income Statement Assumptions'!$D102)*(1+'Income Statement Assumptions'!$G102))*'Income Statement Assumptions'!D$16,0) -> 5298 | AC15: =ROUND(('Income Statement Assumptions'!$B102*(1+'Income Statement Assumptions'!$D102)*(1+'Income Statement Assumptions'!$G102))*'Income Statement Assumptions'!G$16,0) -> 6623 | AD15: =ROUND(('Income Statement Assumptions'!$B102*(1+'Income Statement Assumptions'!$D102)*(1+'Income Statement Assumptions'!$G102))*'Income Statement Assumptions'!J$16,0) -> 8279 | AE15: =ROUND(('Income Statement Assumptions'!$B102*(1+'Income Statement Assumptions'!$D102)*(1+'Income Statement Assumptions'!$G102))*'Income Statement Assumptions'!M$16,0) -> 10348 | AF15: =SUM(AB15:AE15) -> 30548 | AG15: =ROUND(('Income Statement Assumptions'!$B102*(1+'Income Statement Assumptions'!$D102)*(1+'Income Statement Assumptions'!$D102)*(1+'Income Statement Assumptions'!$H102)*'Income Statement Assumptions'!D$21),0) -> 12139 | AH15: =ROUND(('Income Statement Assumptions'!$B102*(1+'Income Statement Assumptions'!$D102)*(1+'Income Statement Assumptions'!$D102)*(1+'Income Statement Assumptions'!$H102)*'Income Statement Assumptions'!G$21),0) -> 13960 | AI15: =ROUND(('Income Statement Assumptions'!$B102*(1+'Income Statement Assumptions'!$D102)*(1+'Income Statement Assumptions'!$D102)*(1+'Income Statement Assumptions'!$H102)*'Income Statement Assumptions'!J$21),0) -> 16053 | AJ15: =ROUND(('Income Statement Assumptions'!$B102*(1+'Income Statement Assumptions'!$D102)*(1+'Income Statement Assumptions'!$D102)*(1+'Income Statement Assumptions'!$H102)*'Income Statement Assumptions'!M$21),0) -> 18462 | AK15: =SUM(AG15:AJ15) -> 60614 | AL15: =ROUND(('Income Statement Assumptions'!$B102*(1+'Income Statement Assumptions'!$D102)*(1+'Income Statement Assumptions'!$D102)*(1+'Income Statement Assumptions'!D102))*(1+'Income Statement Assumptions'!I102)*'Income Statement Assumptions'!N$26,0) -> 81573
A16: ='Income Statement Assumptions'!A103 -> CC fee | B16: ='Income Statement Assumptions'!$B103*'Income Statement Assumptions'!B6 -> 0 | C16: ='Income Statement Assumptions'!$B103*'Income Statement Assumptions'!C6 -> 0 | D16: ='Income Statement Assumptions'!$B103*'Income Statement Assumptions'!D6 -> 0 | E16: ='Income Statement Assumptions'!$B103*'Income Statement Assumptions'!E6 -> 0 | F16: ='Income Statement Assumptions'!$B103*'Income Statement Assumptions'!F6 -> 0 | G16: ='Income Statement Assumptions'!$B103*'Income Statement Assumptions'!G6 -> 0 | H16: ='Income Statement Assumptions'!$B103*'Income Statement Assumptions'!H6 -> 60 | I16: ='Income Statement Assumptions'!$B103*'Income Statement Assumptions'!I6 -> 90 | ... M16: ='Income Statement Assumptions'!$B103*'Income Statement Assumptions'!M6 -> 300 | N16: =SUM(B16:M16) -> 1020 | O16: =ROUND(('Income Statement Assumptions'!B$11*('Income Statement Assumptions'!$B103*(1+'Income Statement Assumptions'!$F$101))),0) -> 338 | P16: =ROUND(('Income Statement Assumptions'!C$11*('Income Statement Assumptions'!$B103*(1+'Income Statement Assumptions'!$F$101))),0) -> 380 | Q16: =ROUND(('Income Statement Assumptions'!D$11*('Income Statement Assumptions'!$B103*(1+'Income Statement Assumptions'!$F$101))),0) -> 428 | R16: =ROUND(('Income Statement Assumptions'!E$11*('Income Statement Assumptions'!$B103*(1+'Income Statement Assumptions'!$F$101))),0) -> 481 | S16: =ROUND(('Income Statement Assumptions'!F$11*('Income Statement Assumptions'!$B103*(1+'Income Statement Assumptions'!$F$101))),0) -> 542 | T16: =ROUND(('Income Statement Assumptions'!G$11*('Income Statement Assumptions'!$B103*(1+'Income Statement Assumptions'!$F$101))),0) -> 609 | U16: =ROUND(('Income Statement Assumptions'!H$11*('Income Statement Assumptions'!$B103*(1+'Income Statement Assumptions'!$F$101))),0) -> 686 | V16: =ROUND(('Income Statement Assumptions'!I$11*('Income Statement Assumptions'!$B103*(1+'Income Statement Assumptions'!$F$101))),0) -> 772 | ... Z16: =ROUND(('Income Statement Assumptions'!M$11*('Income Statement Assumptions'!$B103*(1+'Income Statement Assumptions'!$F$101))),0) -> 1237 | AA16: =SUM(O16:Z16) -> 8417 | AB16: =ROUND(('Income Statement Assumptions'!$B103*(1+'Income Statement Assumptions'!$D103)*(1+'Income Statement Assumptions'!$G103))*'Income Statement Assumptions'!D$16,0) -> 4238 | AC16: =ROUND(('Income Statement Assumptions'!$B103*(1+'Income Statement Assumptions'!$D103)*(1+'Income Statement Assumptions'!$G103))*'Income Statement Assumptions'!G$16,0) -> 5298 | AD16: =ROUND(('Income Statement Assumptions'!$B103*(1+'Income Statement Assumptions'!$D103)*(1+'Income Statement Assumptions'!$G103))*'Income Statement Assumptions'!J$16,0) -> 6623 | AE16: =ROUND(('Income Statement Assumptions'!$B103*(1+'Income Statement Assumptions'!$D103)*(1+'Income Statement Assumptions'!$G103))*'Income Statement Assumptions'!M$16,0) -> 8279 | AF16: =SUM(AB16:AE16) -> 24438 | AG16: =ROUND(('Income Statement Assumptions'!$B103*(1+'Income Statement Assumptions'!$D103)*(1+'Income Statement Assumptions'!$D103)*(1+'Income Statement Assumptions'!$H103)*'Income Statement Assumptions'!D$21),0) -> 9711 | AH16: =ROUND(('Income Statement Assumptions'!$B103*(1+'Income Statement Assumptions'!$D103)*(1+'Income Statement Assumptions'!$D103)*(1+'Income Statement Assumptions'!$H103)*'Income Statement Assumptions'!G$21),0) -> 11168 | AI16: =ROUND(('Income Statement Assumptions'!$B103*(1+'Income Statement Assumptions'!$D103)*(1+'Income Statement Assumptions'!$D103)*(1+'Income Statement Assumptions'!$H103)*'Income Statement Assumptions'!J$21),0) -> 12843 | AJ16: =ROUND(('Income Statement Assumptions'!$B103*(1+'Income Statement Assumptions'!$D103)*(1+'Income Statement Assumptions'!$D103)*(1+'Income Statement Assumptions'!$H103)*'Income Statement Assumptions'!M$21),0) -> 14769 | AK16: =SUM(AG16:AJ16) -> 48491 | AL16: =ROUND(('Income Statement Assumptions'!$B103*(1+'Income Statement Assumptions'!$D103)*(1+'Income Statement Assumptions'!$D103)*(1+'Income Statement Assumptions'!D103))*(1+'Income Statement Assumptions'!I103)*'Income Statement Assumptions'!N$26,0) -> 65258
A17: ='Income Statement Assumptions'!A104 -> warranty | B17: ='Income Statement Assumptions'!$B104*'Income Statement Assumptions'!B6 -> 0 | C17: ='Income Statement Assumptions'!$B104*'Income Statement Assumptions'!C6 -> 0 | D17: ='Income Statement Assumptions'!$B104*'Income Statement Assumptions'!D6 -> 0 | E17: ='Income Statement Assumptions'!$B104*'Income Statement Assumptions'!E6 -> 0 | F17: ='Income Statement Assumptions'!$B104*'Income Statement Assumptions'!F6 -> 0 | G17: ='Income Statement Assumptions'!$B104*'Income Statement Assumptions'!G6 -> 0 | H17: ='Income Statement Assumptions'!$B104*'Income Statement Assumptions'!H6 -> 15 | I17: ='Income Statement Assumptions'!$B104*'Income Statement Assumptions'!I6 -> 22.5 | ... M17: ='Income Statement Assumptions'!$B104*'Income Statement Assumptions'!M6 -> 75 | N17: =SUM(B17:M17) -> 255 | O17: =ROUND(('Income Statement Assumptions'!B$11*('Income Statement Assumptions'!$B104*(1+'Income Statement Assumptions'!$F$101))),0) -> 85 | P17: =ROUND(('Income Statement Assumptions'!C$11*('Income Statement Assumptions'!$B104*(1+'Income Statement Assumptions'!$F$101))),0) -> 95 | Q17: =ROUND(('Income Statement Assumptions'!D$11*('Income Statement Assumptions'!$B104*(1+'Income Statement Assumptions'!$F$101))),0) -> 107 | R17: =ROUND(('Income Statement Assumptions'!E$11*('Income Statement Assumptions'!$B104*(1+'Income Statement Assumptions'!$F$101))),0) -> 120 | S17: =ROUND(('Income Statement Assumptions'!F$11*('Income Statement Assumptions'!$B104*(1+'Income Statement Assumptions'!$F$101))),0) -> 135 | T17: =ROUND(('Income Statement Assumptions'!G$11*('Income Statement Assumptions'!$B104*(1+'Income Statement Assumptions'!$F$101))),0) -> 152 | U17: =ROUND(('Income Statement Assumptions'!H$11*('Income Statement Assumptions'!$B104*(1+'Income Statement Assumptions'!$F$101))),0) -> 171 | V17: =ROUND(('Income Statement Assumptions'!I$11*('Income Statement Assumptions'!$B104*(1+'Income Statement Assumptions'!$F$101))),0) -> 193 | ... Z17: =ROUND(('Income Statement Assumptions'!M$11*('Income Statement Assumptions'!$B104*(1+'Income Statement Assumptions'!$F$101))),0) -> 309 | AA17: =SUM(O17:Z17) -> 2103 | AB17: =ROUND(('Income Statement Assumptions'!$B104*(1+'Income Statement Assumptions'!$D104)*(1+'Income Statement Assumptions'!$G104))*'Income Statement Assumptions'!D$16,0) -> 1099 | AC17: =ROUND(('Income Statement Assumptions'!$B104*(1+'Income Statement Assumptions'!$D104)*(1+'Income Statement Assumptions'!$G104))*'Income Statement Assumptions'!G$16,0) -> 1374 | AD17: =ROUND(('Income Statement Assumptions'!$B104*(1+'Income Statement Assumptions'!$D104)*(1+'Income Statement Assumptions'!$G104))*'Income Statement Assumptions'!J$16,0) -> 1717 | AE17: =ROUND(('Income Statement Assumptions'!$B104*(1+'Income Statement Assumptions'!$D104)*(1+'Income Statement Assumptions'!$G104))*'Income Statement Assumptions'!M$16,0) -> 2146 | AF17: =SUM(AB17:AE17) -> 6336 | AG17: =ROUND(('Income Statement Assumptions'!$B104*(1+'Income Statement Assumptions'!$D104)*(1+'Income Statement Assumptions'!$D104)*(1+'Income Statement Assumptions'!$H104)*'Income Statement Assumptions'!D$21),0) -> 2592 | AH17: =ROUND(('Income Statement Assumptions'!$B104*(1+'Income Statement Assumptions'!$D104)*(1+'Income Statement Assumptions'!$D104)*(1+'Income Statement Assumptions'!$H104)*'Income Statement Assumptions'!G$21),0) -> 2981 | AI17: =ROUND(('Income Statement Assumptions'!$B104*(1+'Income Statement Assumptions'!$D104)*(1+'Income Statement Assumptions'!$D104)*(1+'Income Statement Assumptions'!$H104)*'Income Statement Assumptions'!J$21),0) -> 3428 | AJ17: =ROUND(('Income Statement Assumptions'!$B104*(1+'Income Statement Assumptions'!$D104)*(1+'Income Statement Assumptions'!$D104)*(1+'Income Statement Assumptions'!$H104)*'Income Statement Assumptions'!M$21),0) -> 3942 | AK17: =SUM(AG17:AJ17) -> 12943 | AL17: =ROUND(('Income Statement Assumptions'!$B104*(1+'Income Statement Assumptions'!$D104)*(1+'Income Statement Assumptions'!$D104)*(1+'Income Statement Assumptions'!D104))*(1+'Income Statement Assumptions'!I104)*'Income Statement Assumptions'!N$26,0) -> 18320
A19: =A7 -> Product 2
A20: ='Income Statement Assumptions'!A107 -> Outsourced product | B20: ='Income Statement Assumptions'!$B107*'Income Statement Assumptions'!B38 -> 0 | C20: ='Income Statement Assumptions'!$B107*'Income Statement Assumptions'!C38 -> 0 | D20: ='Income Statement Assumptions'!$B107*'Income Statement Assumptions'!D38 -> 0 | E20: ='Income Statement Assumptions'!$B107*'Income Statement Assumptions'!E38 -> 0 | F20: ='Income Statement Assumptions'!$B107*'Income Statement Assumptions'!F38 -> 0 | G20: ='Income Statement Assumptions'!$B107*'Income Statement Assumptions'!G38 -> 0 | H20: ='Income Statement Assumptions'!$B107*'Income Statement Assumptions'!H38 -> 10500 | I20: ='Income Statement Assumptions'!$B107*'Income Statement Assumptions'!I38 -> 10500 | ... M20: ='Income Statement Assumptions'!$B107*'Income Statement Assumptions'!M38 -> 18375 | N20: =SUM(B20:M20) -> 84000 | O20: =ROUND(('Income Statement Assumptions'!B$43*('Income Statement Assumptions'!$B107*(1+'Income Statement Assumptions'!$F$107))),0) -> 20709 | P20: =ROUND(('Income Statement Assumptions'!C$43*('Income Statement Assumptions'!$B107*(1+'Income Statement Assumptions'!$F$107))),0) -> 23296 | Q20: =ROUND(('Income Statement Assumptions'!D$43*('Income Statement Assumptions'!$B107*(1+'Income Statement Assumptions'!$F$107))),0) -> 26210 | R20: =ROUND(('Income Statement Assumptions'!E$43*('Income Statement Assumptions'!$B107*(1+'Income Statement Assumptions'!$F$107))),0) -> 29486 | S20: =ROUND(('Income Statement Assumptions'!F$43*('Income Statement Assumptions'!$B107*(1+'Income Statement Assumptions'!$F$107))),0) -> 33172 | T20: =ROUND(('Income Statement Assumptions'!G$43*('Income Statement Assumptions'!$B107*(1+'Income Statement Assumptions'!$F$107))),0) -> 37321 | U20: =ROUND(('Income Statement Assumptions'!H$43*('Income Statement Assumptions'!$B107*(1+'Income Statement Assumptions'!$F$107))),0) -> 41986 | V20: =ROUND(('Income Statement Assumptions'!I$43*('Income Statement Assumptions'!$B107*(1+'Income Statement Assumptions'!$F$107))),0) -> 47234 | ... Z20: =ROUND(('Income Statement Assumptions'!M$43*('Income Statement Assumptions'!$B107*(1+'Income Statement Assumptions'!$F$107))),0) -> 75663 | AA20: =SUM(O20:Z20) -> 515252 | AB20: =ROUND(('Income Statement Assumptions'!$B107*(1+'Income Statement Assumptions'!$D107)*(1+'Income Statement Assumptions'!$G107))*'Income Statement Assumptions'!D$48,0) -> 259299 | AC20: =ROUND(('Income Statement Assumptions'!$B107*(1+'Income Statement Assumptions'!$D107)*(1+'Income Statement Assumptions'!$G107))*'Income Statement Assumptions'!G$48,0) -> 324123 | AD20: =ROUND(('Income Statement Assumptions'!$B107*(1+'Income Statement Assumptions'!$D107)*(1+'Income Statement Assumptions'!$G107))*'Income Statement Assumptions'!J$48,0) -> 405156 | AE20: =ROUND(('Income Statement Assumptions'!$B107*(1+'Income Statement Assumptions'!$D107)*(1+'Income Statement Assumptions'!$G107))*'Income Statement Assumptions'!M$48,0) -> 506447 | AF20: =SUM(AB20:AE20) -> 1495025 | AG20: =ROUND(('Income Statement Assumptions'!$B107*(1+'Income Statement Assumptions'!$D107)*(1+'Income Statement Assumptions'!$D107)*(1+'Income Statement Assumptions'!$H107)*'Income Statement Assumptions'!D$53),0) -> 594064 | AH20: =ROUND(('Income Statement Assumptions'!$B107*(1+'Income Statement Assumptions'!$D107)*(1+'Income Statement Assumptions'!$D107)*(1+'Income Statement Assumptions'!$H107)*'Income Statement Assumptions'!G$53),0) -> 683174 | AI20: =ROUND(('Income Statement Assumptions'!$B107*(1+'Income Statement Assumptions'!$D107)*(1+'Income Statement Assumptions'!$D107)*(1+'Income Statement Assumptions'!$H107)*'Income Statement Assumptions'!J$53),0) -> 785650 | AJ20: =ROUND(('Income Statement Assumptions'!$B107*(1+'Income Statement Assumptions'!$D107)*(1+'Income Statement Assumptions'!$D107)*(1+'Income Statement Assumptions'!$H107)*'Income Statement Assumptions'!M$53),0) -> 903497 | AK20: =SUM(AG20:AJ20) -> 2966385 | AL20: =ROUND(('Income Statement Assumptions'!$B107*(1+'Income Statement Assumptions'!$D107)*(1+'Income Statement Assumptions'!$D107)*(1+'Income Statement Assumptions'!D107))*(1+'Income Statement Assumptions'!I107)*'Income Statement Assumptions'!N$58,0) -> 3992134
A21: ='Income Statement Assumptions'!A108 -> 3PL | B21: ='Income Statement Assumptions'!$B108*'Income Statement Assumptions'!B38 -> 0 | C21: ='Income Statement Assumptions'!$B108*'Income Statement Assumptions'!C38 -> 0 | D21: ='Income Statement Assumptions'!$B108*'Income Statement Assumptions'!D38 -> 0 | E21: ='Income Statement Assumptions'!$B108*'Income Statement Assumptions'!E38 -> 0 | F21: ='Income Statement Assumptions'!$B108*'Income Statement Assumptions'!F38 -> 0 | G21: ='Income Statement Assumptions'!$B108*'Income Statement Assumptions'!G38 -> 0 | H21: ='Income Statement Assumptions'!$B108*'Income Statement Assumptions'!H38 -> 1500 | I21: ='Income Statement Assumptions'!$B108*'Income Statement Assumptions'!I38 -> 1500 | ... M21: ='Income Statement Assumptions'!$B108*'Income Statement Assumptions'!M38 -> 2625 | N21: =SUM(B21:M21) -> 12000 | O21: =ROUND(('Income Statement Assumptions'!B$43*('Income Statement Assumptions'!$B108*(1+'Income Statement Assumptions'!$F$107))),0) -> 2958 | P21: =ROUND(('Income Statement Assumptions'!C$43*('Income Statement Assumptions'!$B108*(1+'Income Statement Assumptions'!$F$107))),0) -> 3328 | Q21: =ROUND(('Income Statement Assumptions'!D$43*('Income Statement Assumptions'!$B108*(1+'Income Statement Assumptions'!$F$107))),0) -> 3744 | R21: =ROUND(('Income Statement Assumptions'!E$43*('Income Statement Assumptions'!$B108*(1+'Income Statement Assumptions'!$F$107))),0) -> 4212 | S21: =ROUND(('Income Statement Assumptions'!F$43*('Income Statement Assumptions'!$B108*(1+'Income Statement Assumptions'!$F$107))),0) -> 4739 | T21: =ROUND(('Income Statement Assumptions'!G$43*('Income Statement Assumptions'!$B108*(1+'Income Statement Assumptions'!$F$107))),0) -> 5332 | U21: =ROUND(('Income Statement Assumptions'!H$43*('Income Statement Assumptions'!$B108*(1+'Income Statement Assumptions'!$F$107))),0) -> 5998 | V21: =ROUND(('Income Statement Assumptions'!I$43*('Income Statement Assumptions'!$B108*(1+'Income Statement Assumptions'!$F$107))),0) -> 6748 | ... Z21: =ROUND(('Income Statement Assumptions'!M$43*('Income Statement Assumptions'!$B108*(1+'Income Statement Assumptions'!$F$107))),0) -> 10809 | AA21: =SUM(O21:Z21) -> 73607 | AB21: =ROUND(('Income Statement Assumptions'!$B108*(1+'Income Statement Assumptions'!$D108)*(1+'Income Statement Assumptions'!$G108))*'Income Statement Assumptions'!D$48,0) -> 37043 | AC21: =ROUND(('Income Statement Assumptions'!$B108*(1+'Income Statement Assumptions'!$D108)*(1+'Income Statement Assumptions'!$G108))*'Income Statement Assumptions'!G$48,0) -> 46303 | AD21: =ROUND(('Income Statement Assumptions'!$B108*(1+'Income Statement Assumptions'!$D108)*(1+'Income Statement Assumptions'!$G108))*'Income Statement Assumptions'!J$48,0) -> 57879 | AE21: =ROUND(('Income Statement Assumptions'!$B108*(1+'Income Statement Assumptions'!$D108)*(1+'Income Statement Assumptions'!$G108))*'Income Statement Assumptions'!M$48,0) -> 72350 | AF21: =SUM(AB21:AE21) -> 213575 | AG21: =ROUND(('Income Statement Assumptions'!$B108*(1+'Income Statement Assumptions'!$D108)*(1+'Income Statement Assumptions'!$D108)*(1+'Income Statement Assumptions'!$H108)*'Income Statement Assumptions'!D$53),0) -> 84866 | AH21: =ROUND(('Income Statement Assumptions'!$B108*(1+'Income Statement Assumptions'!$D108)*(1+'Income Statement Assumptions'!$D108)*(1+'Income Statement Assumptions'!$H108)*'Income Statement Assumptions'!G$53),0) -> 97596 | AI21: =ROUND(('Income Statement Assumptions'!$B108*(1+'Income Statement Assumptions'!$D108)*(1+'Income Statement Assumptions'!$D108)*(1+'Income Statement Assumptions'!$H108)*'Income Statement Assumptions'!J$53),0) -> 112236 | AJ21: =ROUND(('Income Statement Assumptions'!$B108*(1+'Income Statement Assumptions'!$D108)*(1+'Income Statement Assumptions'!$D108)*(1+'Income Statement Assumptions'!$H108)*'Income Statement Assumptions'!M$53),0) -> 129071 | AK21: =SUM(AG21:AJ21) -> 423769 | AL21: =ROUND(('Income Statement Assumptions'!$B108*(1+'Income Statement Assumptions'!$D108)*(1+'Income Statement Assumptions'!$D108)*(1+'Income Statement Assumptions'!D108))*(1+'Income Statement Assumptions'!I108)*'Income Statement Assumptions'!N$58,0) -> 570305
A22: ='Income Statement Assumptions'!A109 -> CC fee | B22: ='Income Statement Assumptions'!$B109*'Income Statement Assumptions'!B38 -> 0 | C22: ='Income Statement Assumptions'!$B109*'Income Statement Assumptions'!C38 -> 0 | D22: ='Income Statement Assumptions'!$B109*'Income Statement Assumptions'!D38 -> 0 | E22: ='Income Statement Assumptions'!$B109*'Income Statement Assumptions'!E38 -> 0 | F22: ='Income Statement Assumptions'!$B109*'Income Statement Assumptions'!F38 -> 0 | G22: ='Income Statement Assumptions'!$B109*'Income Statement Assumptions'!G38 -> 0 | H22: ='Income Statement Assumptions'!$B109*'Income Statement Assumptions'!H38 -> 0 | I22: ='Income Statement Assumptions'!$B109*'Income Statement Assumptions'!I38 -> 0 | ... M22: ='Income Statement Assumptions'!$B109*'Income Statement Assumptions'!M38 -> 0 | N22: =SUM(B22:M22) -> 0 | O22: =ROUND(('Income Statement Assumptions'!B$43*('Income Statement Assumptions'!$B109*(1+'Income Statement Assumptions'!$F$107))),0) -> 0 | P22: =ROUND(('Income Statement Assumptions'!C$43*('Income Statement Assumptions'!$B109*(1+'Income Statement Assumptions'!$F$107))),0) -> 0 | Q22: =ROUND(('Income Statement Assumptions'!D$43*('Income Statement Assumptions'!$B109*(1+'Income Statement Assumptions'!$F$107))),0) -> 0 | R22: =ROUND(('Income Statement Assumptions'!E$43*('Income Statement Assumptions'!$B109*(1+'Income Statement Assumptions'!$F$107))),0) -> 0 | S22: =ROUND(('Income Statement Assumptions'!F$43*('Income Statement Assumptions'!$B109*(1+'Income Statement Assumptions'!$F$107))),0) -> 0 | T22: =ROUND(('Income Statement Assumptions'!G$43*('Income Statement Assumptions'!$B109*(1+'Income Statement Assumptions'!$F$107))),0) -> 0 | U22: =ROUND(('Income Statement Assumptions'!H$43*('Income Statement Assumptions'!$B109*(1+'Income Statement Assumptions'!$F$107))),0) -> 0 | V22: =ROUND(('Income Statement Assumptions'!I$43*('Income Statement Assumptions'!$B109*(1+'Income Statement Assumptions'!$F$107))),0) -> 0 | ... Z22: =ROUND(('Income Statement Assumptions'!M$43*('Income Statement Assumptions'!$B109*(1+'Income Statement Assumptions'!$F$107))),0) -> 0 | AA22: =SUM(O22:Z22) -> 0 | AB22: =ROUND(('Income Statement Assumptions'!$B109*(1+'Income Statement Assumptions'!$D109)*(1+'Income Statement Assumptions'!$G109))*'Income Statement Assumptions'!D$48,0) -> 0 | AC22: =ROUND(('Income Statement Assumptions'!$B109*(1+'Income Statement Assumptions'!$D109)*(1+'Income Statement Assumptions'!$G109))*'Income Statement Assumptions'!G$48,0) -> 0 | AD22: =ROUND(('Income Statement Assumptions'!$B109*(1+'Income Statement Assumptions'!$D109)*(1+'Income Statement Assumptions'!$G109))*'Income Statement Assumptions'!J$48,0) -> 0 | AE22: =ROUND(('Income Statement Assumptions'!$B109*(1+'Income Statement Assumptions'!$D109)*(1+'Income Statement Assumptions'!$G109))*'Income Statement Assumptions'!M$48,0) -> 0 | AF22: =SUM(AB22:AE22) -> 0 | AG22: =ROUND(('Income Statement Assumptions'!$B109*(1+'Income Statement Assumptions'!$D109)*(1+'Income Statement Assumptions'!$D109)*(1+'Income Statement Assumptions'!$H109)*'Income Statement Assumptions'!D$53),0) -> 0 | AH22: =ROUND(('Income Statement Assumptions'!$B109*(1+'Income Statement Assumptions'!$D109)*(1+'Income Statement Assumptions'!$D109)*(1+'Income Statement Assumptions'!$H109)*'Income Statement Assumptions'!G$53),0) -> 0 | AI22: =ROUND(('Income Statement Assumptions'!$B109*(1+'Income Statement Assumptions'!$D109)*(1+'Income Statement Assumptions'!$D109)*(1+'Income Statement Assumptions'!$H109)*'Income Statement Assumptions'!J$53),0) -> 0 | AJ22: =ROUND(('Income Statement Assumptions'!$B109*(1+'Income Statement Assumptions'!$D109)*(1+'Income Statement Assumptions'!$D109)*(1+'Income Statement Assumptions'!$H109)*'Income Statement Assumptions'!M$53),0) -> 0 | AK22: =SUM(AG22:AJ22) -> 0 | AL22: =ROUND(('Income Statement Assumptions'!$B109*(1+'Income Statement Assumptions'!$D109)*(1+'Income Statement Assumptions'!$D109)*(1+'Income Statement Assumptions'!D109))*(1+'Income Statement Assumptions'!I109)*'Income Statement Assumptions'!N$58,0) -> 0
A23: ='Income Statement Assumptions'!A110 -> warranty | B23: ='Income Statement Assumptions'!$B110*'Income Statement Assumptions'!B38 -> 0 | C23: ='Income Statement Assumptions'!$B110*'Income Statement Assumptions'!C38 -> 0 | D23: ='Income Statement Assumptions'!$B110*'Income Statement Assumptions'!D38 -> 0 | E23: ='Income Statement Assumptions'!$B110*'Income Statement Assumptions'!E38 -> 0 | F23: ='Income Statement Assumptions'!$B110*'Income Statement Assumptions'!F38 -> 0 | G23: ='Income Statement Assumptions'!$B110*'Income Statement Assumptions'!G38 -> 0 | H23: ='Income Statement Assumptions'!$B110*'Income Statement Assumptions'!H38 -> 300 | I23: ='Income Statement Assumptions'!$B110*'Income Statement Assumptions'!I38 -> 300 | ... M23: ='Income Statement Assumptions'!$B110*'Income Statement Assumptions'!M38 -> 525 | N23: =SUM(B23:M23) -> 2400 | O23: =ROUND(('Income Statement Assumptions'!B$43*('Income Statement Assumptions'!$B110*(1+'Income Statement Assumptions'!$F$107))),0) -> 592 | P23: =ROUND(('Income Statement Assumptions'!C$43*('Income Statement Assumptions'!$B110*(1+'Income Statement Assumptions'!$F$107))),0) -> 666 | Q23: =ROUND(('Income Statement Assumptions'!D$43*('Income Statement Assumptions'!$B110*(1+'Income Statement Assumptions'!$F$107))),0) -> 749 | R23: =ROUND(('Income Statement Assumptions'!E$43*('Income Statement Assumptions'!$B110*(1+'Income Statement Assumptions'!$F$107))),0) -> 842 | S23: =ROUND(('Income Statement Assumptions'!F$43*('Income Statement Assumptions'!$B110*(1+'Income Statement Assumptions'!$F$107))),0) -> 948 | T23: =ROUND(('Income Statement Assumptions'!G$43*('Income Statement Assumptions'!$B110*(1+'Income Statement Assumptions'!$F$107))),0) -> 1066 | U23: =ROUND(('Income Statement Assumptions'!H$43*('Income Statement Assumptions'!$B110*(1+'Income Statement Assumptions'!$F$107))),0) -> 1200 | V23: =ROUND(('Income Statement Assumptions'!I$43*('Income Statement Assumptions'!$B110*(1+'Income Statement Assumptions'!$F$107))),0) -> 1350 | ... Z23: =ROUND(('Income Statement Assumptions'!M$43*('Income Statement Assumptions'!$B110*(1+'Income Statement Assumptions'!$F$107))),0) -> 2162 | AA23: =SUM(O23:Z23) -> 14723 | AB23: =ROUND(('Income Statement Assumptions'!$B110*(1+'Income Statement Assumptions'!$D110)*(1+'Income Statement Assumptions'!$G110))*'Income Statement Assumptions'!D$48,0) -> 7683 | AC23: =ROUND(('Income Statement Assumptions'!$B110*(1+'Income Statement Assumptions'!$D110)*(1+'Income Statement Assumptions'!$G110))*'Income Statement Assumptions'!G$48,0) -> 9604 | AD23: =ROUND(('Income Statement Assumptions'!$B110*(1+'Income Statement Assumptions'!$D110)*(1+'Income Statement Assumptions'!$G110))*'Income Statement Assumptions'!J$48,0) -> 12005 | AE23: =ROUND(('Income Statement Assumptions'!$B110*(1+'Income Statement Assumptions'!$D110)*(1+'Income Statement Assumptions'!$G110))*'Income Statement Assumptions'!M$48,0) -> 15007 | AF23: =SUM(AB23:AE23) -> 44299 | AG23: =ROUND(('Income Statement Assumptions'!$B110*(1+'Income Statement Assumptions'!$D110)*(1+'Income Statement Assumptions'!$D110)*(1+'Income Statement Assumptions'!$H110)*'Income Statement Assumptions'!D$53),0) -> 18121 | AH23: =ROUND(('Income Statement Assumptions'!$B110*(1+'Income Statement Assumptions'!$D110)*(1+'Income Statement Assumptions'!$D110)*(1+'Income Statement Assumptions'!$H110)*'Income Statement Assumptions'!G$53),0) -> 20839 | AI23: =ROUND(('Income Statement Assumptions'!$B110*(1+'Income Statement Assumptions'!$D110)*(1+'Income Statement Assumptions'!$D110)*(1+'Income Statement Assumptions'!$H110)*'Income Statement Assumptions'!J$53),0) -> 23964 | AJ23: =ROUND(('Income Statement Assumptions'!$B110*(1+'Income Statement Assumptions'!$D110)*(1+'Income Statement Assumptions'!$D110)*(1+'Income Statement Assumptions'!$H110)*'Income Statement Assumptions'!M$53),0) -> 27559 | AK23: =SUM(AG23:AJ23) -> 90483 | AL23: =ROUND(('Income Statement Assumptions'!$B110*(1+'Income Statement Assumptions'!$D110)*(1+'Income Statement Assumptions'!$D110)*(1+'Income Statement Assumptions'!D110))*(1+'Income Statement Assumptions'!I110)*'Income Statement Assumptions'!N$58,0) -> 128084
A25: =A8 -> Product 3 | AA25: =SUM(O25:Z25) -> 0
A26: ='Income Statement Assumptions'!A113 -> repair labor | B26: ='Income Statement Assumptions'!$B113*'Income Statement Assumptions'!B70 -> 0 | C26: ='Income Statement Assumptions'!$B113*'Income Statement Assumptions'!C70 -> 0 | D26: ='Income Statement Assumptions'!$B113*'Income Statement Assumptions'!D70 -> 0 | E26: ='Income Statement Assumptions'!$B113*'Income Statement Assumptions'!E70 -> 0 | F26: ='Income Statement Assumptions'!$B113*'Income Statement Assumptions'!F70 -> 0 | G26: ='Income Statement Assumptions'!$B113*'Income Statement Assumptions'!G70 -> 0 | H26: ='Income Statement Assumptions'!$B113*'Income Statement Assumptions'!H70 -> 210 | I26: ='Income Statement Assumptions'!$B113*'Income Statement Assumptions'!I70 -> 215 | ... M26: ='Income Statement Assumptions'!$B113*'Income Statement Assumptions'!M70 -> 400 | N26: =SUM(B26:M26) -> 1795 | O26: =ROUND(('Income Statement Assumptions'!B$75*('Income Statement Assumptions'!$B113*(1+'Income Statement Assumptions'!$F$113))),0) -> 454 | P26: =ROUND(('Income Statement Assumptions'!C$75*('Income Statement Assumptions'!$B113*(1+'Income Statement Assumptions'!$F$113))),0) -> 510 | Q26: =ROUND(('Income Statement Assumptions'!D$75*('Income Statement Assumptions'!$B113*(1+'Income Statement Assumptions'!$F$113))),0) -> 574 | R26: =ROUND(('Income Statement Assumptions'!E$75*('Income Statement Assumptions'!$B113*(1+'Income Statement Assumptions'!$F$113))),0) -> 646 | S26: =ROUND(('Income Statement Assumptions'!F$75*('Income Statement Assumptions'!$B113*(1+'Income Statement Assumptions'!$F$113))),0) -> 727 | T26: =ROUND(('Income Statement Assumptions'!G$75*('Income Statement Assumptions'!$B113*(1+'Income Statement Assumptions'!$F$113))),0) -> 817 | U26: =ROUND(('Income Statement Assumptions'!H$75*('Income Statement Assumptions'!$B113*(1+'Income Statement Assumptions'!$F$113))),0) -> 920 | V26: =ROUND(('Income Statement Assumptions'!I$75*('Income Statement Assumptions'!$B113*(1+'Income Statement Assumptions'!$F$113))),0) -> 1035 | ... Z26: =ROUND(('Income Statement Assumptions'!M$75*('Income Statement Assumptions'!$B113*(1+'Income Statement Assumptions'!$F$113))),0) -> 1657 | AA26: =SUM(O26:Z26) -> 11286 | AB26: =ROUND(('Income Statement Assumptions'!$B113*(1+'Income Statement Assumptions'!$D113)*(1+'Income Statement Assumptions'!$G113))*'Income Statement Assumptions'!D$80,0) -> 6205 | AC26: =ROUND(('Income Statement Assumptions'!$B113*(1+'Income Statement Assumptions'!$D113)*(1+'Income Statement Assumptions'!$G113))*'Income Statement Assumptions'!G$80,0) -> 7756 | AD26: =ROUND(('Income Statement Assumptions'!$B113*(1+'Income Statement Assumptions'!$D113)*(1+'Income Statement Assumptions'!$G113))*'Income Statement Assumptions'!J$80,0) -> 9695 | AE26: =ROUND(('Income Statement Assumptions'!$B113*(1+'Income Statement Assumptions'!$D113)*(1+'Income Statement Assumptions'!$G113))*'Income Statement Assumptions'!M$80,0) -> 12119 | AF26: =SUM(AB26:AE26) -> 35775 | AG26: =ROUND(('Income Statement Assumptions'!$B113*(1+'Income Statement Assumptions'!$D113)*(1+'Income Statement Assumptions'!$D113)*(1+'Income Statement Assumptions'!$H113)*'Income Statement Assumptions'!D$85),0) -> 15330 | AH26: =ROUND(('Income Statement Assumptions'!$B113*(1+'Income Statement Assumptions'!$D113)*(1+'Income Statement Assumptions'!$D113)*(1+'Income Statement Assumptions'!$H113)*'Income Statement Assumptions'!G$85),0) -> 17630 | AI26: =ROUND(('Income Statement Assumptions'!$B113*(1+'Income Statement Assumptions'!$D113)*(1+'Income Statement Assumptions'!$D113)*(1+'Income Statement Assumptions'!$H113)*'Income Statement Assumptions'!J$85),0) -> 20275 | AJ26: =ROUND(('Income Statement Assumptions'!$B113*(1+'Income Statement Assumptions'!$D113)*(1+'Income Statement Assumptions'!$D113)*(1+'Income Statement Assumptions'!$H113)*'Income Statement Assumptions'!M$85),0) -> 23316 | AK26: =SUM(AG26:AJ26) -> 76551 | AL26: =ROUND(('Income Statement Assumptions'!$B113*(1+'Income Statement Assumptions'!$D113)*(1+'Income Statement Assumptions'!$D113)*(1+'Income Statement Assumptions'!D113))*(1+'Income Statement Assumptions'!I113)*'Income Statement Assumptions'!N$90,0) -> 117478
A27: ='Income Statement Assumptions'!A114 -> shipping | B27: ='Income Statement Assumptions'!$B114*'Income Statement Assumptions'!B70 -> 0 | C27: ='Income Statement Assumptions'!$B114*'Income Statement Assumptions'!C70 -> 0 | D27: ='Income Statement Assumptions'!$B114*'Income Statement Assumptions'!D70 -> 0 | E27: ='Income Statement Assumptions'!$B114*'Income Statement Assumptions'!E70 -> 0 | F27: ='Income Statement Assumptions'!$B114*'Income Statement Assumptions'!F70 -> 0 | G27: ='Income Statement Assumptions'!$B114*'Income Statement Assumptions'!G70 -> 0 | H27: ='Income Statement Assumptions'!$B114*'Income Statement Assumptions'!H70 -> 105 | I27: ='Income Statement Assumptions'!$B114*'Income Statement Assumptions'!I70 -> 107.5 | ... M27: ='Income Statement Assumptions'!$B114*'Income Statement Assumptions'!M70 -> 200 | N27: =SUM(B27:M27) -> 897.5 | O27: =ROUND(('Income Statement Assumptions'!B$75*('Income Statement Assumptions'!$B114*(1+'Income Statement Assumptions'!$F$113))),0) -> 227 | P27: =ROUND(('Income Statement Assumptions'!C$75*('Income Statement Assumptions'!$B114*(1+'Income Statement Assumptions'!$F$113))),0) -> 255 | Q27: =ROUND(('Income Statement Assumptions'!D$75*('Income Statement Assumptions'!$B114*(1+'Income Statement Assumptions'!$F$113))),0) -> 287 | R27: =ROUND(('Income Statement Assumptions'!E$75*('Income Statement Assumptions'!$B114*(1+'Income Statement Assumptions'!$F$113))),0) -> 323 | S27: =ROUND(('Income Statement Assumptions'!F$75*('Income Statement Assumptions'!$B114*(1+'Income Statement Assumptions'!$F$113))),0) -> 363 | T27: =ROUND(('Income Statement Assumptions'!G$75*('Income Statement Assumptions'!$B114*(1+'Income Statement Assumptions'!$F$113))),0) -> 409 | U27: =ROUND(('Income Statement Assumptions'!H$75*('Income Statement Assumptions'!$B114*(1+'Income Statement Assumptions'!$F$113))),0) -> 460 | V27: =ROUND(('Income Statement Assumptions'!I$75*('Income Statement Assumptions'!$B114*(1+'Income Statement Assumptions'!$F$113))),0) -> 517 | ... Z27: =ROUND(('Income Statement Assumptions'!M$75*('Income Statement Assumptions'!$B114*(1+'Income Statement Assumptions'!$F$113))),0) -> 829 | AA27: =SUM(O27:Z27) -> 5643 | AB27: =ROUND(('Income Statement Assumptions'!$B114*(1+'Income Statement Assumptions'!$D114)*(1+'Income Statement Assumptions'!$G114))*'Income Statement Assumptions'!D$80,0) -> 2925 | AC27: =ROUND(('Income Statement Assumptions'!$B114*(1+'Income Statement Assumptions'!$D114)*(1+'Income Statement Assumptions'!$G114))*'Income Statement Assumptions'!G$80,0) -> 3657 | AD27: =ROUND(('Income Statement Assumptions'!$B114*(1+'Income Statement Assumptions'!$D114)*(1+'Income Statement Assumptions'!$G114))*'Income Statement Assumptions'!J$80,0) -> 4571 | AE27: =ROUND(('Income Statement Assumptions'!$B114*(1+'Income Statement Assumptions'!$D114)*(1+'Income Statement Assumptions'!$G114))*'Income Statement Assumptions'!M$80,0) -> 5714 | AF27: =SUM(AB27:AE27) -> 16867 | AG27: =ROUND(('Income Statement Assumptions'!$B114*(1+'Income Statement Assumptions'!$D114)*(1+'Income Statement Assumptions'!$D114)*(1+'Income Statement Assumptions'!$H114)*'Income Statement Assumptions'!D$85),0) -> 6899 | AH27: =ROUND(('Income Statement Assumptions'!$B114*(1+'Income Statement Assumptions'!$D114)*(1+'Income Statement Assumptions'!$D114)*(1+'Income Statement Assumptions'!$H114)*'Income Statement Assumptions'!G$85),0) -> 7934 | AI27: =ROUND(('Income Statement Assumptions'!$B114*(1+'Income Statement Assumptions'!$D114)*(1+'Income Statement Assumptions'!$D114)*(1+'Income Statement Assumptions'!$H114)*'Income Statement Assumptions'!J$85),0) -> 9124 | AJ27: =ROUND(('Income Statement Assumptions'!$B114*(1+'Income Statement Assumptions'!$D114)*(1+'Income Statement Assumptions'!$D114)*(1+'Income Statement Assumptions'!$H114)*'Income Statement Assumptions'!M$85),0) -> 10493 | AK27: =SUM(AG27:AJ27) -> 34450 | AL27: =ROUND(('Income Statement Assumptions'!$B114*(1+'Income Statement Assumptions'!$D114)*(1+'Income Statement Assumptions'!$D114)*(1+'Income Statement Assumptions'!D114))*(1+'Income Statement Assumptions'!I114)*'Income Statement Assumptions'!N$90,0) -> 48765
A28: ='Income Statement Assumptions'!A115 -> 0 | B28: ='Income Statement Assumptions'!$B115*'Income Statement Assumptions'!B70 -> 0 | C28: ='Income Statement Assumptions'!$B115*'Income Statement Assumptions'!C70 -> 0 | D28: ='Income Statement Assumptions'!$B115*'Income Statement Assumptions'!D70 -> 0 | E28: ='Income Statement Assumptions'!$B115*'Income Statement Assumptions'!E70 -> 0 | F28: ='Income Statement Assumptions'!$B115*'Income Statement Assumptions'!F70 -> 0 | G28: ='Income Statement Assumptions'!$B115*'Income Statement Assumptions'!G70 -> 0 | H28: ='Income Statement Assumptions'!$B115*'Income Statement Assumptions'!H70 -> 0 | I28: ='Income Statement Assumptions'!$B115*'Income Statement Assumptions'!I70 -> 0 | ... M28: ='Income Statement Assumptions'!$B115*'Income Statement Assumptions'!M70 -> 0 | N28: =SUM(B28:M28) -> 0 | O28: =ROUND(('Income Statement Assumptions'!B$75*('Income Statement Assumptions'!$B115*(1+'Income Statement Assumptions'!$F$113))),0) -> 0 | P28: =ROUND(('Income Statement Assumptions'!C$75*('Income Statement Assumptions'!$B115*(1+'Income Statement Assumptions'!$F$113))),0) -> 0 | Q28: =ROUND(('Income Statement Assumptions'!D$75*('Income Statement Assumptions'!$B115*(1+'Income Statement Assumptions'!$F$113))),0) -> 0 | R28: =ROUND(('Income Statement Assumptions'!E$75*('Income Statement Assumptions'!$B115*(1+'Income Statement Assumptions'!$F$113))),0) -> 0 | S28: =ROUND(('Income Statement Assumptions'!F$75*('Income Statement Assumptions'!$B115*(1+'Income Statement Assumptions'!$F$113))),0) -> 0 | T28: =ROUND(('Income Statement Assumptions'!G$75*('Income Statement Assumptions'!$B115*(1+'Income Statement Assumptions'!$F$113))),0) -> 0 | U28: =ROUND(('Income Statement Assumptions'!H$75*('Income Statement Assumptions'!$B115*(1+'Income Statement Assumptions'!$F$113))),0) -> 0 | V28: =ROUND(('Income Statement Assumptions'!I$75*('Income Statement Assumptions'!$B115*(1+'Income Statement Assumptions'!$F$113))),0) -> 0 | ... Z28: =ROUND(('Income Statement Assumptions'!M$75*('Income Statement Assumptions'!$B115*(1+'Income Statement Assumptions'!$F$113))),0) -> 0 | AA28: =SUM(O28:Z28) -> 0 | AB28: =ROUND(('Income Statement Assumptions'!$B115*(1+'Income Statement Assumptions'!$D115)*(1+'Income Statement Assumptions'!$G115))*'Income Statement Assumptions'!D$80,0) -> 0 | AC28: =ROUND(('Income Statement Assumptions'!$B115*(1+'Income Statement Assumptions'!$D115)*(1+'Income Statement Assumptions'!$G115))*'Income Statement Assumptions'!G$80,0) -> 0 | AD28: =ROUND(('Income Statement Assumptions'!$B115*(1+'Income Statement Assumptions'!$D115)*(1+'Income Statement Assumptions'!$G115))*'Income Statement Assumptions'!J$80,0) -> 0 | AE28: =ROUND(('Income Statement Assumptions'!$B115*(1+'Income Statement Assumptions'!$D115)*(1+'Income Statement Assumptions'!$G115))*'Income Statement Assumptions'!M$80,0) -> 0 | AF28: =SUM(AB28:AE28) -> 0 | AG28: =ROUND(('Income Statement Assumptions'!$B115*(1+'Income Statement Assumptions'!$D115)*(1+'Income Statement Assumptions'!$D115)*(1+'Income Statement Assumptions'!$H115)*'Income Statement Assumptions'!D$85),0) -> 0 | AH28: =ROUND(('Income Statement Assumptions'!$B115*(1+'Income Statement Assumptions'!$D115)*(1+'Income Statement Assumptions'!$D115)*(1+'Income Statement Assumptions'!$H115)*'Income Statement Assumptions'!G$85),0) -> 0 | AI28: =ROUND(('Income Statement Assumptions'!$B115*(1+'Income Statement Assumptions'!$D115)*(1+'Income Statement Assumptions'!$D115)*(1+'Income Statement Assumptions'!$H115)*'Income Statement Assumptions'!J$85),0) -> 0 | AJ28: =ROUND(('Income Statement Assumptions'!$B115*(1+'Income Statement Assumptions'!$D115)*(1+'Income Statement Assumptions'!$D115)*(1+'Income Statement Assumptions'!$H115)*'Income Statement Assumptions'!M$85),0) -> 0 | AK28: =SUM(AG28:AJ28) -> 0 | AL28: =ROUND(('Income Statement Assumptions'!$B115*(1+'Income Statement Assumptions'!$D115)*(1+'Income Statement Assumptions'!$D115)*(1+'Income Statement Assumptions'!D115))*(1+'Income Statement Assumptions'!I115)*'Income Statement Assumptions'!N$90,0) -> 0
A29: ='Income Statement Assumptions'!A116 -> 0 | B29: ='Income Statement Assumptions'!$B116*'Income Statement Assumptions'!B70 -> 0 | C29: ='Income Statement Assumptions'!$B116*'Income Statement Assumptions'!C70 -> 0 | D29: ='Income Statement Assumptions'!$B116*'Income Statement Assumptions'!D70 -> 0 | E29: ='Income Statement Assumptions'!$B116*'Income Statement Assumptions'!E70 -> 0 | F29: ='Income Statement Assumptions'!$B116*'Income Statement Assumptions'!F70 -> 0 | G29: ='Income Statement Assumptions'!$B116*'Income Statement Assumptions'!G70 -> 0 | H29: ='Income Statement Assumptions'!$B116*'Income Statement Assumptions'!H70 -> 0 | I29: ='Income Statement Assumptions'!$B116*'Income Statement Assumptions'!I70 -> 0 | ... M29: ='Income Statement Assumptions'!$B116*'Income Statement Assumptions'!M70 -> 0 | N29: =SUM(B29:M29) -> 0 | O29: =ROUND(('Income Statement Assumptions'!B$75*('Income Statement Assumptions'!$B116*(1+'Income Statement Assumptions'!$F$113))),0) -> 0 | P29: =ROUND(('Income Statement Assumptions'!C$75*('Income Statement Assumptions'!$B116*(1+'Income Statement Assumptions'!$F$113))),0) -> 0 | Q29: =ROUND(('Income Statement Assumptions'!D$75*('Income Statement Assumptions'!$B116*(1+'Income Statement Assumptions'!$F$113))),0) -> 0 | R29: =ROUND(('Income Statement Assumptions'!E$75*('Income Statement Assumptions'!$B116*(1+'Income Statement Assumptions'!$F$113))),0) -> 0 | S29: =ROUND(('Income Statement Assumptions'!F$75*('Income Statement Assumptions'!$B116*(1+'Income Statement Assumptions'!$F$113))),0) -> 0 | T29: =ROUND(('Income Statement Assumptions'!G$75*('Income Statement Assumptions'!$B116*(1+'Income Statement Assumptions'!$F$113))),0) -> 0 | U29: =ROUND(('Income Statement Assumptions'!H$75*('Income Statement Assumptions'!$B116*(1+'Income Statement Assumptions'!$F$113))),0) -> 0 | V29: =ROUND(('Income Statement Assumptions'!I$75*('Income Statement Assumptions'!$B116*(1+'Income Statement Assumptions'!$F$113))),0) -> 0 | ... Z29: =ROUND(('Income Statement Assumptions'!M$75*('Income Statement Assumptions'!$B116*(1+'Income Statement Assumptions'!$F$113))),0) -> 0 | AA29: =SUM(O29:Z29) -> 0 | AB29: =ROUND(('Income Statement Assumptions'!$B116*(1+'Income Statement Assumptions'!$D116)*(1+'Income Statement Assumptions'!$G116))*'Income Statement Assumptions'!D$80,0) -> 0 | AC29: =ROUND(('Income Statement Assumptions'!$B116*(1+'Income Statement Assumptions'!$D116)*(1+'Income Statement Assumptions'!$G116))*'Income Statement Assumptions'!G$80,0) -> 0 | AD29: =ROUND(('Income Statement Assumptions'!$B116*(1+'Income Statement Assumptions'!$D116)*(1+'Income Statement Assumptions'!$G116))*'Income Statement Assumptions'!J$80,0) -> 0 | AE29: =ROUND(('Income Statement Assumptions'!$B116*(1+'Income Statement Assumptions'!$D116)*(1+'Income Statement Assumptions'!$G116))*'Income Statement Assumptions'!M$80,0) -> 0 | AF29: =SUM(AB29:AE29) -> 0 | AG29: =ROUND(('Income Statement Assumptions'!$B116*(1+'Income Statement Assumptions'!$D116)*(1+'Income Statement Assumptions'!$D116)*(1+'Income Statement Assumptions'!$H116)*'Income Statement Assumptions'!D$85),0) -> 0 | AH29: =ROUND(('Income Statement Assumptions'!$B116*(1+'Income Statement Assumptions'!$D116)*(1+'Income Statement Assumptions'!$D116)*(1+'Income Statement Assumptions'!$H116)*'Income Statement Assumptions'!G$85),0) -> 0 | AI29: =ROUND(('Income Statement Assumptions'!$B116*(1+'Income Statement Assumptions'!$D116)*(1+'Income Statement Assumptions'!$D116)*(1+'Income Statement Assumptions'!$H116)*'Income Statement Assumptions'!J$85),0) -> 0 | AJ29: =ROUND(('Income Statement Assumptions'!$B116*(1+'Income Statement Assumptions'!$D116)*(1+'Income Statement Assumptions'!$D116)*(1+'Income Statement Assumptions'!$H116)*'Income Statement Assumptions'!M$85),0) -> 0 | AK29: =SUM(AG29:AJ29) -> 0 | AL29: =ROUND(('Income Statement Assumptions'!$B116*(1+'Income Statement Assumptions'!$D116)*(1+'Income Statement Assumptions'!$D116)*(1+'Income Statement Assumptions'!D116))*(1+'Income Statement Assumptions'!I116)*'Income Statement Assumptions'!N$90,0) -> 0
A31: Total COGS | B31: =SUM(B14:B29) -> 0 | C31: =SUM(C14:C29) -> 0 | D31: =SUM(D14:D29) -> 0 | E31: =SUM(E14:E29) -> 0 | F31: =SUM(F14:F29) -> 0 | G31: =SUM(G14:G29) -> 0 | H31: =SUM(H14:H29) -> 13290 | I31: =SUM(I14:I29) -> 13635 | ... AL31: =SUM(AL14:AL29) -> 5592927
A33: Total Gross Margin | B33: =B10-B31 -> 0 | C33: =C10-C31 -> 0 | D33: =D10-D31 -> 0 | E33: =E10-E31 -> 0 | F33: =F10-F31 -> 0 | G33: =G10-G31 -> 0 | H33: =H10-H31 -> 10810 | I33: =I10-I31 -> 11515 | ... AL33: =AL10-AL31 -> 6502711
A35: ='Income Statement Assumptions'!A120 -> Administrative:
A36: ='Income Statement Assumptions'!A121 -> Start up Expenses | B36: ='Income Statement Assumptions'!B121 -> 125000 | C36: 0 | D36: 0 | E36: 0 | F36: 0 | G36: 0 | H36: 0 | I36: 0 | J36: 0 | K36: 0 | L36: 0 | M36: 0 | N36: =SUM(B36:M36) -> 125000 | O36: 0 | P36: 0 | Q36: 0 | R36: 0 | S36: 0 | T36: 0 | U36: 0 | V36: 0 | W36: 0 | X36: 0 | Y36: 0 | Z36: 0 | AA36: =SUM(O36:Z36) -> 0 | AB36: 0 | AC36: 0 | AD36: 0 | AE36: 0 | AF36: =SUM(AB36:AE36) -> 0 | AG36: 0 | AH36: 0 | AI36: 0 | AJ36: 0 | AK36: =SUM(AG36:AJ36) -> 0 | AL36: 0
A37: ='Income Statement Assumptions'!A122 -> Rent of Office Plus Utilities | B37: =ROUND('Income Statement Assumptions'!$B122/12,0) -> 2000 | C37: =ROUND('Income Statement Assumptions'!$B122/12,0) -> 2000 | D37: =ROUND('Income Statement Assumptions'!$B122/12,0) -> 2000 | E37: =ROUND('Income Statement Assumptions'!$B122/12,0) -> 2000 | F37: =ROUND('Income Statement Assumptions'!$B122/12,0) -> 2000 | G37: =ROUND('Income Statement Assumptions'!$B122/12,0) -> 2000 | H37: =ROUND('Income Statement Assumptions'!$B122/12,0) -> 2000 | I37: =ROUND('Income Statement Assumptions'!$B122/12,0) -> 2000 | ... M37: =ROUND('Income Statement Assumptions'!$B122/12,0) -> 2000 | N37: =SUM(B37:M37) -> 24000 | O37: =ROUND(('Income Statement Assumptions'!$B122*(1+'Income Statement Assumptions'!$F$122))/12,0) -> 2008 | P37: =ROUND(('Income Statement Assumptions'!$B122*(1+'Income Statement Assumptions'!$F$122))/12,0) -> 2008 | Q37: =ROUND(('Income Statement Assumptions'!$B122*(1+'Income Statement Assumptions'!$F$122))/12,0) -> 2008 | R37: =ROUND(('Income Statement Assumptions'!$B122*(1+'Income Statement Assumptions'!$F$122))/12,0) -> 2008 | S37: =ROUND(('Income Statement Assumptions'!$B122*(1+'Income Statement Assumptions'!$F$122))/12,0) -> 2008 | T37: =ROUND(('Income Statement Assumptions'!$B122*(1+'Income Statement Assumptions'!$F$122))/12,0) -> 2008 | U37: =ROUND(('Income Statement Assumptions'!$B122*(1+'Income Statement Assumptions'!$F$122))/12,0) -> 2008 | V37: =ROUND(('Income Statement Assumptions'!$B122*(1+'Income Statement Assumptions'!$F$122))/12,0) -> 2008 | ... Z37: =ROUND(('Income Statement Assumptions'!$B122*(1+'Income Statement Assumptions'!$F$122))/12,0) -> 2008 | AA37: =SUM(O37:Z37) -> 24096 | AB37: =ROUND(('Income Statement Assumptions'!$B122*(1+'Income Statement Assumptions'!$D122)*(1+'Income Statement Assumptions'!$G122)/4),0) -> 6379 | AC37: =ROUND(('Income Statement Assumptions'!$B122*(1+'Income Statement Assumptions'!$D122)*(1+'Income Statement Assumptions'!$G122)/4),0) -> 6379 | AD37: =ROUND(('Income Statement Assumptions'!$B122*(1+'Income Statement Assumptions'!$D122)*(1+'Income Statement Assumptions'!$G122)/4),0) -> 6379 | AE37: =ROUND(('Income Statement Assumptions'!$B122*(1+'Income Statement Assumptions'!$D122)*(1+'Income Statement Assumptions'!$G122)/4),0) -> 6379 | AF37: =SUM(AB37:AE37) -> 25516 | AG37: =ROUND(('Income Statement Assumptions'!$B122*(1+'Income Statement Assumptions'!$D122)*(1+'Income Statement Assumptions'!$D122)*(1+'Income Statement Assumptions'!$H122)/4),0) -> 6698 | AH37: =ROUND(('Income Statement Assumptions'!$B122*(1+'Income Statement Assumptions'!$D122)*(1+'Income Statement Assumptions'!$D122)*(1+'Income Statement Assumptions'!$H122)/4),0) -> 6698 | AI37: =ROUND(('Income Statement Assumptions'!$B122*(1+'Income Statement Assumptions'!$D122)*(1+'Income Statement Assumptions'!$D122)*(1+'Income Statement Assumptions'!$H122)/4),0) -> 6698 | AJ37: =ROUND(('Income Statement Assumptions'!$B122*(1+'Income Statement Assumptions'!$D122)*(1+'Income Statement Assumptions'!$D122)*(1+'Income Statement Assumptions'!$H122)/4),0) -> 6698 | AK37: =SUM(AG37:AJ37) -> 26792 | AL37: =ROUND(('Income Statement Assumptions'!$B122*(1+'Income Statement Assumptions'!$D122)*(1+'Income Statement Assumptions'!$D122)*(1+'Income Statement Assumptions'!$D122)*(1+'Income Statement Assumptions'!$I122)),0) -> 29172
A38: ='Income Statement Assumptions'!A123 -> Office Supplies | B38: =ROUND('Income Statement Assumptions'!$B123/12,0) -> 667 | C38: =ROUND('Income Statement Assumptions'!$B123/12,0) -> 667 | D38: =ROUND('Income Statement Assumptions'!$B123/12,0) -> 667 | E38: =ROUND('Income Statement Assumptions'!$B123/12,0) -> 667 | F38: =ROUND('Income Statement Assumptions'!$B123/12,0) -> 667 | G38: =ROUND('Income Statement Assumptions'!$B123/12,0) -> 667 | H38: =ROUND('Income Statement Assumptions'!$B123/12,0) -> 667 | I38: =ROUND('Income Statement Assumptions'!$B123/12,0) -> 667 | ... M38: =ROUND('Income Statement Assumptions'!$B123/12,0) -> 667 | N38: =SUM(B38:M38) -> 8004 | O38: =ROUND(('Income Statement Assumptions'!$B123*(1+'Income Statement Assumptions'!$F$123))/12,0) -> 669 | P38: =ROUND(('Income Statement Assumptions'!$B123*(1+'Income Statement Assumptions'!$F$123))/12,0) -> 669 | Q38: =ROUND(('Income Statement Assumptions'!$B123*(1+'Income Statement Assumptions'!$F$123))/12,0) -> 669 | R38: =ROUND(('Income Statement Assumptions'!$B123*(1+'Income Statement Assumptions'!$F$123))/12,0) -> 669 | S38: =ROUND(('Income Statement Assumptions'!$B123*(1+'Income Statement Assumptions'!$F$123))/12,0) -> 669 | T38: =ROUND(('Income Statement Assumptions'!$B123*(1+'Income Statement Assumptions'!$F$123))/12,0) -> 669 | U38: =ROUND(('Income Statement Assumptions'!$B123*(1+'Income Statement Assumptions'!$F$123))/12,0) -> 669 | V38: =ROUND(('Income Statement Assumptions'!$B123*(1+'Income Statement Assumptions'!$F$123))/12,0) -> 669 | ... Z38: =ROUND(('Income Statement Assumptions'!$B123*(1+'Income Statement Assumptions'!$F$123))/12,0) -> 669 | AA38: =SUM(O38:Z38) -> 8028 | AB38: =ROUND(('Income Statement Assumptions'!$B123*(1+'Income Statement Assumptions'!$D123)*(1+'Income Statement Assumptions'!$G123)/4),0) -> 2126 | AC38: =ROUND(('Income Statement Assumptions'!$B123*(1+'Income Statement Assumptions'!$D123)*(1+'Income Statement Assumptions'!$G123)/4),0) -> 2126 | AD38: =ROUND(('Income Statement Assumptions'!$B123*(1+'Income Statement Assumptions'!$D123)*(1+'Income Statement Assumptions'!$G123)/4),0) -> 2126 | AE38: =ROUND(('Income Statement Assumptions'!$B123*(1+'Income Statement Assumptions'!$D123)*(1+'Income Statement Assumptions'!$G123)/4),0) -> 2126 | AF38: =SUM(AB38:AE38) -> 8504 | AG38: =ROUND(('Income Statement Assumptions'!$B123*(1+'Income Statement Assumptions'!$D123)*(1+'Income Statement Assumptions'!$D123)*(1+'Income Statement Assumptions'!$H123)/4),0) -> 2233 | AH38: =ROUND(('Income Statement Assumptions'!$B123*(1+'Income Statement Assumptions'!$D123)*(1+'Income Statement Assumptions'!$D123)*(1+'Income Statement Assumptions'!$H123)/4),0) -> 2233 | AI38: =ROUND(('Income Statement Assumptions'!$B123*(1+'Income Statement Assumptions'!$D123)*(1+'Income Statement Assumptions'!$D123)*(1+'Income Statement Assumptions'!$H123)/4),0) -> 2233 | AJ38: =ROUND(('Income Statement Assumptions'!$B123*(1+'Income Statement Assumptions'!$D123)*(1+'Income Statement Assumptions'!$D123)*(1+'Income Statement Assumptions'!$H123)/4),0) -> 2233 | AK38: =SUM(AG38:AJ38) -> 8932 | AL38: =ROUND(('Income Statement Assumptions'!$B123*(1+'Income Statement Assumptions'!$D123)*(1+'Income Statement Assumptions'!$D123)*(1+'Income Statement Assumptions'!$D123)*(1+'Income Statement Assumptions'!$I123)),0) -> 9724
A39: ='Income Statement Assumptions'!A124 -> Other Staff Salaries | N39: =SUM(B39:M39) -> 0 | O39: =ROUND(('Income Statement Assumptions'!$B124*(1+'Income Statement Assumptions'!$F$124))/12,0) -> 3347 | P39: =ROUND(('Income Statement Assumptions'!$B124*(1+'Income Statement Assumptions'!$F$124))/12,0) -> 3347 | Q39: =ROUND(('Income Statement Assumptions'!$B124*(1+'Income Statement Assumptions'!$F$124))/12,0) -> 3347 | R39: =ROUND(('Income Statement Assumptions'!$B124*(1+'Income Statement Assumptions'!$F$124))/12,0) -> 3347 | S39: =ROUND(('Income Statement Assumptions'!$B124*(1+'Income Statement Assumptions'!$F$124))/12,0) -> 3347 | T39: =ROUND(('Income Statement Assumptions'!$B124*(1+'Income Statement Assumptions'!$F$124))/12,0) -> 3347 | U39: =ROUND(('Income Statement Assumptions'!$B124*(1+'Income Statement Assumptions'!$F$124))/12,0) -> 3347 | V39: =ROUND(('Income Statement Assumptions'!$B124*(1+'Income Statement Assumptions'!$F$124))/12,0) -> 3347 | ... Z39: =ROUND(('Income Statement Assumptions'!$B124*(1+'Income Statement Assumptions'!$F$124))/12,0) -> 3347 | AA39: =SUM(O39:Z39) -> 40164 | AB39: =ROUND(('Income Statement Assumptions'!$B124*(1+'Income Statement Assumptions'!$D124)*(1+'Income Statement Assumptions'!$G124)/4),0) -> 10631 | AC39: =ROUND(('Income Statement Assumptions'!$B124*(1+'Income Statement Assumptions'!$D124)*(1+'Income Statement Assumptions'!$G124)/4),0) -> 10631 | AD39: =ROUND(('Income Statement Assumptions'!$B124*(1+'Income Statement Assumptions'!$D124)*(1+'Income Statement Assumptions'!$G124)/4),0) -> 10631 | AE39: =ROUND(('Income Statement Assumptions'!$B124*(1+'Income Statement Assumptions'!$D124)*(1+'Income Statement Assumptions'!$G124)/4),0) -> 10631 | AF39: =SUM(AB39:AE39) -> 42524 | AG39: =ROUND(('Income Statement Assumptions'!$B124*(1+'Income Statement Assumptions'!$D124)*(1+'Income Statement Assumptions'!$D124)*(1+'Income Statement Assumptions'!$H124)/4),0) -> 11163 | AH39: =ROUND(('Income Statement Assumptions'!$B124*(1+'Income Statement Assumptions'!$D124)*(1+'Income Statement Assumptions'!$D124)*(1+'Income Statement Assumptions'!$H124)/4),0) -> 11163 | AI39: =ROUND(('Income Statement Assumptions'!$B124*(1+'Income Statement Assumptions'!$D124)*(1+'Income Statement Assumptions'!$D124)*(1+'Income Statement Assumptions'!$H124)/4),0) -> 11163 | AJ39: =ROUND(('Income Statement Assumptions'!$B124*(1+'Income Statement Assumptions'!$D124)*(1+'Income Statement Assumptions'!$D124)*(1+'Income Statement Assumptions'!$H124)/4),0) -> 11163 | AK39: =SUM(AG39:AJ39) -> 44652 | AL39: =ROUND(('Income Statement Assumptions'!$B124*(1+'Income Statement Assumptions'!$D124)*(1+'Income Statement Assumptions'!$D124)*(1+'Income Statement Assumptions'!$D124)*(1+'Income Statement Assumptions'!$I124)),0) -> 48620
A40: ='Income Statement Assumptions'!A125 -> Executive Salaries | B40: =ROUND('Income Statement Assumptions'!$B125/12,0) -> 16667 | C40: =ROUND('Income Statement Assumptions'!$B125/12,0) -> 16667 | D40: =ROUND('Income Statement Assumptions'!$B125/12,0) -> 16667 | E40: =ROUND('Income Statement Assumptions'!$B125/12,0) -> 16667 | F40: =ROUND('Income Statement Assumptions'!$B125/12,0) -> 16667 | G40: =ROUND('Income Statement Assumptions'!$B125/12,0) -> 16667 | H40: =ROUND('Income Statement Assumptions'!$B125/12,0) -> 16667 | I40: =ROUND('Income Statement Assumptions'!$B125/12,0) -> 16667 | ... M40: =ROUND('Income Statement Assumptions'!$B125/12,0) -> 16667 | N40: =SUM(B40:M40) -> 200004 | O40: =ROUND(('Income Statement Assumptions'!$B125*(1+'Income Statement Assumptions'!$F$125))/12,0) -> 16806 | P40: =ROUND(('Income Statement Assumptions'!$B125*(1+'Income Statement Assumptions'!$F$125))/12,0) -> 16806 | Q40: =ROUND(('Income Statement Assumptions'!$B125*(1+'Income Statement Assumptions'!$F$125))/12,0) -> 16806 | R40: =ROUND(('Income Statement Assumptions'!$B125*(1+'Income Statement Assumptions'!$F$125))/12,0) -> 16806 | S40: =ROUND(('Income Statement Assumptions'!$B125*(1+'Income Statement Assumptions'!$F$125))/12,0) -> 16806 | T40: =ROUND(('Income Statement Assumptions'!$B125*(1+'Income Statement Assumptions'!$F$125))/12,0) -> 16806 | U40: =ROUND(('Income Statement Assumptions'!$B125*(1+'Income Statement Assumptions'!$F$125))/12,0) -> 16806 | V40: =ROUND(('Income Statement Assumptions'!$B125*(1+'Income Statement Assumptions'!$F$125))/12,0) -> 16806 | ... Z40: =ROUND(('Income Statement Assumptions'!$B125*(1+'Income Statement Assumptions'!$F$125))/12,0) -> 16806 | AA40: =SUM(O40:Z40) -> 201672 | AB40: =ROUND(('Income Statement Assumptions'!$B125*(1+'Income Statement Assumptions'!$D125)*(1+'Income Statement Assumptions'!$G125)/4),0) -> 56375 | AC40: =ROUND(('Income Statement Assumptions'!$B125*(1+'Income Statement Assumptions'!$D125)*(1+'Income Statement Assumptions'!$G125)/4),0) -> 56375 | AD40: =ROUND(('Income Statement Assumptions'!$B125*(1+'Income Statement Assumptions'!$D125)*(1+'Income Statement Assumptions'!$G125)/4),0) -> 56375 | AE40: =ROUND(('Income Statement Assumptions'!$B125*(1+'Income Statement Assumptions'!$D125)*(1+'Income Statement Assumptions'!$G125)/4),0) -> 56375 | AF40: =SUM(AB40:AE40) -> 225500 | AG40: =ROUND(('Income Statement Assumptions'!$B125*(1+'Income Statement Assumptions'!$D125)*(1+'Income Statement Assumptions'!$D125)*(1+'Income Statement Assumptions'!$H125)/4),0) -> 62013 | AH40: =ROUND(('Income Statement Assumptions'!$B125*(1+'Income Statement Assumptions'!$D125)*(1+'Income Statement Assumptions'!$D125)*(1+'Income Statement Assumptions'!$H125)/4),0) -> 62013 | AI40: =ROUND(('Income Statement Assumptions'!$B125*(1+'Income Statement Assumptions'!$D125)*(1+'Income Statement Assumptions'!$D125)*(1+'Income Statement Assumptions'!$H125)/4),0) -> 62013 | AJ40: =ROUND(('Income Statement Assumptions'!$B125*(1+'Income Statement Assumptions'!$D125)*(1+'Income Statement Assumptions'!$D125)*(1+'Income Statement Assumptions'!$H125)/4),0) -> 62013 | AK40: =SUM(AG40:AJ40) -> 248052 | AL40: =ROUND(('Income Statement Assumptions'!$B125*(1+'Income Statement Assumptions'!$D125)*(1+'Income Statement Assumptions'!$D125)*(1+'Income Statement Assumptions'!$D125)*(1+'Income Statement Assumptions'!$I125)),0) -> 292820
A41: ='Income Statement Assumptions'!A126 -> Website Maintenance | B41: =ROUND('Income Statement Assumptions'!$B126/12,0) -> 208 | C41: =ROUND('Income Statement Assumptions'!$B126/12,0) -> 208 | D41: =ROUND('Income Statement Assumptions'!$B126/12,0) -> 208 | E41: =ROUND('Income Statement Assumptions'!$B126/12,0) -> 208 | F41: =ROUND('Income Statement Assumptions'!$B126/12,0) -> 208 | G41: =ROUND('Income Statement Assumptions'!$B126/12,0) -> 208 | H41: =ROUND('Income Statement Assumptions'!$B126/12,0) -> 208 | I41: =ROUND('Income Statement Assumptions'!$B126/12,0) -> 208 | ... M41: =ROUND('Income Statement Assumptions'!$B126/12,0) -> 208 | N41: =SUM(B41:M41) -> 2496 | O41: =ROUND(('Income Statement Assumptions'!$B126*(1+'Income Statement Assumptions'!$F$126))/12,0) -> 209 | P41: =ROUND(('Income Statement Assumptions'!$B126*(1+'Income Statement Assumptions'!$F$126))/12,0) -> 209 | Q41: =ROUND(('Income Statement Assumptions'!$B126*(1+'Income Statement Assumptions'!$F$126))/12,0) -> 209 | R41: =ROUND(('Income Statement Assumptions'!$B126*(1+'Income Statement Assumptions'!$F$126))/12,0) -> 209 | S41: =ROUND(('Income Statement Assumptions'!$B126*(1+'Income Statement Assumptions'!$F$126))/12,0) -> 209 | T41: =ROUND(('Income Statement Assumptions'!$B126*(1+'Income Statement Assumptions'!$F$126))/12,0) -> 209 | U41: =ROUND(('Income Statement Assumptions'!$B126*(1+'Income Statement Assumptions'!$F$126))/12,0) -> 209 | V41: =ROUND(('Income Statement Assumptions'!$B126*(1+'Income Statement Assumptions'!$F$126))/12,0) -> 209 | ... Z41: =ROUND(('Income Statement Assumptions'!$B126*(1+'Income Statement Assumptions'!$F$126))/12,0) -> 209 | AA41: =SUM(O41:Z41) -> 2508 | AB41: =ROUND(('Income Statement Assumptions'!$B126*(1+'Income Statement Assumptions'!$D126)*(1+'Income Statement Assumptions'!$G126)/4),0) -> 664 | AC41: =ROUND(('Income Statement Assumptions'!$B126*(1+'Income Statement Assumptions'!$D126)*(1+'Income Statement Assumptions'!$G126)/4),0) -> 664 | AD41: =ROUND(('Income Statement Assumptions'!$B126*(1+'Income Statement Assumptions'!$D126)*(1+'Income Statement Assumptions'!$G126)/4),0) -> 664 | AE41: =ROUND(('Income Statement Assumptions'!$B126*(1+'Income Statement Assumptions'!$D126)*(1+'Income Statement Assumptions'!$G126)/4),0) -> 664 | AF41: =SUM(AB41:AE41) -> 2656 | AG41: =ROUND(('Income Statement Assumptions'!$B126*(1+'Income Statement Assumptions'!$D126)*(1+'Income Statement Assumptions'!$D126)*(1+'Income Statement Assumptions'!$H126)/4),0) -> 698 | AH41: =ROUND(('Income Statement Assumptions'!$B126*(1+'Income Statement Assumptions'!$D126)*(1+'Income Statement Assumptions'!$D126)*(1+'Income Statement Assumptions'!$H126)/4),0) -> 698 | AI41: =ROUND(('Income Statement Assumptions'!$B126*(1+'Income Statement Assumptions'!$D126)*(1+'Income Statement Assumptions'!$D126)*(1+'Income Statement Assumptions'!$H126)/4),0) -> 698 | AJ41: =ROUND(('Income Statement Assumptions'!$B126*(1+'Income Statement Assumptions'!$D126)*(1+'Income Statement Assumptions'!$D126)*(1+'Income Statement Assumptions'!$H126)/4),0) -> 698 | AK41: =SUM(AG41:AJ41) -> 2792 | AL41: =ROUND(('Income Statement Assumptions'!$B126*(1+'Income Statement Assumptions'!$D126)*(1+'Income Statement Assumptions'!$D126)*(1+'Income Statement Assumptions'!$D126)*(1+'Income Statement Assumptions'!$I126)),0) -> 3039
A42: ='Income Statement Assumptions'!A127 -> General Liability Insurance | B42: =ROUND('Income Statement Assumptions'!$B127/12,0) -> 333 | C42: =ROUND('Income Statement Assumptions'!$B127/12,0) -> 333 | D42: =ROUND('Income Statement Assumptions'!$B127/12,0) -> 333 | E42: =ROUND('Income Statement Assumptions'!$B127/12,0) -> 333 | F42: =ROUND('Income Statement Assumptions'!$B127/12,0) -> 333 | G42: =ROUND('Income Statement Assumptions'!$B127/12,0) -> 333 | H42: =ROUND('Income Statement Assumptions'!$B127/12,0) -> 333 | I42: =ROUND('Income Statement Assumptions'!$B127/12,0) -> 333 | ... M42: =ROUND('Income Statement Assumptions'!$B127/12,0) -> 333 | N42: =SUM(B42:M42) -> 3996 | O42: =ROUND(('Income Statement Assumptions'!$B127*(1+'Income Statement Assumptions'!$F$127))/12,0) -> 335 | P42: =ROUND(('Income Statement Assumptions'!$B127*(1+'Income Statement Assumptions'!$F$127))/12,0) -> 335 | Q42: =ROUND(('Income Statement Assumptions'!$B127*(1+'Income Statement Assumptions'!$F$127))/12,0) -> 335 | R42: =ROUND(('Income Statement Assumptions'!$B127*(1+'Income Statement Assumptions'!$F$127))/12,0) -> 335 | S42: =ROUND(('Income Statement Assumptions'!$B127*(1+'Income Statement Assumptions'!$F$127))/12,0) -> 335 | T42: =ROUND(('Income Statement Assumptions'!$B127*(1+'Income Statement Assumptions'!$F$127))/12,0) -> 335 | U42: =ROUND(('Income Statement Assumptions'!$B127*(1+'Income Statement Assumptions'!$F$127))/12,0) -> 335 | V42: =ROUND(('Income Statement Assumptions'!$B127*(1+'Income Statement Assumptions'!$F$127))/12,0) -> 335 | ... Z42: =ROUND(('Income Statement Assumptions'!$B127*(1+'Income Statement Assumptions'!$F$127))/12,0) -> 335 | AA42: =SUM(O42:Z42) -> 4020 | AB42: =ROUND(('Income Statement Assumptions'!$B127*(1+'Income Statement Assumptions'!$D127)*(1+'Income Statement Assumptions'!$G127)/4),0) -> 1063 | AC42: =ROUND(('Income Statement Assumptions'!$B127*(1+'Income Statement Assumptions'!$D127)*(1+'Income Statement Assumptions'!$G127)/4),0) -> 1063 | AD42: =ROUND(('Income Statement Assumptions'!$B127*(1+'Income Statement Assumptions'!$D127)*(1+'Income Statement Assumptions'!$G127)/4),0) -> 1063 | AE42: =ROUND(('Income Statement Assumptions'!$B127*(1+'Income Statement Assumptions'!$D127)*(1+'Income Statement Assumptions'!$G127)/4),0) -> 1063 | AF42: =SUM(AB42:AE42) -> 4252 | AG42: =ROUND(('Income Statement Assumptions'!$B127*(1+'Income Statement Assumptions'!$D127)*(1+'Income Statement Assumptions'!$D127)*(1+'Income Statement Assumptions'!$H127)/4),0) -> 1116 | AH42: =ROUND(('Income Statement Assumptions'!$B127*(1+'Income Statement Assumptions'!$D127)*(1+'Income Statement Assumptions'!$D127)*(1+'Income Statement Assumptions'!$H127)/4),0) -> 1116 | AI42: =ROUND(('Income Statement Assumptions'!$B127*(1+'Income Statement Assumptions'!$D127)*(1+'Income Statement Assumptions'!$D127)*(1+'Income Statement Assumptions'!$H127)/4),0) -> 1116 | AJ42: =ROUND(('Income Statement Assumptions'!$B127*(1+'Income Statement Assumptions'!$D127)*(1+'Income Statement Assumptions'!$D127)*(1+'Income Statement Assumptions'!$H127)/4),0) -> 1116 | AK42: =SUM(AG42:AJ42) -> 4464 | AL42: =ROUND(('Income Statement Assumptions'!$B127*(1+'Income Statement Assumptions'!$D127)*(1+'Income Statement Assumptions'!$D127)*(1+'Income Statement Assumptions'!$D127)*(1+'Income Statement Assumptions'!$I127)),0) -> 4862
A43: ='Income Statement Assumptions'!A128 -> Depreciation Expense | B43: ='Fixed Asset Assumptions'!$B$31 -> 817 | C43: ='Fixed Asset Assumptions'!$B$31 -> 817 | D43: ='Fixed Asset Assumptions'!$B$31 -> 817 | E43: ='Fixed Asset Assumptions'!$B$31 -> 817 | F43: ='Fixed Asset Assumptions'!$B$31 -> 817 | G43: ='Fixed Asset Assumptions'!$B$31 -> 817 | H43: ='Fixed Asset Assumptions'!$B$31 -> 817 | I43: ='Fixed Asset Assumptions'!$B$31 -> 817 | ... M43: ='Fixed Asset Assumptions'!$B$31 -> 817 | N43: =SUM(B43:M43) -> 9804 | O43: ='Fixed Asset Assumptions'!$C$31 -> 858 | P43: ='Fixed Asset Assumptions'!$C$31 -> 858 | Q43: ='Fixed Asset Assumptions'!$C$31 -> 858 | R43: ='Fixed Asset Assumptions'!$C$31 -> 858 | S43: ='Fixed Asset Assumptions'!$C$31 -> 858 | T43: ='Fixed Asset Assumptions'!$C$31 -> 858 | U43: ='Fixed Asset Assumptions'!$C$31 -> 858 | V43: ='Fixed Asset Assumptions'!$C$31 -> 858 | ... Z43: ='Fixed Asset Assumptions'!$C$31 -> 858 | AA43: =SUM(O43:Z43) -> 10296 | AB43: ='Fixed Asset Assumptions'!$D$31 -> 2800 | AC43: ='Fixed Asset Assumptions'!$D$31 -> 2800 | AD43: ='Fixed Asset Assumptions'!$D$31 -> 2800 | AE43: ='Fixed Asset Assumptions'!$D$31 -> 2800 | AF43: =SUM(AB43:AE43) -> 11200 | AG43: ='Fixed Asset Assumptions'!$E$31 -> 3600 | AH43: ='Fixed Asset Assumptions'!$E$31 -> 3600 | AI43: ='Fixed Asset Assumptions'!$E$31 -> 3600 | AJ43: ='Fixed Asset Assumptions'!$E$31 -> 3600 | AK43: =SUM(AG43:AJ43) -> 14400 | AL43: ='Fixed Asset Assumptions'!F31 -> 15300
A44: ='Income Statement Assumptions'!A129 -> Amortization Expense | B44: ='Fixed Asset Assumptions'!$B$49 -> 83 | C44: ='Fixed Asset Assumptions'!$B$49 -> 83 | D44: ='Fixed Asset Assumptions'!$B$49 -> 83 | E44: ='Fixed Asset Assumptions'!$B$49 -> 83 | F44: ='Fixed Asset Assumptions'!$B$49 -> 83 | G44: ='Fixed Asset Assumptions'!$B$49 -> 83 | H44: ='Fixed Asset Assumptions'!$B$49 -> 83 | I44: ='Fixed Asset Assumptions'!$B$49 -> 83 | ... M44: ='Fixed Asset Assumptions'!$B$49 -> 83 | N44: =SUM(B44:M44) -> 996 | O44: ='Fixed Asset Assumptions'!$C$49 -> 83 | P44: ='Fixed Asset Assumptions'!$C$49 -> 83 | Q44: ='Fixed Asset Assumptions'!$C$49 -> 83 | R44: ='Fixed Asset Assumptions'!$C$49 -> 83 | S44: ='Fixed Asset Assumptions'!$C$49 -> 83 | T44: ='Fixed Asset Assumptions'!$C$49 -> 83 | U44: ='Fixed Asset Assumptions'!$C$49 -> 83 | V44: ='Fixed Asset Assumptions'!$C$49 -> 83 | ... Z44: ='Fixed Asset Assumptions'!$C$49 -> 83 | AA44: =SUM(O44:Z44) -> 996 | AB44: ='Fixed Asset Assumptions'!$D$49 -> 250 | AC44: ='Fixed Asset Assumptions'!$D$49 -> 250 | AD44: ='Fixed Asset Assumptions'!$D$49 -> 250 | AE44: ='Fixed Asset Assumptions'!$D$49 -> 250 | AF44: =SUM(AB44:AE44) -> 1000 | AG44: ='Fixed Asset Assumptions'!$E$49 -> 250 | AH44: ='Fixed Asset Assumptions'!$E$49 -> 250 | AI44: ='Fixed Asset Assumptions'!$E$49 -> 250 | AJ44: ='Fixed Asset Assumptions'!$E$49 -> 250 | AK44: =SUM(AG44:AJ44) -> 1000 | AL44: ='Fixed Asset Assumptions'!F49 -> 1000
A45: ='Income Statement Assumptions'!A130 -> Payroll Tax Expense | B45: =ROUND(((B39+B40+B55)*'Income Statement Assumptions'!$B$148),0) -> 4167 | C45: =ROUND(((C39+C40+C55)*'Income Statement Assumptions'!$B$148),0) -> 4167 | D45: =ROUND(((D39+D40+D55)*'Income Statement Assumptions'!$B$148),0) -> 4167 | E45: =ROUND(((E39+E40+E55)*'Income Statement Assumptions'!$B$148),0) -> 4167 | F45: =ROUND(((F39+F40+F55)*'Income Statement Assumptions'!$B$148),0) -> 4167 | G45: =ROUND(((G39+G40+G55)*'Income Statement Assumptions'!$B$148),0) -> 4167 | H45: =ROUND(((H39+H40+H55)*'Income Statement Assumptions'!$B$148),0) -> 4167 | I45: =ROUND(((I39+I40+I55)*'Income Statement Assumptions'!$B$148),0) -> 4167 | ... M45: =ROUND(((M39+M40+M55)*'Income Statement Assumptions'!$B$148),0) -> 4167 | N45: =SUM(B45:M45) -> 50004 | O45: =ROUND(((O39+O40+O55)*'Income Statement Assumptions'!$B$148),0) -> 5038 | P45: =ROUND(((P39+P40+P55)*'Income Statement Assumptions'!$B$148),0) -> 5038 | Q45: =ROUND(((Q39+Q40+Q55)*'Income Statement Assumptions'!$B$148),0) -> 5038 | R45: =ROUND(((R39+R40+R55)*'Income Statement Assumptions'!$B$148),0) -> 5038 | S45: =ROUND(((S39+S40+S55)*'Income Statement Assumptions'!$B$148),0) -> 5038 | T45: =ROUND(((T39+T40+T55)*'Income Statement Assumptions'!$B$148),0) -> 5038 | U45: =ROUND(((U39+U40+U55)*'Income Statement Assumptions'!$B$148),0) -> 5038 | V45: =ROUND(((V39+V40+V55)*'Income Statement Assumptions'!$B$148),0) -> 5038 | ... Z45: =ROUND(((Z39+Z40+Z55)*'Income Statement Assumptions'!$B$148),0) -> 5038 | AA45: =SUM(O45:Z45) -> 60456 | AB45: =ROUND(((AB39+AB40+AB55)*'Income Statement Assumptions'!$B$148),0) -> 16752 | AC45: =ROUND(((AC39+AC40+AC55)*'Income Statement Assumptions'!$B$148),0) -> 16752 | AD45: =ROUND(((AD39+AD40+AD55)*'Income Statement Assumptions'!$B$148),0) -> 16752 | AE45: =ROUND(((AE39+AE40+AE55)*'Income Statement Assumptions'!$B$148),0) -> 16752 | AF45: =SUM(AB45:AE45) -> 67008 | AG45: =ROUND(((AG39+AG40+AG55)*'Income Statement Assumptions'!$B$148),0) -> 18294 | AH45: =ROUND(((AH39+AH40+AH55)*'Income Statement Assumptions'!$B$148),0) -> 18294 | AI45: =ROUND(((AI39+AI40+AI55)*'Income Statement Assumptions'!$B$148),0) -> 18294 | AJ45: =ROUND(((AJ39+AJ40+AJ55)*'Income Statement Assumptions'!$B$148),0) -> 18294 | AK45: =SUM(AG45:AJ45) -> 73176 | AL45: =ROUND(((AL39+AL40+AL55)*'Income Statement Assumptions'!$B$148),0) -> 85360
A46: ='Income Statement Assumptions'!A131 -> Product Liability Insurance | I46: =ROUND('Income Statement Assumptions'!$B131/12,0) -> 3333 | J46: =ROUND('Income Statement Assumptions'!$B131/12,0) -> 3333 | K46: =ROUND('Income Statement Assumptions'!$B131/12,0) -> 3333 | L46: =ROUND('Income Statement Assumptions'!$B131/12,0) -> 3333 | M46: =ROUND('Income Statement Assumptions'!$B131/12,0) -> 3333 | N46: =SUM(B46:M46) -> 16665 | O46: =ROUND(('Income Statement Assumptions'!$B131*(1+'Income Statement Assumptions'!$F$131))/12,0) -> 3347 | P46: =ROUND(('Income Statement Assumptions'!$B131*(1+'Income Statement Assumptions'!$F$131))/12,0) -> 3347 | Q46: =ROUND(('Income Statement Assumptions'!$B131*(1+'Income Statement Assumptions'!$F$131))/12,0) -> 3347 | R46: =ROUND(('Income Statement Assumptions'!$B131*(1+'Income Statement Assumptions'!$F$131))/12,0) -> 3347 | S46: =ROUND(('Income Statement Assumptions'!$B131*(1+'Income Statement Assumptions'!$F$131))/12,0) -> 3347 | T46: =ROUND(('Income Statement Assumptions'!$B131*(1+'Income Statement Assumptions'!$F$131))/12,0) -> 3347 | U46: =ROUND(('Income Statement Assumptions'!$B131*(1+'Income Statement Assumptions'!$F$131))/12,0) -> 3347 | V46: =ROUND(('Income Statement Assumptions'!$B131*(1+'Income Statement Assumptions'!$F$131))/12,0) -> 3347 | ... Z46: =ROUND(('Income Statement Assumptions'!$B131*(1+'Income Statement Assumptions'!$F$131))/12,0) -> 3347 | AA46: =SUM(O46:Z46) -> 40164 | AB46: =ROUND(('Income Statement Assumptions'!$B131*(1+'Income Statement Assumptions'!$D131)*(1+'Income Statement Assumptions'!$G131)/4),0) -> 10631 | AC46: =ROUND(('Income Statement Assumptions'!$B131*(1+'Income Statement Assumptions'!$D131)*(1+'Income Statement Assumptions'!$G131)/4),0) -> 10631 | AD46: =ROUND(('Income Statement Assumptions'!$B131*(1+'Income Statement Assumptions'!$D131)*(1+'Income Statement Assumptions'!$G131)/4),0) -> 10631 | AE46: =ROUND(('Income Statement Assumptions'!$B131*(1+'Income Statement Assumptions'!$D131)*(1+'Income Statement Assumptions'!$G131)/4),0) -> 10631 | AF46: =SUM(AB46:AE46) -> 42524 | AG46: =ROUND(('Income Statement Assumptions'!$B131*(1+'Income Statement Assumptions'!$D131)*(1+'Income Statement Assumptions'!$D131)*(1+'Income Statement Assumptions'!$H131)/4),0) -> 11163 | AH46: =ROUND(('Income Statement Assumptions'!$B131*(1+'Income Statement Assumptions'!$D131)*(1+'Income Statement Assumptions'!$D131)*(1+'Income Statement Assumptions'!$H131)/4),0) -> 11163 | AI46: =ROUND(('Income Statement Assumptions'!$B131*(1+'Income Statement Assumptions'!$D131)*(1+'Income Statement Assumptions'!$D131)*(1+'Income Statement Assumptions'!$H131)/4),0) -> 11163 | AJ46: =ROUND(('Income Statement Assumptions'!$B131*(1+'Income Statement Assumptions'!$D131)*(1+'Income Statement Assumptions'!$D131)*(1+'Income Statement Assumptions'!$H131)/4),0) -> 11163 | AK46: =SUM(AG46:AJ46) -> 44652 | AL46: =ROUND(('Income Statement Assumptions'!$B131*(1+'Income Statement Assumptions'!$D131)*(1+'Income Statement Assumptions'!$D131)*(1+'Income Statement Assumptions'!$D131)*(1+'Income Statement Assumptions'!$I131)),0) -> 48620
A47: ='Income Statement Assumptions'!A132 -> Vehicle Leases | B47: =ROUND('Income Statement Assumptions'!$B132/12,0) -> 1667 | C47: =ROUND('Income Statement Assumptions'!$B132/12,0) -> 1667 | D47: =ROUND('Income Statement Assumptions'!$B132/12,0) -> 1667 | E47: =ROUND('Income Statement Assumptions'!$B132/12,0) -> 1667 | F47: =ROUND('Income Statement Assumptions'!$B132/12,0) -> 1667 | G47: =ROUND('Income Statement Assumptions'!$B132/12,0) -> 1667 | H47: =ROUND('Income Statement Assumptions'!$B132/12,0) -> 1667 | I47: =ROUND('Income Statement Assumptions'!$B132/12,0) -> 1667 | ... M47: =ROUND('Income Statement Assumptions'!$B132/12,0) -> 1667 | N47: =SUM(B47:M47) -> 20004 | O47: =ROUND(('Income Statement Assumptions'!$B132*(1+'Income Statement Assumptions'!$F$132))/12,0) -> 1667 | P47: =ROUND(('Income Statement Assumptions'!$B132*(1+'Income Statement Assumptions'!$F$132))/12,0) -> 1667 | Q47: =ROUND(('Income Statement Assumptions'!$B132*(1+'Income Statement Assumptions'!$F$132))/12,0) -> 1667 | R47: =ROUND(('Income Statement Assumptions'!$B132*(1+'Income Statement Assumptions'!$F$132))/12,0) -> 1667 | S47: =ROUND(('Income Statement Assumptions'!$B132*(1+'Income Statement Assumptions'!$F$132))/12,0) -> 1667 | T47: =ROUND(('Income Statement Assumptions'!$B132*(1+'Income Statement Assumptions'!$F$132))/12,0) -> 1667 | U47: =ROUND(('Income Statement Assumptions'!$B132*(1+'Income Statement Assumptions'!$F$132))/12,0) -> 1667 | V47: =ROUND(('Income Statement Assumptions'!$B132*(1+'Income Statement Assumptions'!$F$132))/12,0) -> 1667 | ... Z47: =ROUND(('Income Statement Assumptions'!$B132*(1+'Income Statement Assumptions'!$F$132))/12,0) -> 1667 | AA47: =SUM(O47:Z47) -> 20004 | AB47: =ROUND(('Income Statement Assumptions'!$B132*(1+'Income Statement Assumptions'!$D132)*(1+'Income Statement Assumptions'!$G132)/4),0) -> 5000 | AC47: =ROUND(('Income Statement Assumptions'!$B132*(1+'Income Statement Assumptions'!$D132)*(1+'Income Statement Assumptions'!$G132)/4),0) -> 5000 | AD47: =ROUND(('Income Statement Assumptions'!$B132*(1+'Income Statement Assumptions'!$D132)*(1+'Income Statement Assumptions'!$G132)/4),0) -> 5000 | AE47: =ROUND(('Income Statement Assumptions'!$B132*(1+'Income Statement Assumptions'!$D132)*(1+'Income Statement Assumptions'!$G132)/4),0) -> 5000 | AF47: =SUM(AB47:AE47) -> 20000 | AG47: =ROUND(('Income Statement Assumptions'!$B132*(1+'Income Statement Assumptions'!$D132)*(1+'Income Statement Assumptions'!$D132)*(1+'Income Statement Assumptions'!$H132)/4),0) -> 5000 | AH47: =ROUND(('Income Statement Assumptions'!$B132*(1+'Income Statement Assumptions'!$D132)*(1+'Income Statement Assumptions'!$D132)*(1+'Income Statement Assumptions'!$H132)/4),0) -> 5000 | AI47: =ROUND(('Income Statement Assumptions'!$B132*(1+'Income Statement Assumptions'!$D132)*(1+'Income Statement Assumptions'!$D132)*(1+'Income Statement Assumptions'!$H132)/4),0) -> 5000 | AJ47: =ROUND(('Income Statement Assumptions'!$B132*(1+'Income Statement Assumptions'!$D132)*(1+'Income Statement Assumptions'!$D132)*(1+'Income Statement Assumptions'!$H132)/4),0) -> 5000 | AK47: =SUM(AG47:AJ47) -> 20000 | AL47: =ROUND(('Income Statement Assumptions'!$B132*(1+'Income Statement Assumptions'!$D132)*(1+'Income Statement Assumptions'!$D132)*(1+'Income Statement Assumptions'!$D132)*(1+'Income Statement Assumptions'!$I132)),0) -> 20000
A48: ='Income Statement Assumptions'!A133 -> Vehicle maintenance | B48: =ROUND('Income Statement Assumptions'!$B133/12,0) -> 167 | C48: =ROUND('Income Statement Assumptions'!$B133/12,0) -> 167 | D48: =ROUND('Income Statement Assumptions'!$B133/12,0) -> 167 | E48: =ROUND('Income Statement Assumptions'!$B133/12,0) -> 167 | F48: =ROUND('Income Statement Assumptions'!$B133/12,0) -> 167 | G48: =ROUND('Income Statement Assumptions'!$B133/12,0) -> 167 | H48: =ROUND('Income Statement Assumptions'!$B133/12,0) -> 167 | I48: =ROUND('Income Statement Assumptions'!$B133/12,0) -> 167 | ... M48: =ROUND('Income Statement Assumptions'!$B133/12,0) -> 167 | N48: =SUM(B48:M48) -> 2004 | O48: =ROUND(('Income Statement Assumptions'!$B133*(1+'Income Statement Assumptions'!$F$133))/12,0) -> 167 | P48: =ROUND(('Income Statement Assumptions'!$B133*(1+'Income Statement Assumptions'!$F$133))/12,0) -> 167 | Q48: =ROUND(('Income Statement Assumptions'!$B133*(1+'Income Statement Assumptions'!$F$133))/12,0) -> 167 | R48: =ROUND(('Income Statement Assumptions'!$B133*(1+'Income Statement Assumptions'!$F$133))/12,0) -> 167 | S48: =ROUND(('Income Statement Assumptions'!$B133*(1+'Income Statement Assumptions'!$F$133))/12,0) -> 167 | T48: =ROUND(('Income Statement Assumptions'!$B133*(1+'Income Statement Assumptions'!$F$133))/12,0) -> 167 | U48: =ROUND(('Income Statement Assumptions'!$B133*(1+'Income Statement Assumptions'!$F$133))/12,0) -> 167 | V48: =ROUND(('Income Statement Assumptions'!$B133*(1+'Income Statement Assumptions'!$F$133))/12,0) -> 167 | ... Z48: =ROUND(('Income Statement Assumptions'!$B133*(1+'Income Statement Assumptions'!$F$133))/12,0) -> 167 | AA48: =SUM(O48:Z48) -> 2004 | AB48: =ROUND(('Income Statement Assumptions'!$B133*(1+'Income Statement Assumptions'!$D133)*(1+'Income Statement Assumptions'!$G133)/4),0) -> 532 | AC48: =ROUND(('Income Statement Assumptions'!$B133*(1+'Income Statement Assumptions'!$D133)*(1+'Income Statement Assumptions'!$G133)/4),0) -> 532 | AD48: =ROUND(('Income Statement Assumptions'!$B133*(1+'Income Statement Assumptions'!$D133)*(1+'Income Statement Assumptions'!$G133)/4),0) -> 532 | AE48: =ROUND(('Income Statement Assumptions'!$B133*(1+'Income Statement Assumptions'!$D133)*(1+'Income Statement Assumptions'!$G133)/4),0) -> 532 | AF48: =SUM(AB48:AE48) -> 2128 | AG48: =ROUND(('Income Statement Assumptions'!$B133*(1+'Income Statement Assumptions'!$D133)*(1+'Income Statement Assumptions'!$D133)*(1+'Income Statement Assumptions'!$H133)/4),0) -> 558 | AH48: =ROUND(('Income Statement Assumptions'!$B133*(1+'Income Statement Assumptions'!$D133)*(1+'Income Statement Assumptions'!$D133)*(1+'Income Statement Assumptions'!$H133)/4),0) -> 558 | AI48: =ROUND(('Income Statement Assumptions'!$B133*(1+'Income Statement Assumptions'!$D133)*(1+'Income Statement Assumptions'!$D133)*(1+'Income Statement Assumptions'!$H133)/4),0) -> 558 | AJ48: =ROUND(('Income Statement Assumptions'!$B133*(1+'Income Statement Assumptions'!$D133)*(1+'Income Statement Assumptions'!$D133)*(1+'Income Statement Assumptions'!$H133)/4),0) -> 558 | AK48: =SUM(AG48:AJ48) -> 2232 | AL48: =ROUND(('Income Statement Assumptions'!$B133*(1+'Income Statement Assumptions'!$D133)*(1+'Income Statement Assumptions'!$D133)*(1+'Income Statement Assumptions'!$D133)*(1+'Income Statement Assumptions'!$I133)),0) -> 2431
A49: ='Income Statement Assumptions'!A134 -> 0 | B49: =ROUND('Income Statement Assumptions'!$B134/12,0) -> 0 | C49: =ROUND('Income Statement Assumptions'!$B134/12,0) -> 0 | D49: =ROUND('Income Statement Assumptions'!$B134/12,0) -> 0 | E49: =ROUND('Income Statement Assumptions'!$B134/12,0) -> 0 | F49: =ROUND('Income Statement Assumptions'!$B134/12,0) -> 0 | G49: =ROUND('Income Statement Assumptions'!$B134/12,0) -> 0 | H49: =ROUND('Income Statement Assumptions'!$B134/12,0) -> 0 | I49: =ROUND('Income Statement Assumptions'!$B134/12,0) -> 0 | ... M49: =ROUND('Income Statement Assumptions'!$B134/12,0) -> 0 | N49: =SUM(B49:M49) -> 0 | O49: =ROUND(('Income Statement Assumptions'!$B134*(1+'Income Statement Assumptions'!$F$123))/12,0) -> 0 | P49: =ROUND(('Income Statement Assumptions'!$B134*(1+'Income Statement Assumptions'!$F$123))/12,0) -> 0 | Q49: =ROUND(('Income Statement Assumptions'!$B134*(1+'Income Statement Assumptions'!$F$123))/12,0) -> 0 | R49: =ROUND(('Income Statement Assumptions'!$B134*(1+'Income Statement Assumptions'!$F$123))/12,0) -> 0 | S49: =ROUND(('Income Statement Assumptions'!$B134*(1+'Income Statement Assumptions'!$F$123))/12,0) -> 0 | T49: =ROUND(('Income Statement Assumptions'!$B134*(1+'Income Statement Assumptions'!$F$123))/12,0) -> 0 | U49: =ROUND(('Income Statement Assumptions'!$B134*(1+'Income Statement Assumptions'!$F$123))/12,0) -> 0 | V49: =ROUND(('Income Statement Assumptions'!$B134*(1+'Income Statement Assumptions'!$F$123))/12,0) -> 0 | ... Z49: =ROUND(('Income Statement Assumptions'!$B134*(1+'Income Statement Assumptions'!$F$123))/12,0) -> 0 | AA49: =SUM(O49:Z49) -> 0 | AB49: =ROUND(('Income Statement Assumptions'!$B134*(1+'Income Statement Assumptions'!$D134)*(1+'Income Statement Assumptions'!$G134)/4),0) -> 0 | AC49: =ROUND(('Income Statement Assumptions'!$B134*(1+'Income Statement Assumptions'!$D134)*(1+'Income Statement Assumptions'!$G134)/4),0) -> 0 | AD49: =ROUND(('Income Statement Assumptions'!$B134*(1+'Income Statement Assumptions'!$D134)*(1+'Income Statement Assumptions'!$G134)/4),0) -> 0 | AE49: =ROUND(('Income Statement Assumptions'!$B134*(1+'Income Statement Assumptions'!$D134)*(1+'Income Statement Assumptions'!$G134)/4),0) -> 0 | AF49: =SUM(AB49:AE49) -> 0 | AG49: =ROUND(('Income Statement Assumptions'!$B134*(1+'Income Statement Assumptions'!$D134)*(1+'Income Statement Assumptions'!$D134)*(1+'Income Statement Assumptions'!$H134)/4),0) -> 0 | AH49: =ROUND(('Income Statement Assumptions'!$B134*(1+'Income Statement Assumptions'!$D134)*(1+'Income Statement Assumptions'!$D134)*(1+'Income Statement Assumptions'!$H134)/4),0) -> 0 | AI49: =ROUND(('Income Statement Assumptions'!$B134*(1+'Income Statement Assumptions'!$D134)*(1+'Income Statement Assumptions'!$D134)*(1+'Income Statement Assumptions'!$H134)/4),0) -> 0 | AJ49: =ROUND(('Income Statement Assumptions'!$B134*(1+'Income Statement Assumptions'!$D134)*(1+'Income Statement Assumptions'!$D134)*(1+'Income Statement Assumptions'!$H134)/4),0) -> 0 | AK49: =SUM(AG49:AJ49) -> 0 | AL49: =ROUND(('Income Statement Assumptions'!$B134*(1+'Income Statement Assumptions'!$D134)*(1+'Income Statement Assumptions'!$D134)*(1+'Income Statement Assumptions'!$D134)*(1+'Income Statement Assumptions'!$I134)),0) -> 0
A50: ='Income Statement Assumptions'!A135 -> Selling:
A51: ='Income Statement Assumptions'!A136 -> Marketing & Advertising Expense | B51: =ROUND('Income Statement Assumptions'!$B136/12,0) -> 8333 | C51: =ROUND('Income Statement Assumptions'!$B136/12,0) -> 8333 | D51: =ROUND('Income Statement Assumptions'!$B136/12,0) -> 8333 | E51: =ROUND('Income Statement Assumptions'!$B136/12,0) -> 8333 | F51: =ROUND('Income Statement Assumptions'!$B136/12,0) -> 8333 | G51: =ROUND('Income Statement Assumptions'!$B136/12,0) -> 8333 | H51: =ROUND('Income Statement Assumptions'!$B136/12,0) -> 8333 | I51: =ROUND('Income Statement Assumptions'!$B136/12,0) -> 8333 | ... M51: =ROUND('Income Statement Assumptions'!$B136/12,0) -> 8333 | N51: =SUM(B51:M51) -> 99996 | O51: =ROUND(('Income Statement Assumptions'!$B136*(1+'Income Statement Assumptions'!$F$136))/12,0) -> 8438 | P51: =ROUND(('Income Statement Assumptions'!$B136*(1+'Income Statement Assumptions'!$F$136))/12,0) -> 8438 | Q51: =ROUND(('Income Statement Assumptions'!$B136*(1+'Income Statement Assumptions'!$F$136))/12,0) -> 8438 | R51: =ROUND(('Income Statement Assumptions'!$B136*(1+'Income Statement Assumptions'!$F$136))/12,0) -> 8438 | S51: =ROUND(('Income Statement Assumptions'!$B136*(1+'Income Statement Assumptions'!$F$136))/12,0) -> 8438 | T51: =ROUND(('Income Statement Assumptions'!$B136*(1+'Income Statement Assumptions'!$F$136))/12,0) -> 8438 | U51: =ROUND(('Income Statement Assumptions'!$B136*(1+'Income Statement Assumptions'!$F$136))/12,0) -> 8438 | V51: =ROUND(('Income Statement Assumptions'!$B136*(1+'Income Statement Assumptions'!$F$136))/12,0) -> 8438 | ... Z51: =ROUND(('Income Statement Assumptions'!$B136*(1+'Income Statement Assumptions'!$F$136))/12,0) -> 8438 | AA51: =SUM(O51:Z51) -> 101256 | AB51: =ROUND(('Income Statement Assumptions'!$B136*(1+'Income Statement Assumptions'!$D136)*(1+'Income Statement Assumptions'!$G136)/4),0) -> 29828 | AC51: =ROUND(('Income Statement Assumptions'!$B136*(1+'Income Statement Assumptions'!$D136)*(1+'Income Statement Assumptions'!$G136)/4),0) -> 29828 | AD51: =ROUND(('Income Statement Assumptions'!$B136*(1+'Income Statement Assumptions'!$D136)*(1+'Income Statement Assumptions'!$G136)/4),0) -> 29828 | AE51: =ROUND(('Income Statement Assumptions'!$B136*(1+'Income Statement Assumptions'!$D136)*(1+'Income Statement Assumptions'!$G136)/4),0) -> 29828 | AF51: =SUM(AB51:AE51) -> 119312 | AG51: =ROUND(('Income Statement Assumptions'!$B136*(1+'Income Statement Assumptions'!$D136)*(1+'Income Statement Assumptions'!$D136)*(1+'Income Statement Assumptions'!$H136)/4),0) -> 34302 | AH51: =ROUND(('Income Statement Assumptions'!$B136*(1+'Income Statement Assumptions'!$D136)*(1+'Income Statement Assumptions'!$D136)*(1+'Income Statement Assumptions'!$H136)/4),0) -> 34302 | AI51: =ROUND(('Income Statement Assumptions'!$B136*(1+'Income Statement Assumptions'!$D136)*(1+'Income Statement Assumptions'!$D136)*(1+'Income Statement Assumptions'!$H136)/4),0) -> 34302 | AJ51: =ROUND(('Income Statement Assumptions'!$B136*(1+'Income Statement Assumptions'!$D136)*(1+'Income Statement Assumptions'!$D136)*(1+'Income Statement Assumptions'!$H136)/4),0) -> 34302 | AK51: =SUM(AG51:AJ51) -> 137208 | AL51: =ROUND(('Income Statement Assumptions'!$B136*(1+'Income Statement Assumptions'!$D136)*(1+'Income Statement Assumptions'!$D136)*(1+'Income Statement Assumptions'!$D136)*(1+'Income Statement Assumptions'!$I136)),0) -> 174901
A52: ='Income Statement Assumptions'!A137 -> Tradeshows | B52: =ROUND('Income Statement Assumptions'!$B137/12,0) -> 3333 | C52: =ROUND('Income Statement Assumptions'!$B137/12,0) -> 3333 | D52: =ROUND('Income Statement Assumptions'!$B137/12,0) -> 3333 | E52: =ROUND('Income Statement Assumptions'!$B137/12,0) -> 3333 | F52: =ROUND('Income Statement Assumptions'!$B137/12,0) -> 3333 | G52: =ROUND('Income Statement Assumptions'!$B137/12,0) -> 3333 | H52: =ROUND('Income Statement Assumptions'!$B137/12,0) -> 3333 | I52: =ROUND('Income Statement Assumptions'!$B137/12,0) -> 3333 | ... M52: =ROUND('Income Statement Assumptions'!$B137/12,0) -> 3333 | N52: =SUM(B52:M52) -> 39996 | O52: =ROUND(('Income Statement Assumptions'!$B137*(1+'Income Statement Assumptions'!$F$137))/12,0) -> 3347 | P52: =ROUND(('Income Statement Assumptions'!$B137*(1+'Income Statement Assumptions'!$F$137))/12,0) -> 3347 | Q52: =ROUND(('Income Statement Assumptions'!$B137*(1+'Income Statement Assumptions'!$F$137))/12,0) -> 3347 | R52: =ROUND(('Income Statement Assumptions'!$B137*(1+'Income Statement Assumptions'!$F$137))/12,0) -> 3347 | S52: =ROUND(('Income Statement Assumptions'!$B137*(1+'Income Statement Assumptions'!$F$137))/12,0) -> 3347 | T52: =ROUND(('Income Statement Assumptions'!$B137*(1+'Income Statement Assumptions'!$F$137))/12,0) -> 3347 | U52: =ROUND(('Income Statement Assumptions'!$B137*(1+'Income Statement Assumptions'!$F$137))/12,0) -> 3347 | V52: =ROUND(('Income Statement Assumptions'!$B137*(1+'Income Statement Assumptions'!$F$137))/12,0) -> 3347 | ... Z52: =ROUND(('Income Statement Assumptions'!$B137*(1+'Income Statement Assumptions'!$F$137))/12,0) -> 3347 | AA52: =SUM(O52:Z52) -> 40164 | AB52: =ROUND(('Income Statement Assumptions'!$B137*(1+'Income Statement Assumptions'!$D137)*(1+'Income Statement Assumptions'!$G137)/4),0) -> 10631 | AC52: =ROUND(('Income Statement Assumptions'!$B137*(1+'Income Statement Assumptions'!$D137)*(1+'Income Statement Assumptions'!$G137)/4),0) -> 10631 | AD52: =ROUND(('Income Statement Assumptions'!$B137*(1+'Income Statement Assumptions'!$D137)*(1+'Income Statement Assumptions'!$G137)/4),0) -> 10631 | AE52: =ROUND(('Income Statement Assumptions'!$B137*(1+'Income Statement Assumptions'!$D137)*(1+'Income Statement Assumptions'!$G137)/4),0) -> 10631 | AF52: =SUM(AB52:AE52) -> 42524 | AG52: =ROUND(('Income Statement Assumptions'!$B137*(1+'Income Statement Assumptions'!$D137)*(1+'Income Statement Assumptions'!$D137)*(1+'Income Statement Assumptions'!$H137)/4),0) -> 11163 | AH52: =ROUND(('Income Statement Assumptions'!$B137*(1+'Income Statement Assumptions'!$D137)*(1+'Income Statement Assumptions'!$D137)*(1+'Income Statement Assumptions'!$H137)/4),0) -> 11163 | AI52: =ROUND(('Income Statement Assumptions'!$B137*(1+'Income Statement Assumptions'!$D137)*(1+'Income Statement Assumptions'!$D137)*(1+'Income Statement Assumptions'!$H137)/4),0) -> 11163 | AJ52: =ROUND(('Income Statement Assumptions'!$B137*(1+'Income Statement Assumptions'!$D137)*(1+'Income Statement Assumptions'!$D137)*(1+'Income Statement Assumptions'!$H137)/4),0) -> 11163 | AK52: =SUM(AG52:AJ52) -> 44652 | AL52: =ROUND(('Income Statement Assumptions'!$B137*(1+'Income Statement Assumptions'!$D137)*(1+'Income Statement Assumptions'!$D137)*(1+'Income Statement Assumptions'!$D137)*(1+'Income Statement Assumptions'!$I137)),0) -> 48620
A53: ='Income Statement Assumptions'!A138 -> 0 | B53: =ROUND('Income Statement Assumptions'!$B138/12,0) -> 0 | C53: =ROUND('Income Statement Assumptions'!$B138/12,0) -> 0 | D53: =ROUND('Income Statement Assumptions'!$B138/12,0) -> 0 | E53: =ROUND('Income Statement Assumptions'!$B138/12,0) -> 0 | F53: =ROUND('Income Statement Assumptions'!$B138/12,0) -> 0 | G53: =ROUND('Income Statement Assumptions'!$B138/12,0) -> 0 | H53: =ROUND('Income Statement Assumptions'!$B138/12,0) -> 0 | I53: =ROUND('Income Statement Assumptions'!$B138/12,0) -> 0 | ... M53: =ROUND('Income Statement Assumptions'!$B138/12,0) -> 0 | N53: =SUM(B53:M53) -> 0 | O53: =ROUND(('Income Statement Assumptions'!$B138*(1+'Income Statement Assumptions'!$F$123))/12,0) -> 0 | P53: =ROUND(('Income Statement Assumptions'!$B138*(1+'Income Statement Assumptions'!$F$123))/12,0) -> 0 | Q53: =ROUND(('Income Statement Assumptions'!$B138*(1+'Income Statement Assumptions'!$F$123))/12,0) -> 0 | R53: =ROUND(('Income Statement Assumptions'!$B138*(1+'Income Statement Assumptions'!$F$123))/12,0) -> 0 | S53: =ROUND(('Income Statement Assumptions'!$B138*(1+'Income Statement Assumptions'!$F$123))/12,0) -> 0 | T53: =ROUND(('Income Statement Assumptions'!$B138*(1+'Income Statement Assumptions'!$F$123))/12,0) -> 0 | U53: =ROUND(('Income Statement Assumptions'!$B138*(1+'Income Statement Assumptions'!$F$123))/12,0) -> 0 | V53: =ROUND(('Income Statement Assumptions'!$B138*(1+'Income Statement Assumptions'!$F$123))/12,0) -> 0 | ... Z53: =ROUND(('Income Statement Assumptions'!$B138*(1+'Income Statement Assumptions'!$F$123))/12,0) -> 0 | AA53: =SUM(O53:Z53) -> 0 | AB53: =ROUND(('Income Statement Assumptions'!$B138*(1+'Income Statement Assumptions'!$D138)*(1+'Income Statement Assumptions'!$G138)/4),0) -> 0 | AC53: =ROUND(('Income Statement Assumptions'!$B138*(1+'Income Statement Assumptions'!$D138)*(1+'Income Statement Assumptions'!$G138)/4),0) -> 0 | AD53: =ROUND(('Income Statement Assumptions'!$B138*(1+'Income Statement Assumptions'!$D138)*(1+'Income Statement Assumptions'!$G138)/4),0) -> 0 | AE53: =ROUND(('Income Statement Assumptions'!$B138*(1+'Income Statement Assumptions'!$D138)*(1+'Income Statement Assumptions'!$G138)/4),0) -> 0 | AF53: =SUM(AB53:AE53) -> 0 | AG53: =ROUND(('Income Statement Assumptions'!$B138*(1+'Income Statement Assumptions'!$D138)*(1+'Income Statement Assumptions'!$D138)*(1+'Income Statement Assumptions'!$H138)/4),0) -> 0 | AH53: =ROUND(('Income Statement Assumptions'!$B138*(1+'Income Statement Assumptions'!$D138)*(1+'Income Statement Assumptions'!$D138)*(1+'Income Statement Assumptions'!$H138)/4),0) -> 0 | AI53: =ROUND(('Income Statement Assumptions'!$B138*(1+'Income Statement Assumptions'!$D138)*(1+'Income Statement Assumptions'!$D138)*(1+'Income Statement Assumptions'!$H138)/4),0) -> 0 | AJ53: =ROUND(('Income Statement Assumptions'!$B138*(1+'Income Statement Assumptions'!$D138)*(1+'Income Statement Assumptions'!$D138)*(1+'Income Statement Assumptions'!$H138)/4),0) -> 0 | AK53: =SUM(AG53:AJ53) -> 0 | AL53: =ROUND(('Income Statement Assumptions'!$B138*(1+'Income Statement Assumptions'!$D138)*(1+'Income Statement Assumptions'!$D138)*(1+'Income Statement Assumptions'!$D138)*(1+'Income Statement Assumptions'!$I138)),0) -> 0
A54: ='Income Statement Assumptions'!A139 -> 0 | B54: =ROUND('Income Statement Assumptions'!$B139/12,0) -> 0 | C54: =ROUND('Income Statement Assumptions'!$B139/12,0) -> 0 | D54: =ROUND('Income Statement Assumptions'!$B139/12,0) -> 0 | E54: =ROUND('Income Statement Assumptions'!$B139/12,0) -> 0 | F54: =ROUND('Income Statement Assumptions'!$B139/12,0) -> 0 | G54: =ROUND('Income Statement Assumptions'!$B139/12,0) -> 0 | H54: =ROUND('Income Statement Assumptions'!$B139/12,0) -> 0 | I54: =ROUND('Income Statement Assumptions'!$B139/12,0) -> 0 | ... M54: =ROUND('Income Statement Assumptions'!$B139/12,0) -> 0 | N54: =SUM(B54:M54) -> 0 | O54: =ROUND(('Income Statement Assumptions'!$B139*(1+'Income Statement Assumptions'!$F$123))/12,0) -> 0 | P54: =ROUND(('Income Statement Assumptions'!$B139*(1+'Income Statement Assumptions'!$F$123))/12,0) -> 0 | Q54: =ROUND(('Income Statement Assumptions'!$B139*(1+'Income Statement Assumptions'!$F$123))/12,0) -> 0 | R54: =ROUND(('Income Statement Assumptions'!$B139*(1+'Income Statement Assumptions'!$F$123))/12,0) -> 0 | S54: =ROUND(('Income Statement Assumptions'!$B139*(1+'Income Statement Assumptions'!$F$123))/12,0) -> 0 | T54: =ROUND(('Income Statement Assumptions'!$B139*(1+'Income Statement Assumptions'!$F$123))/12,0) -> 0 | U54: =ROUND(('Income Statement Assumptions'!$B139*(1+'Income Statement Assumptions'!$F$123))/12,0) -> 0 | V54: =ROUND(('Income Statement Assumptions'!$B139*(1+'Income Statement Assumptions'!$F$123))/12,0) -> 0 | ... Z54: =ROUND(('Income Statement Assumptions'!$B139*(1+'Income Statement Assumptions'!$F$123))/12,0) -> 0 | AA54: =SUM(O54:Z54) -> 0 | AB54: =ROUND(('Income Statement Assumptions'!$B139*(1+'Income Statement Assumptions'!$D139)*(1+'Income Statement Assumptions'!$G139)/4),0) -> 0 | AC54: =ROUND(('Income Statement Assumptions'!$B139*(1+'Income Statement Assumptions'!$D139)*(1+'Income Statement Assumptions'!$G139)/4),0) -> 0 | AD54: =ROUND(('Income Statement Assumptions'!$B139*(1+'Income Statement Assumptions'!$D139)*(1+'Income Statement Assumptions'!$G139)/4),0) -> 0 | AE54: =ROUND(('Income Statement Assumptions'!$B139*(1+'Income Statement Assumptions'!$D139)*(1+'Income Statement Assumptions'!$G139)/4),0) -> 0 | AF54: =SUM(AB54:AE54) -> 0 | AG54: =ROUND(('Income Statement Assumptions'!$B139*(1+'Income Statement Assumptions'!$D139)*(1+'Income Statement Assumptions'!$D139)*(1+'Income Statement Assumptions'!$H139)/4),0) -> 0 | AH54: =ROUND(('Income Statement Assumptions'!$B139*(1+'Income Statement Assumptions'!$D139)*(1+'Income Statement Assumptions'!$D139)*(1+'Income Statement Assumptions'!$H139)/4),0) -> 0 | AI54: =ROUND(('Income Statement Assumptions'!$B139*(1+'Income Statement Assumptions'!$D139)*(1+'Income Statement Assumptions'!$D139)*(1+'Income Statement Assumptions'!$H139)/4),0) -> 0 | AJ54: =ROUND(('Income Statement Assumptions'!$B139*(1+'Income Statement Assumptions'!$D139)*(1+'Income Statement Assumptions'!$D139)*(1+'Income Statement Assumptions'!$H139)/4),0) -> 0 | AK54: =SUM(AG54:AJ54) -> 0 | AL54: =ROUND(('Income Statement Assumptions'!$B139*(1+'Income Statement Assumptions'!$D139)*(1+'Income Statement Assumptions'!$D139)*(1+'Income Statement Assumptions'!$D139)*(1+'Income Statement Assumptions'!$I139)),0) -> 0
A55: ='Income Statement Assumptions'!A140 -> 0 | B55: =ROUND('Income Statement Assumptions'!$B140/12,0) -> 0 | C55: =ROUND('Income Statement Assumptions'!$B140/12,0) -> 0 | D55: =ROUND('Income Statement Assumptions'!$B140/12,0) -> 0 | E55: =ROUND('Income Statement Assumptions'!$B140/12,0) -> 0 | F55: =ROUND('Income Statement Assumptions'!$B140/12,0) -> 0 | G55: =ROUND('Income Statement Assumptions'!$B140/12,0) -> 0 | H55: =ROUND('Income Statement Assumptions'!$B140/12,0) -> 0 | I55: =ROUND('Income Statement Assumptions'!$B140/12,0) -> 0 | ... M55: =ROUND('Income Statement Assumptions'!$B140/12,0) -> 0 | N55: =SUM(B55:M55) -> 0 | O55: =ROUND(('Income Statement Assumptions'!$B140*(1+'Income Statement Assumptions'!$F$123))/12,0) -> 0 | P55: =ROUND(('Income Statement Assumptions'!$B140*(1+'Income Statement Assumptions'!$F$123))/12,0) -> 0 | Q55: =ROUND(('Income Statement Assumptions'!$B140*(1+'Income Statement Assumptions'!$F$123))/12,0) -> 0 | R55: =ROUND(('Income Statement Assumptions'!$B140*(1+'Income Statement Assumptions'!$F$123))/12,0) -> 0 | S55: =ROUND(('Income Statement Assumptions'!$B140*(1+'Income Statement Assumptions'!$F$123))/12,0) -> 0 | T55: =ROUND(('Income Statement Assumptions'!$B140*(1+'Income Statement Assumptions'!$F$123))/12,0) -> 0 | U55: =ROUND(('Income Statement Assumptions'!$B140*(1+'Income Statement Assumptions'!$F$123))/12,0) -> 0 | V55: =ROUND(('Income Statement Assumptions'!$B140*(1+'Income Statement Assumptions'!$F$123))/12,0) -> 0 | ... Z55: =ROUND(('Income Statement Assumptions'!$B140*(1+'Income Statement Assumptions'!$F$123))/12,0) -> 0 | AA55: =SUM(O55:Z55) -> 0 | AB55: =ROUND(('Income Statement Assumptions'!$B140*(1+'Income Statement Assumptions'!$D140)*(1+'Income Statement Assumptions'!$G140)/4),0) -> 0 | AC55: =ROUND(('Income Statement Assumptions'!$B140*(1+'Income Statement Assumptions'!$D140)*(1+'Income Statement Assumptions'!$G140)/4),0) -> 0 | AD55: =ROUND(('Income Statement Assumptions'!$B140*(1+'Income Statement Assumptions'!$D140)*(1+'Income Statement Assumptions'!$G140)/4),0) -> 0 | AE55: =ROUND(('Income Statement Assumptions'!$B140*(1+'Income Statement Assumptions'!$D140)*(1+'Income Statement Assumptions'!$G140)/4),0) -> 0 | AF55: =SUM(AB55:AE55) -> 0 | AG55: =ROUND(('Income Statement Assumptions'!$B140*(1+'Income Statement Assumptions'!$D140)*(1+'Income Statement Assumptions'!$D140)*(1+'Income Statement Assumptions'!$H140)/4),0) -> 0 | AH55: =ROUND(('Income Statement Assumptions'!$B140*(1+'Income Statement Assumptions'!$D140)*(1+'Income Statement Assumptions'!$D140)*(1+'Income Statement Assumptions'!$H140)/4),0) -> 0 | AI55: =ROUND(('Income Statement Assumptions'!$B140*(1+'Income Statement Assumptions'!$D140)*(1+'Income Statement Assumptions'!$D140)*(1+'Income Statement Assumptions'!$H140)/4),0) -> 0 | AJ55: =ROUND(('Income Statement Assumptions'!$B140*(1+'Income Statement Assumptions'!$D140)*(1+'Income Statement Assumptions'!$D140)*(1+'Income Statement Assumptions'!$H140)/4),0) -> 0 | AK55: =SUM(AG55:AJ55) -> 0 | AL55: =ROUND(('Income Statement Assumptions'!$B140*(1+'Income Statement Assumptions'!$D140)*(1+'Income Statement Assumptions'!$D140)*(1+'Income Statement Assumptions'!$D140)*(1+'Income Statement Assumptions'!$I140)),0) -> 0
A56: ='Income Statement Assumptions'!A141 -> 0 | B56: =ROUND('Income Statement Assumptions'!$B141/12,0) -> 0 | C56: =ROUND('Income Statement Assumptions'!$B141/12,0) -> 0 | D56: =ROUND('Income Statement Assumptions'!$B141/12,0) -> 0 | E56: =ROUND('Income Statement Assumptions'!$B141/12,0) -> 0 | F56: =ROUND('Income Statement Assumptions'!$B141/12,0) -> 0 | G56: =ROUND('Income Statement Assumptions'!$B141/12,0) -> 0 | H56: =ROUND('Income Statement Assumptions'!$B141/12,0) -> 0 | I56: =ROUND('Income Statement Assumptions'!$B141/12,0) -> 0 | ... M56: =ROUND('Income Statement Assumptions'!$B141/12,0) -> 0 | N56: =SUM(B56:M56) -> 0 | O56: =ROUND(('Income Statement Assumptions'!$B141*(1+'Income Statement Assumptions'!$F$123))/12,0) -> 0 | P56: =ROUND(('Income Statement Assumptions'!$B141*(1+'Income Statement Assumptions'!$F$123))/12,0) -> 0 | Q56: =ROUND(('Income Statement Assumptions'!$B141*(1+'Income Statement Assumptions'!$F$123))/12,0) -> 0 | R56: =ROUND(('Income Statement Assumptions'!$B141*(1+'Income Statement Assumptions'!$F$123))/12,0) -> 0 | S56: =ROUND(('Income Statement Assumptions'!$B141*(1+'Income Statement Assumptions'!$F$123))/12,0) -> 0 | T56: =ROUND(('Income Statement Assumptions'!$B141*(1+'Income Statement Assumptions'!$F$123))/12,0) -> 0 | U56: =ROUND(('Income Statement Assumptions'!$B141*(1+'Income Statement Assumptions'!$F$123))/12,0) -> 0 | V56: =ROUND(('Income Statement Assumptions'!$B141*(1+'Income Statement Assumptions'!$F$123))/12,0) -> 0 | ... Z56: =ROUND(('Income Statement Assumptions'!$B141*(1+'Income Statement Assumptions'!$F$123))/12,0) -> 0 | AA56: =SUM(O56:Z56) -> 0 | AB56: =ROUND(('Income Statement Assumptions'!$B141*(1+'Income Statement Assumptions'!$D141)*(1+'Income Statement Assumptions'!$G141)/4),0) -> 0 | AC56: =ROUND(('Income Statement Assumptions'!$B141*(1+'Income Statement Assumptions'!$D141)*(1+'Income Statement Assumptions'!$G141)/4),0) -> 0 | AD56: =ROUND(('Income Statement Assumptions'!$B141*(1+'Income Statement Assumptions'!$D141)*(1+'Income Statement Assumptions'!$G141)/4),0) -> 0 | AE56: =ROUND(('Income Statement Assumptions'!$B141*(1+'Income Statement Assumptions'!$D141)*(1+'Income Statement Assumptions'!$G141)/4),0) -> 0 | AF56: =SUM(AB56:AE56) -> 0 | AG56: =ROUND(('Income Statement Assumptions'!$B141*(1+'Income Statement Assumptions'!$D141)*(1+'Income Statement Assumptions'!$D141)*(1+'Income Statement Assumptions'!$H141)/4),0) -> 0 | AH56: =ROUND(('Income Statement Assumptions'!$B141*(1+'Income Statement Assumptions'!$D141)*(1+'Income Statement Assumptions'!$D141)*(1+'Income Statement Assumptions'!$H141)/4),0) -> 0 | AI56: =ROUND(('Income Statement Assumptions'!$B141*(1+'Income Statement Assumptions'!$D141)*(1+'Income Statement Assumptions'!$D141)*(1+'Income Statement Assumptions'!$H141)/4),0) -> 0 | AJ56: =ROUND(('Income Statement Assumptions'!$B141*(1+'Income Statement Assumptions'!$D141)*(1+'Income Statement Assumptions'!$D141)*(1+'Income Statement Assumptions'!$H141)/4),0) -> 0 | AK56: =SUM(AG56:AJ56) -> 0 | AL56: =ROUND(('Income Statement Assumptions'!$B141*(1+'Income Statement Assumptions'!$D141)*(1+'Income Statement Assumptions'!$D141)*(1+'Income Statement Assumptions'!$D141)*(1+'Income Statement Assumptions'!$I141)),0) -> 0
A57: ='Income Statement Assumptions'!A142 -> 0 | B57: =ROUND('Income Statement Assumptions'!$B142/12,0) -> 0 | C57: =ROUND('Income Statement Assumptions'!$B142/12,0) -> 0 | D57: =ROUND('Income Statement Assumptions'!$B142/12,0) -> 0 | E57: =ROUND('Income Statement Assumptions'!$B142/12,0) -> 0 | F57: =ROUND('Income Statement Assumptions'!$B142/12,0) -> 0 | G57: =ROUND('Income Statement Assumptions'!$B142/12,0) -> 0 | H57: =ROUND('Income Statement Assumptions'!$B142/12,0) -> 0 | I57: =ROUND('Income Statement Assumptions'!$B142/12,0) -> 0 | ... M57: =ROUND('Income Statement Assumptions'!$B142/12,0) -> 0 | N57: =SUM(B57:M57) -> 0 | O57: =ROUND(('Income Statement Assumptions'!$B142*(1+'Income Statement Assumptions'!$F$123))/12,0) -> 0 | P57: =ROUND(('Income Statement Assumptions'!$B142*(1+'Income Statement Assumptions'!$F$123))/12,0) -> 0 | Q57: =ROUND(('Income Statement Assumptions'!$B142*(1+'Income Statement Assumptions'!$F$123))/12,0) -> 0 | R57: =ROUND(('Income Statement Assumptions'!$B142*(1+'Income Statement Assumptions'!$F$123))/12,0) -> 0 | S57: =ROUND(('Income Statement Assumptions'!$B142*(1+'Income Statement Assumptions'!$F$123))/12,0) -> 0 | T57: =ROUND(('Income Statement Assumptions'!$B142*(1+'Income Statement Assumptions'!$F$123))/12,0) -> 0 | U57: =ROUND(('Income Statement Assumptions'!$B142*(1+'Income Statement Assumptions'!$F$123))/12,0) -> 0 | V57: =ROUND(('Income Statement Assumptions'!$B142*(1+'Income Statement Assumptions'!$F$123))/12,0) -> 0 | ... Z57: =ROUND(('Income Statement Assumptions'!$B142*(1+'Income Statement Assumptions'!$F$123))/12,0) -> 0 | AA57: =SUM(O57:Z57) -> 0 | AB57: =ROUND(('Income Statement Assumptions'!$B142*(1+'Income Statement Assumptions'!$D142)*(1+'Income Statement Assumptions'!$G142)/4),0) -> 0 | AC57: =ROUND(('Income Statement Assumptions'!$B142*(1+'Income Statement Assumptions'!$D142)*(1+'Income Statement Assumptions'!$G142)/4),0) -> 0 | AD57: =ROUND(('Income Statement Assumptions'!$B142*(1+'Income Statement Assumptions'!$D142)*(1+'Income Statement Assumptions'!$G142)/4),0) -> 0 | AE57: =ROUND(('Income Statement Assumptions'!$B142*(1+'Income Statement Assumptions'!$D142)*(1+'Income Statement Assumptions'!$G142)/4),0) -> 0 | AF57: =SUM(AB57:AE57) -> 0 | AG57: =ROUND(('Income Statement Assumptions'!$B142*(1+'Income Statement Assumptions'!$D142)*(1+'Income Statement Assumptions'!$D142)*(1+'Income Statement Assumptions'!$H142)/4),0) -> 0 | AH57: =ROUND(('Income Statement Assumptions'!$B142*(1+'Income Statement Assumptions'!$D142)*(1+'Income Statement Assumptions'!$D142)*(1+'Income Statement Assumptions'!$H142)/4),0) -> 0 | AI57: =ROUND(('Income Statement Assumptions'!$B142*(1+'Income Statement Assumptions'!$D142)*(1+'Income Statement Assumptions'!$D142)*(1+'Income Statement Assumptions'!$H142)/4),0) -> 0 | AJ57: =ROUND(('Income Statement Assumptions'!$B142*(1+'Income Statement Assumptions'!$D142)*(1+'Income Statement Assumptions'!$D142)*(1+'Income Statement Assumptions'!$H142)/4),0) -> 0 | AK57: =SUM(AG57:AJ57) -> 0 | AL57: =ROUND(('Income Statement Assumptions'!$B142*(1+'Income Statement Assumptions'!$D142)*(1+'Income Statement Assumptions'!$D142)*(1+'Income Statement Assumptions'!$D142)*(1+'Income Statement Assumptions'!$I142)),0) -> 0
A58: ='Income Statement Assumptions'!A143 -> 0 | B58: =ROUND('Income Statement Assumptions'!$B143/12,0) -> 0 | C58: =ROUND('Income Statement Assumptions'!$B143/12,0) -> 0 | D58: =ROUND('Income Statement Assumptions'!$B143/12,0) -> 0 | E58: =ROUND('Income Statement Assumptions'!$B143/12,0) -> 0 | F58: =ROUND('Income Statement Assumptions'!$B143/12,0) -> 0 | G58: =ROUND('Income Statement Assumptions'!$B143/12,0) -> 0 | H58: =ROUND('Income Statement Assumptions'!$B143/12,0) -> 0 | I58: =ROUND('Income Statement Assumptions'!$B143/12,0) -> 0 | ... M58: =ROUND('Income Statement Assumptions'!$B143/12,0) -> 0 | N58: =SUM(B58:M58) -> 0 | O58: =ROUND(('Income Statement Assumptions'!$B143*(1+'Income Statement Assumptions'!$F$123))/12,0) -> 0 | P58: =ROUND(('Income Statement Assumptions'!$B143*(1+'Income Statement Assumptions'!$F$123))/12,0) -> 0 | Q58: =ROUND(('Income Statement Assumptions'!$B143*(1+'Income Statement Assumptions'!$F$123))/12,0) -> 0 | R58: =ROUND(('Income Statement Assumptions'!$B143*(1+'Income Statement Assumptions'!$F$123))/12,0) -> 0 | S58: =ROUND(('Income Statement Assumptions'!$B143*(1+'Income Statement Assumptions'!$F$123))/12,0) -> 0 | T58: =ROUND(('Income Statement Assumptions'!$B143*(1+'Income Statement Assumptions'!$F$123))/12,0) -> 0 | U58: =ROUND(('Income Statement Assumptions'!$B143*(1+'Income Statement Assumptions'!$F$123))/12,0) -> 0 | V58: =ROUND(('Income Statement Assumptions'!$B143*(1+'Income Statement Assumptions'!$F$123))/12,0) -> 0 | ... Z58: =ROUND(('Income Statement Assumptions'!$B143*(1+'Income Statement Assumptions'!$F$123))/12,0) -> 0 | AA58: =SUM(O58:Z58) -> 0 | AB58: =ROUND(('Income Statement Assumptions'!$B143*(1+'Income Statement Assumptions'!$D143)*(1+'Income Statement Assumptions'!$G143)/4),0) -> 0 | AC58: =ROUND(('Income Statement Assumptions'!$B143*(1+'Income Statement Assumptions'!$D143)*(1+'Income Statement Assumptions'!$G143)/4),0) -> 0 | AD58: =ROUND(('Income Statement Assumptions'!$B143*(1+'Income Statement Assumptions'!$D143)*(1+'Income Statement Assumptions'!$G143)/4),0) -> 0 | AE58: =ROUND(('Income Statement Assumptions'!$B143*(1+'Income Statement Assumptions'!$D143)*(1+'Income Statement Assumptions'!$G143)/4),0) -> 0 | AF58: =SUM(AB58:AE58) -> 0 | AG58: =ROUND(('Income Statement Assumptions'!$B143*(1+'Income Statement Assumptions'!$D143)*(1+'Income Statement Assumptions'!$D143)*(1+'Income Statement Assumptions'!$H143)/4),0) -> 0 | AH58: =ROUND(('Income Statement Assumptions'!$B143*(1+'Income Statement Assumptions'!$D143)*(1+'Income Statement Assumptions'!$D143)*(1+'Income Statement Assumptions'!$H143)/4),0) -> 0 | AI58: =ROUND(('Income Statement Assumptions'!$B143*(1+'Income Statement Assumptions'!$D143)*(1+'Income Statement Assumptions'!$D143)*(1+'Income Statement Assumptions'!$H143)/4),0) -> 0 | AJ58: =ROUND(('Income Statement Assumptions'!$B143*(1+'Income Statement Assumptions'!$D143)*(1+'Income Statement Assumptions'!$D143)*(1+'Income Statement Assumptions'!$H143)/4),0) -> 0 | AK58: =SUM(AG58:AJ58) -> 0 | AL58: =ROUND(('Income Statement Assumptions'!$B143*(1+'Income Statement Assumptions'!$D143)*(1+'Income Statement Assumptions'!$D143)*(1+'Income Statement Assumptions'!$D143)*(1+'Income Statement Assumptions'!$I143)),0) -> 0
A59: ='Income Statement Assumptions'!A144 -> 0 | B59: =ROUND('Income Statement Assumptions'!$B144/12,0) -> 0 | C59: =ROUND('Income Statement Assumptions'!$B144/12,0) -> 0 | D59: =ROUND('Income Statement Assumptions'!$B144/12,0) -> 0 | E59: =ROUND('Income Statement Assumptions'!$B144/12,0) -> 0 | F59: =ROUND('Income Statement Assumptions'!$B144/12,0) -> 0 | G59: =ROUND('Income Statement Assumptions'!$B144/12,0) -> 0 | H59: =ROUND('Income Statement Assumptions'!$B144/12,0) -> 0 | I59: =ROUND('Income Statement Assumptions'!$B144/12,0) -> 0 | ... M59: =ROUND('Income Statement Assumptions'!$B144/12,0) -> 0 | N59: =SUM(B59:M59) -> 0 | O59: =ROUND(('Income Statement Assumptions'!$B144*(1+'Income Statement Assumptions'!$F$123))/12,0) -> 0 | P59: =ROUND(('Income Statement Assumptions'!$B144*(1+'Income Statement Assumptions'!$F$123))/12,0) -> 0 | Q59: =ROUND(('Income Statement Assumptions'!$B144*(1+'Income Statement Assumptions'!$F$123))/12,0) -> 0 | R59: =ROUND(('Income Statement Assumptions'!$B144*(1+'Income Statement Assumptions'!$F$123))/12,0) -> 0 | S59: =ROUND(('Income Statement Assumptions'!$B144*(1+'Income Statement Assumptions'!$F$123))/12,0) -> 0 | T59: =ROUND(('Income Statement Assumptions'!$B144*(1+'Income Statement Assumptions'!$F$123))/12,0) -> 0 | U59: =ROUND(('Income Statement Assumptions'!$B144*(1+'Income Statement Assumptions'!$F$123))/12,0) -> 0 | V59: =ROUND(('Income Statement Assumptions'!$B144*(1+'Income Statement Assumptions'!$F$123))/12,0) -> 0 | ... Z59: =ROUND(('Income Statement Assumptions'!$B144*(1+'Income Statement Assumptions'!$F$123))/12,0) -> 0 | AA59: =SUM(O59:Z59) -> 0 | AB59: =ROUND(('Income Statement Assumptions'!$B144*(1+'Income Statement Assumptions'!$D144)*(1+'Income Statement Assumptions'!$G144)/4),0) -> 0 | AC59: =ROUND(('Income Statement Assumptions'!$B144*(1+'Income Statement Assumptions'!$D144)*(1+'Income Statement Assumptions'!$G144)/4),0) -> 0 | AD59: =ROUND(('Income Statement Assumptions'!$B144*(1+'Income Statement Assumptions'!$D144)*(1+'Income Statement Assumptions'!$G144)/4),0) -> 0 | AE59: =ROUND(('Income Statement Assumptions'!$B144*(1+'Income Statement Assumptions'!$D144)*(1+'Income Statement Assumptions'!$G144)/4),0) -> 0 | AF59: =SUM(AB59:AE59) -> 0 | AG59: =ROUND(('Income Statement Assumptions'!$B144*(1+'Income Statement Assumptions'!$D144)*(1+'Income Statement Assumptions'!$D144)*(1+'Income Statement Assumptions'!$H144)/4),0) -> 0 | AH59: =ROUND(('Income Statement Assumptions'!$B144*(1+'Income Statement Assumptions'!$D144)*(1+'Income Statement Assumptions'!$D144)*(1+'Income Statement Assumptions'!$H144)/4),0) -> 0 | AI59: =ROUND(('Income Statement Assumptions'!$B144*(1+'Income Statement Assumptions'!$D144)*(1+'Income Statement Assumptions'!$D144)*(1+'Income Statement Assumptions'!$H144)/4),0) -> 0 | AJ59: =ROUND(('Income Statement Assumptions'!$B144*(1+'Income Statement Assumptions'!$D144)*(1+'Income Statement Assumptions'!$D144)*(1+'Income Statement Assumptions'!$H144)/4),0) -> 0 | AK59: =SUM(AG59:AJ59) -> 0 | AL59: =ROUND(('Income Statement Assumptions'!$B144*(1+'Income Statement Assumptions'!$D144)*(1+'Income Statement Assumptions'!$D144)*(1+'Income Statement Assumptions'!$D144)*(1+'Income Statement Assumptions'!$I144)),0) -> 0
A61: Total Selling & Adminstrative Expenses | B61: =SUM(B36:B59) -> 163442 | C61: =SUM(C36:C59) -> 38442 | D61: =SUM(D36:D59) -> 38442 | E61: =SUM(E36:E59) -> 38442 | F61: =SUM(F36:F59) -> 38442 | G61: =SUM(G36:G59) -> 38442 | H61: =SUM(H36:H59) -> 38442 | I61: =SUM(I36:I59) -> 41775 | ... AL61: =SUM(AL36:AL59) -> 784469
A63: Earnings/(Loss) Before Taxes | B63: =B33-B61 -> -163442 | C63: =C33-C61 -> -38442 | D63: =D33-D61 -> -38442 | E63: =E33-E61 -> -38442 | F63: =F33-F61 -> -38442 | G63: =G33-G61 -> -38442 | H63: =H33-H61 -> -27632 | I63: =I33-I61 -> -30260 | ... AL63: =AL33-AL61 -> 5718242
A65: Income Tax Expense | AC65: =(AB69+AC63)*'Income Statement Assumptions'!B149 -> 40603.35 | AD65: =AD63*'Income Statement Assumptions'!B149 -> 130037.7 | AE65: =AE63*'Income Statement Assumptions'!B149 -> 174071.7 | AF65: =SUM(AB65:AE65) -> 344712.75 | AG65: =AG63*'Income Statement Assumptions'!B149 -> 239040 | AH65: =AH63*'Income Statement Assumptions'!B149 -> 282468 | AI65: =AI63*'Income Statement Assumptions'!B149 -> 332409 | AJ65: =AJ63*'Income Statement Assumptions'!B149 -> 389842.8 | AK65: =+SUM(AG65:AJ65) -> 1243759.8 | AL65: =AL63*'Income Statement Assumptions'!B149 -> 1715472.6
A67: Net Income/(Loss) | B67: =B63-B65 -> -163442 | C67: =C63-C65 -> -38442 | D67: =D63-D65 -> -38442 | E67: =E63-E65 -> -38442 | F67: =F63-F65 -> -38442 | G67: =G63-G65 -> -38442 | H67: =H63-H65 -> -27632 | I67: =I63-I65 -> -30260 | ... AL67: =AL63-AL65 -> 4002769.4
A69: Net Operating Loss Carryover | B69: ='Statement of Retained Earnings'!B7 -> -163442 | C69: =B69+'Statement of Retained Earnings'!C7 -> -201884 | D69: =C69+'Statement of Retained Earnings'!D7 -> -240326 | E69: =D69+'Statement of Retained Earnings'!E7 -> -278768 | F69: =E69+'Statement of Retained Earnings'!F7 -> -317210 | G69: =F69+'Statement of Retained Earnings'!G7 -> -355652 | H69: =G69+'Statement of Retained Earnings'!H7 -> -383284 | I69: =H69+'Statement of Retained Earnings'!I7 -> -413544 | J69: =I69+'Statement of Retained Earnings'!J7 -> -439831.5 | ... M69: =L69+'Statement of Retained Earnings'!M7 -> -503586.5 | N69: =M69 -> -503586.5 | O69: =N69+O63 -> -523512.5 | P69: =O69+P63 -> -540144.5 | Q69: =P69+Q63 -> -553067.5 | R69: =Q69+R63 -> -561814.5 | S69: =R69+S63 -> -565868.5 | T69: =S69+T63 -> -564631.5 | U69: =T69+U63 -> -557448.5 | V69: =U69+V63 -> -543573.5 | ... Z69: =Y69+Z63 -> -402767.5 | AA69: =Z69 -> -402767.5 | AB69: =AA69+AB67 -> -180680.5 | AC69: =AB69+AC67 -> 94741.15 | AD69: =AC69+AD67 -> 398162.45 | AE69: =AD69+AE67 -> 804329.75 | AF69: =AE69 -> 804329.75 | AG69: =AF69+AG67 -> 1362089.8 | AH69: =AG69+AH67 -> 2021181.8 | AI69: =AH69+AI67 -> 2796802.8 | AJ69: =AI69+AJ67 -> 3706436 | AK69: =AJ69 -> 3706436 | AL69: =AK69+AL67 -> 7709205.4

Sheet Statement of Retained Earnings
B1: Company Name | N1: =B1 -> Company Name | Z1: =N1 -> Company Name
B2: Statement of Retained Earnings | N2: Statement of Retained Earnings | Z2: Statement of Retained Earnings
B4: Year 1 | N4: Year 2 | Z4: Year 3 | AD4: Year 4 | AH4: Year 5
B5: January | C5: February | D5: March | E5: April | F5: May | G5: June | H5: July | I5: August | J5: September | K5: October | L5: November | M5: December | N5: January | O5: February | P5: March | Q5: April | R5: May | S5: June | T5: July | U5: August | V5: September | W5: October | X5: November | Y5: December | Z5: Quarter 1 | AA5: Quarter 2 | AB5: Quarter 3 | AC5: Quarter 4 | AD5: Quarter 1 | AE5: Quarter 2 | AF5: Quarter 3 | AG5: Quarter 4 | AH5: Total
A6: Beginning Retained Earnings | B6: 0 | C6: =B9 -> -163442 | D6: =C9 -> -201884 | E6: =D9 -> -240326 | F6: =E9 -> -278768 | G6: =F9 -> -317210 | H6: =G9 -> -355652 | I6: =H9 -> -383284 | J6: =I9 -> -413544 | ... AH6: =AG9 -> 3706436
A7: Net Income/(Loss) | B7: ='Income Statement'!B67 -> -163442 | C7: ='Income Statement'!C67 -> -38442 | D7: ='Income Statement'!D67 -> -38442 | E7: ='Income Statement'!E67 -> -38442 | F7: ='Income Statement'!F67 -> -38442 | G7: ='Income Statement'!G67 -> -38442 | H7: ='Income Statement'!H67 -> -27632 | I7: ='Income Statement'!I67 -> -30260 | ... M7: ='Income Statement'!M67 -> -18275 | N7: ='Income Statement'!O67 -> -19926 | O7: ='Income Statement'!P67 -> -16632 | P7: ='Income Statement'!Q67 -> -12923 | Q7: ='Income Statement'!R67 -> -8747 | R7: ='Income Statement'!S67 -> -4054 | S7: ='Income Statement'!T67 -> 1237 | T7: ='Income Statement'!U67 -> 7183 | U7: ='Income Statement'!V67 -> 13875 | ... Y7: ='Income Statement'!Z67 -> 50120 | Z7: ='Income Statement'!AB67 -> 222087 | AA7: ='Income Statement'!AC67 -> 275421.65 | AB7: ='Income Statement'!AD67 -> 303421.3 | AC7: ='Income Statement'!AE67 -> 406167.3 | AD7: ='Income Statement'!AG67 -> 557760 | AE7: ='Income Statement'!AH67 -> 659092 | AF7: ='Income Statement'!AI67 -> 775621 | AG7: ='Income Statement'!AJ67 -> 909633.2 | AH7: ='Income Statement'!AL67 -> 4002769.4
A8: Dividends | B8: =-'Cash Flow Statement'!B27 -> 0 | C8: =-'Cash Flow Statement'!C27 -> 0 | D8: =-'Cash Flow Statement'!D27 -> 0 | E8: =-'Cash Flow Statement'!E27 -> 0 | F8: =-'Cash Flow Statement'!F27 -> 0 | G8: =-'Cash Flow Statement'!G27 -> 0 | H8: =-'Cash Flow Statement'!H27 -> 0 | I8: =-'Cash Flow Statement'!I27 -> 0 | ... M8: =-'Cash Flow Statement'!M27 -> 0 | N8: ='Cash Flow Statement'!O27 -> 0 | O8: ='Cash Flow Statement'!P27 -> 0 | P8: ='Cash Flow Statement'!Q27 -> 0 | Q8: ='Cash Flow Statement'!R27 -> 0 | R8: ='Cash Flow Statement'!S27 -> 0 | S8: ='Cash Flow Statement'!T27 -> 0 | T8: ='Cash Flow Statement'!U27 -> 0 | U8: ='Cash Flow Statement'!V27 -> 0 | ... Y8: ='Cash Flow Statement'!Z27 -> 0 | Z8: ='Cash Flow Statement'!AB27 -> 0 | AA8: ='Cash Flow Statement'!AC27 -> 0 | AB8: ='Cash Flow Statement'!AD27 -> 0 | AC8: ='Cash Flow Statement'!AE27 -> 0 | AD8: ='Cash Flow Statement'!AG27 -> 0 | AE8: ='Cash Flow Statement'!AH27 -> 0 | AF8: ='Cash Flow Statement'!AI27 -> 0 | AG8: ='Cash Flow Statement'!AJ27 -> 0 | AH8: ='Cash Flow Statement'!AL27 -> 0
A9: Ending Retained Earnings | B9: =B6+B7-B8 -> -163442 | C9: =C6+C7-C8 -> -201884 | D9: =D6+D7-D8 -> -240326 | E9: =E6+E7-E8 -> -278768 | F9: =F6+F7-F8 -> -317210 | G9: =G6+G7-G8 -> -355652 | H9: =H6+H7-H8 -> -383284 | I9: =I6+I7-I8 -> -413544 | ... AH9: =AH6+AH7-AH8 -> 7709205.4

Sheet Balance Sheet
C1: Company Name | O1: =C1 -> Company Name | AA1: =O1 -> Company Name
C2: Balance Sheet | O2: Balance Sheet | AA2: Balance Sheet
C4: Year 1 | O4: Year 2 | AA4: Year 3 | AE4: Year 4 | AI4: Year 5
C5: January | D5: February | E5: March | F5: April | G5: May | H5: June | I5: July | J5: August | K5: September | L5: October | M5: November | N5: December | O5: January | P5: February | Q5: March | R5: April | S5: May | T5: June | U5: July | V5: August | W5: September | X5: October | Y5: November | Z5: December | AA5: Quarter 1 | AB5: Quarter 2 | AC5: Quarter 3 | AD5: Quarter 4 | AE5: Quarter 1 | AF5: Quarter 2 | AG5: Quarter 3 | AH5: Quarter 4 | AI5: Total
A6: Assets:
A7: Current Assets
B8: Cash | C8: ='Cash Flow Statement'!B35 -> 543458 | D8: ='Cash Flow Statement'!C35 -> 505916 | E8: ='Cash Flow Statement'!D35 -> 468374 | F8: ='Cash Flow Statement'!E35 -> 430832 | G8: ='Cash Flow Statement'!F35 -> 393290 | H8: ='Cash Flow Statement'!G35 -> 355748 | I8: ='Cash Flow Statement'!H35 -> 319624 | J8: ='Cash Flow Statement'!I35 -> 289808 | ... N8: ='Cash Flow Statement'!M35 -> 193813.5 | O8: ='Cash Flow Statement'!O35 -> 169907.7 | P8: ='Cash Flow Statement'!P35 -> 151493.5 | Q8: ='Cash Flow Statement'!Q35 -> 136444.3 | R8: ='Cash Flow Statement'!R35 -> 125185.9 | S8: ='Cash Flow Statement'!S35 -> 118192.1 | T8: ='Cash Flow Statement'!T35 -> 115996.5 | U8: ='Cash Flow Statement'!U35 -> 119204.3 | V8: ='Cash Flow Statement'!V35 -> 128488.1 | ... Z8: ='Cash Flow Statement'!Z35 -> 243094.5 | AA8: ='Cash Flow Statement'!AB35 -> 444748.5 | AB8: ='Cash Flow Statement'!AC35 -> 698542.15 | AC8: ='Cash Flow Statement'!AD35 -> 974163.45 | AD8: ='Cash Flow Statement'!AE35 -> 1344819.8 | AE8: ='Cash Flow Statement'!AG35 -> 1839521.8 | AF8: ='Cash Flow Statement'!AH35 -> 2465904.8 | AG8: ='Cash Flow Statement'!AI35 -> 3203336.8 | AH8: ='Cash Flow Statement'!AJ35 -> 4068473 | AI8: ='Cash Flow Statement'!AL35 -> 8042927.4
B9: Accounts Receivable | C9: =ROUND('Balance Sheet Assumptions'!$B$5*'Income Statement'!B10,0) -> 0 | D9: =ROUND('Balance Sheet Assumptions'!$B$5*'Income Statement'!C10,0) -> 0 | E9: =ROUND('Balance Sheet Assumptions'!$B$5*'Income Statement'!D10,0) -> 0 | F9: =ROUND('Balance Sheet Assumptions'!$B$5*'Income Statement'!E10,0) -> 0 | G9: =ROUND('Balance Sheet Assumptions'!$B$5*'Income Statement'!F10,0) -> 0 | H9: =ROUND('Balance Sheet Assumptions'!$B$5*'Income Statement'!G10,0) -> 0 | I9: =ROUND('Balance Sheet Assumptions'!$B$5*'Income Statement'!H10,0) -> 12050 | J9: =ROUND('Balance Sheet Assumptions'!$B$5*'Income Statement'!I10,0) -> 12575 | ... N9: =ROUND('Balance Sheet Assumptions'!$B$5*'Income Statement'!M10,0) -> 24500 | O9: =ROUND('Balance Sheet Assumptions'!$B$5*'Income Statement'!O10,0) -> 27570 | P9: =ROUND('Balance Sheet Assumptions'!$B$5*'Income Statement'!P10,0) -> 31011 | Q9: =ROUND('Balance Sheet Assumptions'!$B$5*'Income Statement'!Q10,0) -> 34887 | R9: =ROUND('Balance Sheet Assumptions'!$B$5*'Income Statement'!R10,0) -> 39248 | S9: =ROUND('Balance Sheet Assumptions'!$B$5*'Income Statement'!S10,0) -> 44153 | T9: =ROUND('Balance Sheet Assumptions'!$B$5*'Income Statement'!T10,0) -> 49678 | U9: =ROUND('Balance Sheet Assumptions'!$B$5*'Income Statement'!U10,0) -> 55890 | V9: =ROUND('Balance Sheet Assumptions'!$B$5*'Income Statement'!V10,0) -> 62880 | ... Z9: =ROUND('Balance Sheet Assumptions'!$B$5*'Income Statement'!Z10,0) -> 100737 | AA9: =ROUND((('Balance Sheet Assumptions'!$B$5*'Income Statement'!AB10)/3),0) -> 122771 | AB9: =ROUND((('Balance Sheet Assumptions'!$B$5*'Income Statement'!AC10)/3),0) -> 153464 | AC9: =ROUND((('Balance Sheet Assumptions'!$B$5*'Income Statement'!AD10)/3),0) -> 191833 | AD9: =ROUND((('Balance Sheet Assumptions'!$B$5*'Income Statement'!AE10)/3),0) -> 239792 | AE9: =ROUND((('Balance Sheet Assumptions'!$B$5*'Income Statement'!AG10)/3),0) -> 298957 | AF9: =ROUND((('Balance Sheet Assumptions'!$B$5*'Income Statement'!AH10)/3),0) -> 343802 | AG9: =ROUND((('Balance Sheet Assumptions'!$B$5*'Income Statement'!AI10)/3),0) -> 395371 | AH9: =ROUND((('Balance Sheet Assumptions'!$B$5*'Income Statement'!AJ10)/3),0) -> 454678 | AI9: =ROUND((('Balance Sheet Assumptions'!$B$5*'Income Statement'!AL10)/12),0) -> 503985
B10: Inventory | C10: =ROUND('Balance Sheet Assumptions'!$B$7*'Income Statement'!B31,0) -> 0 | D10: =ROUND('Balance Sheet Assumptions'!$B$7*'Income Statement'!C31,0) -> 0 | E10: =ROUND('Balance Sheet Assumptions'!$B$7*'Income Statement'!D31,0) -> 0 | F10: =ROUND('Balance Sheet Assumptions'!$B$7*'Income Statement'!E31,0) -> 0 | G10: =ROUND('Balance Sheet Assumptions'!$B$7*'Income Statement'!F31,0) -> 0 | H10: =ROUND('Balance Sheet Assumptions'!$B$7*'Income Statement'!G31,0) -> 0 | I10: =ROUND('Balance Sheet Assumptions'!$B$7*'Income Statement'!H31,0) -> 5316 | J10: =ROUND('Balance Sheet Assumptions'!$B$7*'Income Statement'!I31,0) -> 5454 | ... N10: =ROUND('Balance Sheet Assumptions'!$B$7*'Income Statement'!M31,0) -> 10200 | O10: =ROUND('Balance Sheet Assumptions'!$B$7*'Income Statement'!O31,0) -> 11499 | P10: =ROUND('Balance Sheet Assumptions'!$B$7*'Income Statement'!P31,0) -> 12934 | Q10: =ROUND('Balance Sheet Assumptions'!$B$7*'Income Statement'!Q31,0) -> 14551 | R10: =ROUND('Balance Sheet Assumptions'!$B$7*'Income Statement'!R31,0) -> 16370 | S10: =ROUND('Balance Sheet Assumptions'!$B$7*'Income Statement'!S31,0) -> 18416 | T10: =ROUND('Balance Sheet Assumptions'!$B$7*'Income Statement'!T31,0) -> 20720 | U10: =ROUND('Balance Sheet Assumptions'!$B$7*'Income Statement'!U31,0) -> 23311 | V10: =ROUND('Balance Sheet Assumptions'!$B$7*'Income Statement'!V31,0) -> 26226 | ... Z10: =ROUND('Balance Sheet Assumptions'!$B$7*'Income Statement'!Z31,0) -> 42014 | AA10: =ROUND(('Balance Sheet Assumptions'!$B$7*'Income Statement'!AB31)/3,0) -> 48117 | AB10: =ROUND(('Balance Sheet Assumptions'!$B$7*'Income Statement'!AC31)/3,0) -> 60146 | AC10: =ROUND(('Balance Sheet Assumptions'!$B$7*'Income Statement'!AD31)/3,0) -> 75183 | AD10: =ROUND(('Balance Sheet Assumptions'!$B$7*'Income Statement'!AE31)/3,0) -> 93980 | AE10: =ROUND(('Balance Sheet Assumptions'!$B$7*'Income Statement'!AG31)/3,0) -> 110492 | AF10: =ROUND(('Balance Sheet Assumptions'!$B$7*'Income Statement'!AH31)/3,0) -> 127067 | AG10: =ROUND(('Balance Sheet Assumptions'!$B$7*'Income Statement'!AI31)/3,0) -> 146126 | AH10: =ROUND(('Balance Sheet Assumptions'!$B$7*'Income Statement'!AJ31)/3,0) -> 168045 | AI10: =ROUND(('Balance Sheet Assumptions'!$B$7*'Income Statement'!AL31)/12,0) -> 186431
B11: Other Current Assets | C11: 0 | D11: 0 | E11: 0 | F11: 0 | G11: 0 | H11: 0 | I11: 0 | J11: 0 | K11: 0 | L11: 0 | M11: 0 | N11: 0 | O11: 0 | P11: 0 | Q11: 0 | R11: 0 | S11: 0 | T11: 0 | U11: 0 | V11: 0 | W11: 0 | X11: 0 | Y11: 0 | Z11: 0 | AA11: 0 | AB11: 0 | AC11: 0 | AD11: 0 | AE11: 0 | AF11: 0 | AG11: 0 | AH11: 0 | AI11: 0
A12: Total Current Assets | C12: =SUM(C8:C11) -> 543458 | D12: =SUM(D8:D11) -> 505916 | E12: =SUM(E8:E11) -> 468374 | F12: =SUM(F8:F11) -> 430832 | G12: =SUM(G8:G11) -> 393290 | H12: =SUM(H8:H11) -> 355748 | I12: =SUM(I8:I11) -> 336990 | J12: =SUM(J8:J11) -> 307837 | ... AI12: =SUM(AI8:AI11) -> 8733343.4
A14: Non-Current Assets
B15: Property, Plant, & Equipment | C15: ='Fixed Asset Assumptions'!B25 -> 49000 | D15: =C15 -> 49000 | E15: =D15 -> 49000 | F15: =E15 -> 49000 | G15: =F15 -> 49000 | H15: =G15 -> 49000 | I15: =H15 -> 49000 | J15: =I15 -> 49000 | K15: =J15 -> 49000 | ... N15: =M15 -> 49000 | O15: ='Fixed Asset Assumptions'!C25 -> 51500 | P15: =O15 -> 51500 | Q15: =P15 -> 51500 | R15: =Q15 -> 51500 | S15: =R15 -> 51500 | T15: =S15 -> 51500 | U15: =T15 -> 51500 | V15: =U15 -> 51500 | W15: =V15 -> 51500 | ... Z15: =Y15 -> 51500 | AA15: ='Fixed Asset Assumptions'!D25 -> 56000 | AB15: =AA15 -> 56000 | AC15: =AB15 -> 56000 | AD15: =AC15 -> 56000 | AE15: ='Fixed Asset Assumptions'!E25 -> 72000 | AF15: =AE15 -> 72000 | AG15: =AF15 -> 72000 | AH15: =AG15 -> 72000 | AI15: ='Fixed Asset Assumptions'!F25 -> 76500
B16: Accumulated Depreciation | C16: ='Income Statement'!B43 -> 817 | D16: =C16+'Income Statement'!C43 -> 1634 | E16: =D16+'Income Statement'!D43 -> 2451 | F16: =E16+'Income Statement'!E43 -> 3268 | G16: =F16+'Income Statement'!F43 -> 4085 | H16: =G16+'Income Statement'!G43 -> 4902 | I16: =H16+'Income Statement'!H43 -> 5719 | J16: =I16+'Income Statement'!I43 -> 6536 | K16: =J16+'Income Statement'!J43 -> 7353 | ... N16: =M16+'Income Statement'!M43 -> 9804 | O16: =N16+'Income Statement'!O43 -> 10662 | P16: =O16+'Income Statement'!P43 -> 11520 | Q16: =P16+'Income Statement'!Q43 -> 12378 | R16: =Q16+'Income Statement'!R43 -> 13236 | S16: =R16+'Income Statement'!S43 -> 14094 | T16: =S16+'Income Statement'!T43 -> 14952 | U16: =T16+'Income Statement'!U43 -> 15810 | V16: =U16+'Income Statement'!V43 -> 16668 | ... Z16: =Y16+'Income Statement'!Z43 -> 20100 | AA16: =Z16+'Income Statement'!AB43 -> 22900 | AB16: =AA16+'Income Statement'!AC43 -> 25700 | AC16: =AB16+'Income Statement'!AD43 -> 28500 | AD16: =AC16+'Income Statement'!AE43 -> 31300 | AE16: =AD16+'Income Statement'!AG43 -> 34900 | AF16: =AE16+'Income Statement'!AH43 -> 38500 | AG16: =AF16+'Income Statement'!AI43 -> 42100 | AH16: =AG16+'Income Statement'!AJ43 -> 45700 | AI16: =AH16+'Income Statement'!AL43 -> 61000
B17: Net PP&E | C17: =C15-C16 -> 48183 | D17: =D15-D16 -> 47366 | E17: =E15-E16 -> 46549 | F17: =F15-F16 -> 45732 | G17: =G15-G16 -> 44915 | H17: =H15-H16 -> 44098 | I17: =I15-I16 -> 43281 | J17: =J15-J16 -> 42464 | ... AI17: =AI15-AI16 -> 15500
B19: Intangible Assets | C19: ='Fixed Asset Assumptions'!B43 -> 20000 | D19: =C19 -> 20000 | E19: =D19 -> 20000 | F19: =E19 -> 20000 | G19: =F19 -> 20000 | H19: =G19 -> 20000 | I19: =H19 -> 20000 | J19: =I19 -> 20000 | K19: =J19 -> 20000 | ... N19: =M19 -> 20000 | O19: ='Fixed Asset Assumptions'!C43 -> 20000 | P19: =O19 -> 20000 | Q19: =P19 -> 20000 | R19: =Q19 -> 20000 | S19: =R19 -> 20000 | T19: =S19 -> 20000 | U19: =T19 -> 20000 | V19: =U19 -> 20000 | W19: =V19 -> 20000 | ... Z19: =Y19 -> 20000 | AA19: ='Fixed Asset Assumptions'!D43 -> 20000 | AB19: =AA19 -> 20000 | AC19: =AB19 -> 20000 | AD19: =AC19 -> 20000 | AE19: ='Fixed Asset Assumptions'!E43 -> 20000 | AF19: =AE19 -> 20000 | AG19: =AF19 -> 20000 | AH19: =AG19 -> 20000 | AI19: ='Fixed Asset Assumptions'!F43 -> 20000
B20: Accumulated Amortization | C20: ='Income Statement'!B44 -> 83 | D20: =C20+'Income Statement'!C44 -> 166 | E20: =D20+'Income Statement'!D44 -> 249 | F20: =E20+'Income Statement'!E44 -> 332 | G20: =F20+'Income Statement'!F44 -> 415 | H20: =G20+'Income Statement'!G44 -> 498 | I20: =H20+'Income Statement'!H44 -> 581 | J20: =I20+'Income Statement'!I44 -> 664 | K20: =J20+'Income Statement'!J44 -> 747 | ... N20: =M20+'Income Statement'!M44 -> 996 | O20: =N20+'Income Statement'!O44 -> 1079 | P20: =O20+'Income Statement'!P44 -> 1162 | Q20: =P20+'Income Statement'!Q44 -> 1245 | R20: =Q20+'Income Statement'!R44 -> 1328 | S20: =R20+'Income Statement'!S44 -> 1411 | T20: =S20+'Income Statement'!T44 -> 1494 | U20: =T20+'Income Statement'!U44 -> 1577 | V20: =U20+'Income Statement'!V44 -> 1660 | ... Z20: =Y20+'Income Statement'!Z44 -> 1992 | AA20: =Z20+'Income Statement'!AB44 -> 2242 | AB20: =AA20+'Income Statement'!AC44 -> 2492 | AC20: =AB20+'Income Statement'!AD44 -> 2742 | AD20: =AC20+'Income Statement'!AE44 -> 2992 | AE20: =AD20+'Income Statement'!AG44 -> 3242 | AF20: =AE20+'Income Statement'!AH44 -> 3492 | AG20: =AF20+'Income Statement'!AI44 -> 3742 | AH20: =AG20+'Income Statement'!AJ44 -> 3992 | AI20: =AH20+'Income Statement'!AL44 -> 4992
B21: Net Intangible Assets | C21: =C19-C20 -> 19917 | D21: =D19-D20 -> 19834 | E21: =E19-E20 -> 19751 | F21: =F19-F20 -> 19668 | G21: =G19-G20 -> 19585 | H21: =H19-H20 -> 19502 | I21: =I19-I20 -> 19419 | J21: =J19-J20 -> 19336 | ... AI21: =AI19-AI20 -> 15008
A23: Total Non-Current Assets | C23: =C17+C21 -> 68100 | D23: =D17+D21 -> 67200 | E23: =E17+E21 -> 66300 | F23: =F17+F21 -> 65400 | G23: =G17+G21 -> 64500 | H23: =H17+H21 -> 63600 | I23: =I17+I21 -> 62700 | J23: =J17+J21 -> 61800 | ... AI23: =AI17+AI21 -> 30508
A25: Total Assets | C25: =C12+C23 -> 611558 | D25: =D12+D23 -> 573116 | E25: =E12+E23 -> 534674 | F25: =F12+F23 -> 496232 | G25: =G12+G23 -> 457790 | H25: =H12+H23 -> 419348 | I25: =I12+I23 -> 399690 | J25: =J12+J23 -> 369637 | ... AI25: =AI12+AI23 -> 8763851.4
A28: Liabilities:
A29: Current Liabilities
B30: Accounts Payable | C30: ='Balance Sheet Assumptions'!$B$14*'Income Statement'!B31 -> 0 | D30: ='Balance Sheet Assumptions'!$B$14*'Income Statement'!C31 -> 0 | E30: ='Balance Sheet Assumptions'!$B$14*'Income Statement'!D31 -> 0 | F30: ='Balance Sheet Assumptions'!$B$14*'Income Statement'!E31 -> 0 | G30: ='Balance Sheet Assumptions'!$B$14*'Income Statement'!F31 -> 0 | H30: ='Balance Sheet Assumptions'!$B$14*'Income Statement'!G31 -> 0 | I30: ='Balance Sheet Assumptions'!$B$14*'Income Statement'!H31 -> 7974 | J30: ='Balance Sheet Assumptions'!$B$14*'Income Statement'!I31 -> 8181 | ... N30: ='Balance Sheet Assumptions'!$B$14*'Income Statement'!M31 -> 15300 | O30: ='Balance Sheet Assumptions'!$B$14*'Income Statement'!O31 -> 17248.2 | P30: ='Balance Sheet Assumptions'!$B$14*'Income Statement'!P31 -> 19401 | Q30: ='Balance Sheet Assumptions'!$B$14*'Income Statement'!Q31 -> 21826.8 | R30: ='Balance Sheet Assumptions'!$B$14*'Income Statement'!R31 -> 24554.4 | S30: ='Balance Sheet Assumptions'!$B$14*'Income Statement'!S31 -> 27624.6 | T30: ='Balance Sheet Assumptions'!$B$14*'Income Statement'!T31 -> 31080 | U30: ='Balance Sheet Assumptions'!$B$14*'Income Statement'!U31 -> 34966.8 | V30: ='Balance Sheet Assumptions'!$B$14*'Income Statement'!V31 -> 39339.6 | ... Z30: ='Balance Sheet Assumptions'!$B$14*'Income Statement'!Z31 -> 63021 | AA30: =ROUND((('Balance Sheet Assumptions'!$B$14*'Income Statement'!AB31)/3),0) -> 72175 | AB30: =ROUND((('Balance Sheet Assumptions'!$B$14*'Income Statement'!AC31)/3),0) -> 90219 | AC30: =ROUND((('Balance Sheet Assumptions'!$B$14*'Income Statement'!AD31)/3),0) -> 112775 | AD30: =ROUND((('Balance Sheet Assumptions'!$B$14*'Income Statement'!AE31)/3),0) -> 140970 | AE30: =ROUND((('Balance Sheet Assumptions'!$B$14*'Income Statement'!AG31)/3),0) -> 165739 | AF30: =ROUND((('Balance Sheet Assumptions'!$B$14*'Income Statement'!AH31)/3),0) -> 190600 | AG30: =ROUND((('Balance Sheet Assumptions'!$B$14*'Income Statement'!AI31)/3),0) -> 219189 | AH30: =ROUND((('Balance Sheet Assumptions'!$B$14*'Income Statement'!AJ31)/3),0) -> 252068 | AI30: =ROUND((('Balance Sheet Assumptions'!$B$14*'Income Statement'!AL31)/12),0) -> 279646
B31: Other Current Liabilities | C31: 0 | D31: 0 | E31: 0 | F31: 0 | G31: 0 | H31: 0 | I31: 0 | J31: 0 | K31: 0 | L31: 0 | M31: 0 | N31: 0 | O31: 0 | P31: 0 | Q31: 0 | R31: 0 | S31: 0 | T31: 0 | U31: 0 | V31: 0 | W31: 0 | X31: 0 | Y31: 0 | Z31: 0 | AA31: 0 | AB31: 0 | AC31: 0 | AD31: 0 | AE31: 0 | AF31: 0 | AG31: 0 | AH31: 0 | AI31: 0
A32: Total Current Liabilities | C32: =SUM(C30:C31) -> 0 | D32: =SUM(D30:D31) -> 0 | E32: =SUM(E30:E31) -> 0 | F32: =SUM(F30:F31) -> 0 | G32: =SUM(G30:G31) -> 0 | H32: =SUM(H30:H31) -> 0 | I32: =SUM(I30:I31) -> 7974 | J32: =SUM(J30:J31) -> 8181 | ... AI32: =SUM(AI30:AI31) -> 279646
A34: Non-Current Liabilities
B35: Other Long Term Liabilities | C35: 0 | D35: 0 | E35: 0 | F35: 0 | G35: 0 | H35: 0 | I35: 0 | J35: 0 | K35: 0 | L35: 0 | M35: 0 | N35: 0 | O35: 0 | P35: 0 | Q35: 0 | R35: 0 | S35: 0 | T35: 0 | U35: 0 | V35: 0 | W35: 0 | X35: 0 | Y35: 0 | Z35: 0 | AA35: 0 | AB35: 0 | AC35: 0 | AD35: 0 | AE35: 0 | AF35: 0 | AG35: 0 | AH35: 0 | AI35: 0
A37: Total Liabilties | C37: =C32+C35 -> 0 | D37: =D32+D35 -> 0 | E37: =E32+E35 -> 0 | F37: =F32+F35 -> 0 | G37: =G32+G35 -> 0 | H37: =H32+H35 -> 0 | I37: =I32+I35 -> 7974 | J37: =J32+J35 -> 8181 | ... AI37: =AI32+AI35 -> 279646
A39: Owners' Equity
B40: Founders' Investment | C40: ='Balance Sheet Assumptions'!B19 -> 100000 | D40: =C40 -> 100000 | E40: =D40 -> 100000 | F40: =E40 -> 100000 | G40: =F40 -> 100000 | H40: =G40 -> 100000 | I40: =H40 -> 100000 | J40: =I40 -> 100000 | K40: =J40 -> 100000 | ... AI40: =AH40 -> 100000
B41: Angel Investor's Investment | C41: ='Balance Sheet Assumptions'!B20 -> 675000 | D41: =C41 -> 675000 | E41: =D41 -> 675000 | F41: =E41 -> 675000 | G41: =F41 -> 675000 | H41: =G41 -> 675000 | I41: =H41 -> 675000 | J41: =I41 -> 675000 | K41: =J41 -> 675000 | ... AI41: =AH41 -> 675000
B42: Retained Earnings | C42: ='Statement of Retained Earnings'!B9 -> -163442 | D42: ='Statement of Retained Earnings'!C9 -> -201884 | E42: ='Statement of Retained Earnings'!D9 -> -240326 | F42: ='Statement of Retained Earnings'!E9 -> -278768 | G42: ='Statement of Retained Earnings'!F9 -> -317210 | H42: ='Statement of Retained Earnings'!G9 -> -355652 | I42: ='Statement of Retained Earnings'!H9 -> -383284 | J42: ='Statement of Retained Earnings'!I9 -> -413544 | ... AI42: ='Statement of Retained Earnings'!AH9 -> 7709205.4
A43: Total Owners' Equity | C43: =SUM(C39:C42) -> 611558 | D43: =SUM(D39:D42) -> 573116 | E43: =SUM(E39:E42) -> 534674 | F43: =SUM(F39:F42) -> 496232 | G43: =SUM(G39:G42) -> 457790 | H43: =SUM(H39:H42) -> 419348 | I43: =SUM(I39:I42) -> 391716 | J43: =SUM(J39:J42) -> 361456 | ... AI43: =SUM(AI39:AI42) -> 8484205.4
A45: Total Liabilties & Owners' Equity | C45: =C37+C43 -> 611558 | D45: =D37+D43 -> 573116 | E45: =E37+E43 -> 534674 | F45: =F37+F43 -> 496232 | G45: =G37+G43 -> 457790 | H45: =H37+H43 -> 419348 | I45: =I37+I43 -> 399690 | J45: =J37+J43 -> 369637 | ... AI45: =AI37+AI43 -> 8763851.4
C48: =C25-C45 -> 0 | D48: =D25-D45 -> 0 | E48: =E25-E45 -> 0 | F48: =F25-F45 -> 0 | G48: =G25-G45 -> 0 | H48: =H25-H45 -> 0 | I48: =I25-I45 -> 0 | J48: =J25-J45 -> 0 | ... AI48: =AI25-AI45 -> 0

Sheet Cash Flow Statement
B1: Company Name | O1: =B1 -> Company Name | AB1: =O1 -> Company Name
B2: Cash Flow Statement | O2: Cash Flow Statement | AB2: Cash Flow Statement
B4: Year 1 | O4: Year 2 | AB4: Year 3 | AG4: Year 4 | AL4: Year 5
A5: Operations | B5: January | C5: February | D5: March | E5: April | F5: May | G5: June | H5: July | I5: August | J5: September | K5: October | L5: November | M5: December | N5: Total | O5: January | P5: February | Q5: March | R5: April | S5: May | T5: June | U5: July | V5: August | W5: September | X5: October | Y5: November | Z5: December | AA5: Total | AB5: Quarter 1 | AC5: Quarter 2 | AD5: Quarter 3 | AE5: Quarter 4 | AF5: Total | AG5: Quarter 1 | AH5: Quarter 2 | AI5: Quarter 3 | AJ5: Quarter 4 | AK5: Total | AL5: Total
A7: Net Income | B7: ='Income Statement'!B67 -> -163442 | C7: ='Income Statement'!C67 -> -38442 | D7: ='Income Statement'!D67 -> -38442 | E7: ='Income Statement'!E67 -> -38442 | F7: ='Income Statement'!F67 -> -38442 | G7: ='Income Statement'!G67 -> -38442 | H7: ='Income Statement'!H67 -> -27632 | I7: ='Income Statement'!I67 -> -30260 | ... M7: ='Income Statement'!M67 -> -18275 | N7: =SUM(B7:M7) -> -503586.5 | O7: ='Income Statement'!O67 -> -19926 | P7: ='Income Statement'!P67 -> -16632 | Q7: ='Income Statement'!Q67 -> -12923 | R7: ='Income Statement'!R67 -> -8747 | S7: ='Income Statement'!S67 -> -4054 | T7: ='Income Statement'!T67 -> 1237 | U7: ='Income Statement'!U67 -> 7183 | V7: ='Income Statement'!V67 -> 13875 | ... Z7: ='Income Statement'!Z67 -> 50120 | AA7: =SUM(O7:Z7) -> 100819 | AB7: ='Income Statement'!AB67 -> 222087 | AC7: ='Income Statement'!AC67 -> 275421.65 | AD7: ='Income Statement'!AD67 -> 303421.3 | AE7: ='Income Statement'!AE67 -> 406167.3 | AF7: ='Income Statement'!AF67 -> 1207097.2 | AG7: ='Income Statement'!AG67 -> 557760 | AH7: ='Income Statement'!AH67 -> 659092 | AI7: ='Income Statement'!AI67 -> 775621 | ... AL7: ='Income Statement'!AL67 -> 4002769.4
A8: ='Income Statement'!A43 -> Depreciation Expense | B8: ='Income Statement'!B43 -> 817 | C8: ='Income Statement'!C43 -> 817 | D8: ='Income Statement'!D43 -> 817 | E8: ='Income Statement'!E43 -> 817 | F8: ='Income Statement'!F43 -> 817 | G8: ='Income Statement'!G43 -> 817 | H8: ='Income Statement'!H43 -> 817 | ... M8: ='Income Statement'!M43 -> 817 | N8: =SUM(B8:M8) -> 9804 | O8: ='Income Statement'!O43 -> 858 | P8: ='Income Statement'!P43 -> 858 | Q8: ='Income Statement'!Q43 -> 858 | R8: ='Income Statement'!R43 -> 858 | S8: ='Income Statement'!S43 -> 858 | T8: ='Income Statement'!T43 -> 858 | U8: ='Income Statement'!U43 -> 858 | V8: ='Income Statement'!V43 -> 858 | ... Z8: ='Income Statement'!Z43 -> 858 | AA8: =SUM(O8:Z8) -> 10296 | AB8: ='Income Statement'!AB43 -> 2800 | AC8: ='Income Statement'!AC43 -> 2800 | AD8: ='Income Statement'!AD43 -> 2800 | AE8: ='Income Statement'!AE43 -> 2800 | AF8: ='Income Statement'!AF43 -> 11200 | AG8: ='Income Statement'!AG43 -> 3600 | AH8: ='Income Statement'!AH43 -> 3600 | AI8: ='Income Statement'!AI43 -> 3600 | ... AL8: ='Income Statement'!AL43 -> 15300
A9: ='Income Statement'!A44 -> Amortization Expense | B9: ='Income Statement'!B44 -> 83 | C9: ='Income Statement'!C44 -> 83 | D9: ='Income Statement'!D44 -> 83 | E9: ='Income Statement'!E44 -> 83 | F9: ='Income Statement'!F44 -> 83 | G9: ='Income Statement'!G44 -> 83 | H9: ='Income Statement'!H44 -> 83 | ... M9: ='Income Statement'!M44 -> 83 | N9: =SUM(B9:M9) -> 996 | O9: ='Income Statement'!O44 -> 83 | P9: ='Income Statement'!P44 -> 83 | Q9: ='Income Statement'!Q44 -> 83 | R9: ='Income Statement'!R44 -> 83 | S9: ='Income Statement'!S44 -> 83 | T9: ='Income Statement'!T44 -> 83 | U9: ='Income Statement'!U44 -> 83 | V9: ='Income Statement'!V44 -> 83 | ... Z9: ='Income Statement'!Z44 -> 83 | AA9: =SUM(O9:Z9) -> 996 | AB9: ='Income Statement'!AB44 -> 250 | AC9: ='Income Statement'!AC44 -> 250 | AD9: ='Income Statement'!AD44 -> 250 | AE9: ='Income Statement'!AE44 -> 250 | AF9: ='Income Statement'!AF44 -> 1000 | AG9: ='Income Statement'!AG44 -> 250 | AH9: ='Income Statement'!AH44 -> 250 | AI9: ='Income Statement'!AI44 -> 250 | ... AL9: ='Income Statement'!AL44 -> 1000
A10: (Inc/Dec) in A/R | B10: =0-'Balance Sheet'!C9 -> 0 | C10: ='Balance Sheet'!C9-'Balance Sheet'!D9 -> 0 | D10: ='Balance Sheet'!D9-'Balance Sheet'!E9 -> 0 | E10: ='Balance Sheet'!E9-'Balance Sheet'!F9 -> 0 | F10: ='Balance Sheet'!F9-'Balance Sheet'!G9 -> 0 | G10: ='Balance Sheet'!G9-'Balance Sheet'!H9 -> 0 | H10: ='Balance Sheet'!H9-'Balance Sheet'!I9 -> -12050 | I10: ='Balance Sheet'!I9-'Balance Sheet'!J9 -> -525 | J10: ='Balance Sheet'!J9-'Balance Sheet'!K9 -> -3925 | ... M10: ='Balance Sheet'!M9-'Balance Sheet'!N9 -> -3800 | N10: =0-'Balance Sheet'!N9 -> -24500 | O10: ='Balance Sheet'!N9-'Balance Sheet'!O9 -> -3070 | P10: ='Balance Sheet'!O9-'Balance Sheet'!P9 -> -3441 | Q10: ='Balance Sheet'!P9-'Balance Sheet'!Q9 -> -3876 | R10: ='Balance Sheet'!Q9-'Balance Sheet'!R9 -> -4361 | S10: ='Balance Sheet'!R9-'Balance Sheet'!S9 -> -4905 | T10: ='Balance Sheet'!S9-'Balance Sheet'!T9 -> -5525 | U10: ='Balance Sheet'!T9-'Balance Sheet'!U9 -> -6212 | V10: ='Balance Sheet'!U9-'Balance Sheet'!V9 -> -6990 | ... Z10: ='Balance Sheet'!Y9-'Balance Sheet'!Z9 -> -11198 | AA10: ='Balance Sheet'!N9-'Balance Sheet'!Z9 -> -76237 | AB10: ='Balance Sheet'!Z9-'Balance Sheet'!AA9 -> -22034 | AC10: ='Balance Sheet'!AA9-'Balance Sheet'!AB9 -> -30693 | AD10: ='Balance Sheet'!AB9-'Balance Sheet'!AC9 -> -38369 | AE10: ='Balance Sheet'!AC9-'Balance Sheet'!AD9 -> -47959 | AF10: ='Balance Sheet'!Z9-'Balance Sheet'!AD9 -> -139055 | AG10: ='Balance Sheet'!AD9-'Balance Sheet'!AE9 -> -59165 | AH10: ='Balance Sheet'!AE9-'Balance Sheet'!AF9 -> -44845 | AI10: ='Balance Sheet'!AF9-'Balance Sheet'!AG9 -> -51569 | AJ10: ='Balance Sheet'!AG9-'Balance Sheet'!AH9 -> -59307 | AK10: ='Balance Sheet'!AD9-'Balance Sheet'!AH9 -> -214886 | AL10: ='Balance Sheet'!AH9-'Balance Sheet'!AI9 -> -49307
A11: (Inc/Dec) in Inventory | B11: =0-'Balance Sheet'!C10 -> 0 | C11: ='Balance Sheet'!C10-'Balance Sheet'!D10 -> 0 | D11: ='Balance Sheet'!D10-'Balance Sheet'!E10 -> 0 | E11: ='Balance Sheet'!E10-'Balance Sheet'!F10 -> 0 | F11: ='Balance Sheet'!F10-'Balance Sheet'!G10 -> 0 | G11: ='Balance Sheet'!G10-'Balance Sheet'!H10 -> 0 | H11: ='Balance Sheet'!H10-'Balance Sheet'!I10 -> -5316 | I11: ='Balance Sheet'!I10-'Balance Sheet'!J10 -> -138 | J11: ='Balance Sheet'!J10-'Balance Sheet'!K10 -> -1551 | ... M11: ='Balance Sheet'!M10-'Balance Sheet'!N10 -> -1536 | N11: =0-'Balance Sheet'!N10 -> -10200 | O11: ='Balance Sheet'!N10-'Balance Sheet'!O10 -> -1299 | P11: ='Balance Sheet'!O10-'Balance Sheet'!P10 -> -1435 | Q11: ='Balance Sheet'!P10-'Balance Sheet'!Q10 -> -1617 | R11: ='Balance Sheet'!Q10-'Balance Sheet'!R10 -> -1819 | S11: ='Balance Sheet'!R10-'Balance Sheet'!S10 -> -2046 | T11: ='Balance Sheet'!S10-'Balance Sheet'!T10 -> -2304 | U11: ='Balance Sheet'!T10-'Balance Sheet'!U10 -> -2591 | V11: ='Balance Sheet'!U10-'Balance Sheet'!V10 -> -2915 | ... Z11: ='Balance Sheet'!Y10-'Balance Sheet'!Z10 -> -4670 | AA11: ='Balance Sheet'!N10-'Balance Sheet'!Z10 -> -31814 | AB11: ='Balance Sheet'!Z10-'Balance Sheet'!AA10 -> -6103 | AC11: ='Balance Sheet'!AA10-'Balance Sheet'!AB10 -> -12029 | AD11: ='Balance Sheet'!AB10-'Balance Sheet'!AC10 -> -15037 | AE11: ='Balance Sheet'!AC10-'Balance Sheet'!AD10 -> -18797 | AF11: ='Balance Sheet'!Z10-'Balance Sheet'!AD10 -> -51966 | AG11: ='Balance Sheet'!AD10-'Balance Sheet'!AE10 -> -16512 | AH11: ='Balance Sheet'!AE10-'Balance Sheet'!AF10 -> -16575 | AI11: ='Balance Sheet'!AF10-'Balance Sheet'!AG10 -> -19059 | AJ11: ='Balance Sheet'!AG10-'Balance Sheet'!AH10 -> -21919 | AK11: ='Balance Sheet'!AD10-'Balance Sheet'!AH10 -> -74065 | AL11: ='Balance Sheet'!AH10-'Balance Sheet'!AI10 -> -18386
A12: (Inc/Dec) in A/P | B12: ='Balance Sheet'!C30-0 -> 0 | C12: ='Balance Sheet'!D30-'Balance Sheet'!C30 -> 0 | D12: ='Balance Sheet'!E30-'Balance Sheet'!D30 -> 0 | E12: ='Balance Sheet'!F30-'Balance Sheet'!E30 -> 0 | F12: ='Balance Sheet'!G30-'Balance Sheet'!F30 -> 0 | G12: ='Balance Sheet'!H30-'Balance Sheet'!G30 -> 0 | H12: ='Balance Sheet'!I30-'Balance Sheet'!H30 -> 7974 | I12: ='Balance Sheet'!J30-'Balance Sheet'!I30 -> 207 | J12: ='Balance Sheet'!K30-'Balance Sheet'!J30 -> 2326.5 | ... M12: ='Balance Sheet'!N30-'Balance Sheet'!M30 -> 2304 | N12: ='Balance Sheet'!N30-0 -> 15300 | O12: ='Balance Sheet'!O30-'Balance Sheet'!N30 -> 1948.2 | P12: ='Balance Sheet'!P30-'Balance Sheet'!O30 -> 2152.8 | Q12: ='Balance Sheet'!Q30-'Balance Sheet'!P30 -> 2425.8 | R12: ='Balance Sheet'!R30-'Balance Sheet'!Q30 -> 2727.6 | S12: ='Balance Sheet'!S30-'Balance Sheet'!R30 -> 3070.2 | T12: ='Balance Sheet'!T30-'Balance Sheet'!S30 -> 3455.4 | U12: ='Balance Sheet'!U30-'Balance Sheet'!T30 -> 3886.8 | V12: ='Balance Sheet'!V30-'Balance Sheet'!U30 -> 4372.8 | ... Z12: ='Balance Sheet'!Z30-'Balance Sheet'!Y30 -> 7005.6 | AA12: ='Balance Sheet'!Z30-'Balance Sheet'!N30 -> 47721 | AB12: ='Balance Sheet'!AA30-'Balance Sheet'!Z30 -> 9154 | AC12: ='Balance Sheet'!AB30-'Balance Sheet'!AA30 -> 18044 | AD12: ='Balance Sheet'!AC30-'Balance Sheet'!AB30 -> 22556 | AE12: ='Balance Sheet'!AD30-'Balance Sheet'!AC30 -> 28195 | AF12: ='Balance Sheet'!AD30-'Balance Sheet'!Z30 -> 77949 | AG12: ='Balance Sheet'!AE30-'Balance Sheet'!AD30 -> 24769 | AH12: ='Balance Sheet'!AF30-'Balance Sheet'!AE30 -> 24861 | AI12: ='Balance Sheet'!AG30-'Balance Sheet'!AF30 -> 28589 | AJ12: ='Balance Sheet'!AH30-'Balance Sheet'!AG30 -> 32879 | AK12: ='Balance Sheet'!AH30-'Balance Sheet'!AD30 -> 111098 | AL12: ='Balance Sheet'!AI30-'Balance Sheet'!AH30 -> 27578
A14: Net Cash Flow from Operations | B14: =SUM(B7:B13) -> -162542 | C14: =SUM(C7:C13) -> -37542 | D14: =SUM(D7:D13) -> -37542 | E14: =SUM(E7:E13) -> -37542 | F14: =SUM(F7:F13) -> -37542 | G14: =SUM(G7:G13) -> -37542 | H14: =SUM(H7:H13) -> -36124 | I14: =SUM(I7:I13) -> -29816 | ... AL14: =SUM(AL7:AL13) -> 3978954.4
A17: Investing Activities
A18: Cash Paid for Fixed Assets | B18: =-'Balance Sheet'!C15 -> -49000 | C18: ='Balance Sheet'!C15-'Balance Sheet'!D15 -> 0 | D18: ='Balance Sheet'!D15-'Balance Sheet'!E15 -> 0 | E18: ='Balance Sheet'!E15-'Balance Sheet'!F15 -> 0 | F18: ='Balance Sheet'!F15-'Balance Sheet'!G15 -> 0 | G18: ='Balance Sheet'!G15-'Balance Sheet'!H15 -> 0 | H18: ='Balance Sheet'!H15-'Balance Sheet'!I15 -> 0 | I18: ='Balance Sheet'!I15-'Balance Sheet'!J15 -> 0 | J18: ='Balance Sheet'!J15-'Balance Sheet'!K15 -> 0 | ... M18: ='Balance Sheet'!M15-'Balance Sheet'!N15 -> 0 | N18: =SUM(B18:M18) -> -49000 | O18: ='Balance Sheet'!N15-'Balance Sheet'!O15 -> -2500 | P18: ='Balance Sheet'!O15-'Balance Sheet'!P15 -> 0 | Q18: ='Balance Sheet'!P15-'Balance Sheet'!Q15 -> 0 | R18: ='Balance Sheet'!Q15-'Balance Sheet'!R15 -> 0 | S18: ='Balance Sheet'!R15-'Balance Sheet'!S15 -> 0 | T18: ='Balance Sheet'!S15-'Balance Sheet'!T15 -> 0 | U18: ='Balance Sheet'!T15-'Balance Sheet'!U15 -> 0 | V18: ='Balance Sheet'!U15-'Balance Sheet'!V15 -> 0 | ... Z18: ='Balance Sheet'!Y15-'Balance Sheet'!Z15 -> 0 | AA18: =SUM(O18:Z18) -> -2500 | AB18: ='Balance Sheet'!Z15-'Balance Sheet'!AA15 -> -4500 | AC18: ='Balance Sheet'!AA15-'Balance Sheet'!AB15 -> 0 | AD18: ='Balance Sheet'!AB15-'Balance Sheet'!AC15 -> 0 | AE18: ='Balance Sheet'!AC15-'Balance Sheet'!AD15 -> 0 | AF18: =SUM(AB18:AE18) -> -4500 | AG18: ='Balance Sheet'!AD15-'Balance Sheet'!AE15 -> -16000 | AH18: ='Balance Sheet'!AE15-'Balance Sheet'!AF15 -> 0 | AI18: ='Balance Sheet'!AF15-'Balance Sheet'!AG15 -> 0 | AJ18: ='Balance Sheet'!AG15-'Balance Sheet'!AH15 -> 0 | AK18: =SUM(AG18:AJ18) -> -16000 | AL18: ='Balance Sheet'!AH15-'Balance Sheet'!AI15 -> -4500
A19: Cash Paid for Intangible Assets | B19: =-'Balance Sheet'!C19 -> -20000 | C19: ='Balance Sheet'!C19-'Balance Sheet'!D19 -> 0 | D19: ='Balance Sheet'!D19-'Balance Sheet'!E19 -> 0 | E19: ='Balance Sheet'!E19-'Balance Sheet'!F19 -> 0 | F19: ='Balance Sheet'!F19-'Balance Sheet'!G19 -> 0 | G19: ='Balance Sheet'!G19-'Balance Sheet'!H19 -> 0 | H19: ='Balance Sheet'!H19-'Balance Sheet'!I19 -> 0 | I19: ='Balance Sheet'!I19-'Balance Sheet'!J19 -> 0 | J19: ='Balance Sheet'!J19-'Balance Sheet'!K19 -> 0 | ... M19: ='Balance Sheet'!M19-'Balance Sheet'!N19 -> 0 | N19: =SUM(B19:M19) -> -20000 | O19: ='Balance Sheet'!N19-'Balance Sheet'!O19 -> 0 | P19: ='Balance Sheet'!O19-'Balance Sheet'!P19 -> 0 | Q19: ='Balance Sheet'!P19-'Balance Sheet'!Q19 -> 0 | R19: ='Balance Sheet'!Q19-'Balance Sheet'!R19 -> 0 | S19: ='Balance Sheet'!R19-'Balance Sheet'!S19 -> 0 | T19: ='Balance Sheet'!S19-'Balance Sheet'!T19 -> 0 | U19: ='Balance Sheet'!T19-'Balance Sheet'!U19 -> 0 | V19: ='Balance Sheet'!U19-'Balance Sheet'!V19 -> 0 | ... Z19: ='Balance Sheet'!Y19-'Balance Sheet'!Z19 -> 0 | AA19: =SUM(O19:Z19) -> 0 | AB19: ='Balance Sheet'!Z19-'Balance Sheet'!AA19 -> 0 | AC19: ='Balance Sheet'!AA19-'Balance Sheet'!AB19 -> 0 | AD19: ='Balance Sheet'!AB19-'Balance Sheet'!AC19 -> 0 | AE19: ='Balance Sheet'!AC19-'Balance Sheet'!AD19 -> 0 | AF19: =SUM(AB19:AE19) -> 0 | AG19: ='Balance Sheet'!AD19-'Balance Sheet'!AE19 -> 0 | AH19: ='Balance Sheet'!AE19-'Balance Sheet'!AF19 -> 0 | AI19: ='Balance Sheet'!AF19-'Balance Sheet'!AG19 -> 0 | AJ19: ='Balance Sheet'!AG19-'Balance Sheet'!AH19 -> 0 | AK19: =SUM(AG19:AJ19) -> 0 | AL19: ='Balance Sheet'!AH19-'Balance Sheet'!AI19 -> 0
A21: Net Cash Flow from Investing | B21: =SUM(B18:B19) -> -69000 | C21: =SUM(C18:C19) -> 0 | D21: =SUM(D18:D19) -> 0 | E21: =SUM(E18:E19) -> 0 | F21: =SUM(F18:F19) -> 0 | G21: =SUM(G18:G19) -> 0 | H21: =SUM(H18:H19) -> 0 | I21: =SUM(I18:I19) -> 0 | ... AL21: =SUM(AL18:AL19) -> -4500
A24: Financing Activities
A25: Cash from Founders | B25: ='Balance Sheet'!C40 -> 100000 | C25: ='Balance Sheet'!C40-'Balance Sheet'!D40 -> 0 | D25: ='Balance Sheet'!D40-'Balance Sheet'!E40 -> 0 | E25: ='Balance Sheet'!E40-'Balance Sheet'!F40 -> 0 | F25: ='Balance Sheet'!F40-'Balance Sheet'!G40 -> 0 | G25: ='Balance Sheet'!G40-'Balance Sheet'!H40 -> 0 | H25: ='Balance Sheet'!H40-'Balance Sheet'!I40 -> 0 | I25: ='Balance Sheet'!I40-'Balance Sheet'!J40 -> 0 | J25: ='Balance Sheet'!J40-'Balance Sheet'!K40 -> 0 | ... M25: ='Balance Sheet'!M40-'Balance Sheet'!N40 -> 0 | N25: =SUM(B25:M25) -> 100000 | O25: ='Balance Sheet'!O40-'Balance Sheet'!N40 -> 0 | P25: ='Balance Sheet'!P40-'Balance Sheet'!O40 -> 0 | Q25: ='Balance Sheet'!Q40-'Balance Sheet'!P40 -> 0 | R25: ='Balance Sheet'!R40-'Balance Sheet'!Q40 -> 0 | S25: ='Balance Sheet'!S40-'Balance Sheet'!R40 -> 0 | T25: ='Balance Sheet'!T40-'Balance Sheet'!S40 -> 0 | U25: ='Balance Sheet'!U40-'Balance Sheet'!T40 -> 0 | V25: ='Balance Sheet'!V40-'Balance Sheet'!U40 -> 0 | ... Z25: ='Balance Sheet'!Z40-'Balance Sheet'!Y40 -> 0 | AA25: =SUM(O25:Z25) -> 0 | AB25: =SUM(P25:AA25) -> 0 | AC25: =SUM(Q25:AB25) -> 0 | AD25: =SUM(R25:AC25) -> 0 | AE25: =SUM(S25:AD25) -> 0 | AF25: =SUM(T25:AE25) -> 0 | AG25: =SUM(U25:AF25) -> 0 | AH25: =SUM(V25:AG25) -> 0 | ... AL25: =SUM(Z25:AK25) -> 0
A26: Cash from Angel Investor | B26: ='Balance Sheet'!C41 -> 675000 | C26: ='Balance Sheet'!C41-'Balance Sheet'!D41 -> 0 | D26: ='Balance Sheet'!D41-'Balance Sheet'!E41 -> 0 | E26: ='Balance Sheet'!E41-'Balance Sheet'!F41 -> 0 | F26: ='Balance Sheet'!F41-'Balance Sheet'!G41 -> 0 | G26: ='Balance Sheet'!G41-'Balance Sheet'!H41 -> 0 | H26: ='Balance Sheet'!H41-'Balance Sheet'!I41 -> 0 | I26: ='Balance Sheet'!I41-'Balance Sheet'!J41 -> 0 | J26: ='Balance Sheet'!J41-'Balance Sheet'!K41 -> 0 | ... M26: ='Balance Sheet'!M41-'Balance Sheet'!N41 -> 0 | N26: =SUM(B26:M26) -> 675000 | O26: ='Balance Sheet'!O41-'Balance Sheet'!N41 -> 0 | P26: ='Balance Sheet'!P41-'Balance Sheet'!O41 -> 0 | Q26: ='Balance Sheet'!Q41-'Balance Sheet'!P41 -> 0 | R26: ='Balance Sheet'!R41-'Balance Sheet'!Q41 -> 0 | S26: ='Balance Sheet'!S41-'Balance Sheet'!R41 -> 0 | T26: ='Balance Sheet'!T41-'Balance Sheet'!S41 -> 0 | U26: ='Balance Sheet'!U41-'Balance Sheet'!T41 -> 0 | V26: ='Balance Sheet'!V41-'Balance Sheet'!U41 -> 0 | ... Z26: ='Balance Sheet'!Z41-'Balance Sheet'!Y41 -> 0 | AA26: =SUM(O26:Z26) -> 0 | AB26: =SUM(P26:AA26) -> 0 | AC26: =SUM(Q26:AB26) -> 0 | AD26: =SUM(R26:AC26) -> 0 | AE26: =SUM(S26:AD26) -> 0 | AF26: =SUM(T26:AE26) -> 0 | AG26: =SUM(U26:AF26) -> 0 | AH26: =SUM(V26:AG26) -> 0 | ... AL26: =SUM(Z26:AK26) -> 0
A27: Dividends to Shareholders | B27: 0 | C27: 0 | D27: 0 | E27: 0 | F27: 0 | G27: 0 | H27: 0 | I27: 0 | J27: 0 | K27: 0 | L27: 0 | M27: 0 | N27: =SUM(B27:M27) -> 0 | O27: 0 | P27: 0 | Q27: 0 | R27: 0 | S27: 0 | T27: 0 | U27: 0 | V27: 0 | W27: 0 | X27: 0 | Y27: 0 | Z27: 0 | AA27: =SUM(O27:Z27) -> 0 | AB27: =SUM(P27:AA27) -> 0 | AC27: =SUM(Q27:AB27) -> 0 | AD27: =SUM(R27:AC27) -> 0 | AE27: =SUM(S27:AD27) -> 0 | AF27: =SUM(T27:AE27) -> 0 | AG27: =SUM(U27:AF27) -> 0 | AH27: =SUM(V27:AG27) -> 0 | ... AL27: =SUM(Z27:AK27) -> 0
A29: Net Cash Flow from Financing | B29: =B25+B26-B27 -> 775000 | C29: =C25+C26-C27 -> 0 | D29: =D25+D26-D27 -> 0 | E29: =E25+E26-E27 -> 0 | F29: =F25+F26-F27 -> 0 | G29: =G25+G26-G27 -> 0 | H29: =H25+H26-H27 -> 0 | I29: =I25+I26-I27 -> 0 | ... AL29: =AL25+AL26-AL27 -> 0
A31: Net Change in Cash | B31: =B14+B21+B29 -> 543458 | C31: =C14+C21+C29 -> -37542 | D31: =D14+D21+D29 -> -37542 | E31: =E14+E21+E29 -> -37542 | F31: =F14+F21+F29 -> -37542 | G31: =G14+G21+G29 -> -37542 | H31: =H14+H21+H29 -> -36124 | I31: =I14+I21+I29 -> -29816 | ... AL31: =AL14+AL21+AL29 -> 3974454.4
A33: Beginning Cash Balance | B33: 0 | C33: =B35 -> 543458 | D33: =C35 -> 505916 | E33: =D35 -> 468374 | F33: =E35 -> 430832 | G33: =F35 -> 393290 | H33: =G35 -> 355748 | I33: =H35 -> 319624 | J33: =I35 -> 289808 | ... M33: =L35 -> 214220.5 | N33: =B33 -> 0 | O33: =N35 -> 193813.5 | P33: =O35 -> 169907.7 | Q33: =P35 -> 151493.5 | R33: =Q35 -> 136444.3 | S33: =R35 -> 125185.9 | T33: =S35 -> 118192.1 | U33: =T35 -> 115996.5 | V33: =U35 -> 119204.3 | ... Z33: =Y35 -> 200895.9 | AA33: =N35 -> 193813.5 | AB33: =AA35 -> 243094.5 | AC33: =AB35 -> 444748.5 | AD33: =AC35 -> 698542.15 | AE33: =AD35 -> 974163.45 | AF33: =AB33 -> 243094.5 | AG33: =AF35 -> 1344819.8 | AH33: =AG35 -> 1839521.8 | AI33: =AH35 -> 2465904.8 | AJ33: =AI35 -> 3203336.8 | AK33: =AG33 -> 1344819.8 | AL33: =AK35 -> 4068473
A35: Ending Cash Balance | B35: =B31+B33 -> 543458 | C35: =C31+C33 -> 505916 | D35: =D31+D33 -> 468374 | E35: =E31+E33 -> 430832 | F35: =F31+F33 -> 393290 | G35: =G31+G33 -> 355748 | H35: =H31+H33 -> 319624 | I35: =I31+I33 -> 289808 | ... AL35: =AL31+AL33 -> 8042927.4
A39: Minimum Cash Reserve | B39: ='Balance Sheet Assumptions'!$B$3 -> 100000 | C39: ='Balance Sheet Assumptions'!$B$3 -> 100000 | D39: ='Balance Sheet Assumptions'!$B$3 -> 100000 | E39: ='Balance Sheet Assumptions'!$B$3 -> 100000 | F39: ='Balance Sheet Assumptions'!$B$3 -> 100000 | G39: ='Balance Sheet Assumptions'!$B$3 -> 100000 | H39: ='Balance Sheet Assumptions'!$B$3 -> 100000 | I39: ='Balance Sheet Assumptions'!$B$3 -> 100000 | ... AL39: ='Balance Sheet Assumptions'!$B$3 -> 100000
A41: Do we fall below the minimum? | B41: =IF(B35>B39,"NO", "YES") -> NO | C41: =IF(C35>C39,"NO", "YES") -> NO | D41: =IF(D35>D39,"NO", "YES") -> NO | E41: =IF(E35>E39,"NO", "YES") -> NO | F41: =IF(F35>F39,"NO", "YES") -> NO | G41: =IF(G35>G39,"NO", "YES") -> NO | H41: =IF(H35>H39,"NO", "YES") -> NO | I41: =IF(I35>I39,"NO", "YES") -> NO | ... AL41: =IF(AL35>AL39,"NO", "YES") -> NO

Sheet Valuation
B1: Company Name
B2: Valuation
C4: Year 0 | E4: Year 1 | G4: Year 2 | I4: Year 3 | K4: Year 4 | M4: Year 5 | O4: Horizon Value Year 5
A6: Initial Cash Outlay | C6: ='Cash Flow Statement'!N21 -> -69000
A8: Operating Cash Flow | E8: ='Cash Flow Statement'!N14 -> -512186.5 | G8: ='Cash Flow Statement'!AA14 -> 51781 | I8: ='Cash Flow Statement'!AF14 -> 1106225.2 | K8: ='Cash Flow Statement'!AK14 -> 2739653.2 | M8: ='Cash Flow Statement'!AL14 -> 3978954.4
A10: Capital Expenditures | G10: ='Cash Flow Statement'!AA21 -> -2500 | I10: ='Cash Flow Statement'!AF21 -> -4500 | K10: ='Cash Flow Statement'!AK21 -> -16000 | M10: ='Cash Flow Statement'!AL21 -> -4500
A12: Payments to Shareholders | E12: =-'Cash Flow Statement'!N27 -> 0 | G12: =-'Cash Flow Statement'!Z27 -> 0 | I12: =-'Cash Flow Statement'!AF27 -> 0 | K12: =-'Cash Flow Statement'!AK27 -> 0 | M12: =-'Cash Flow Statement'!AL27 -> 0
A14: Free Cash Flow | C14: =SUM(C6:C13) -> -69000 | E14: =SUM(E6:E13) -> -512186.5 | G14: =SUM(G6:G13) -> 49281 | I14: =SUM(I6:I13) -> 1101725.2 | K14: =SUM(K6:K13) -> 2723653.2 | M14: =SUM(M6:M13) -> 3974454.4 | O14: =ROUND((M14*(1+E25))/(C23-E25),0) -> 11923363
A16: Discounted Free Cash Flows | C16: =C14/(1+C23)^0 -> -69000 | E16: =E14/(1+$C$23)^1 -> -365847.5 | G16: =G14/(1+$C$23)^2 -> 25143.367 | I16: =I14/(1+$C$23)^3 -> 401503.37 | K16: =K14/(1+$C$23)^4 -> 708989.28 | M16: =M14/(1+$C$23)^5 -> 738987.92 | O16: =O14/(1+$C$23)^5 -> 2216963.7
A18: NPV | C18: =SUM(C16:O16) -> 3656740.2
A20: Dilution | C20: ='Balance Sheet'!C41/Valuation!C18 -> 0.18459064 | E20: 20-40% | I20: 250-1MM
A23: Discount Rate | C23: 0.4
A25: Estimated Long Term Industry Growth Rate | E25: 0.05
